Workbook
Name Liste: parameters!$A$2:$A$3
Name liste1: #REF!
Name liste2: #REF!
Name SOCIETE: parameters!$A$8:$A$55

Sheet read me
B1: INSTRUCTIONS FOR USE
B3: The aim of this document is to follow the orderbook per week.
B5: This document has to be sent each Friday afternoon to : | H5: dashboard@diaminter.com
B11: How to fill in the document :
C13: 1 | D13: Select the worksheet for the appropriate week
C15: 2 | D15: Fill in your company name in the cell G2
C17: 3 | D17: The current month corresponding to the week is automatically mentionned: please make sure to report data for this month (and not previous or next one when the week runs over two different months)
C19: 4 | D19: Column E : Fill in product name
C21: 5 | D21: Column F : Fill in customers statut (external or internal customers)
C23: 6 | D23: Column G : fill in the customers name
C25: 7 | D25: Please never correct the worksheet of a past week
C27: 8 | D27: You can update the pivot tables on the worksheet [analysis week] to see the detailed variations by customers in the orderbook from previous week to ongoing week
C29: 9 | D29: This is a synthesis of the orders taken and the sales invoiced during the year. Please update the YTD figures at the end of each months (yellow cells) to show the
B33: IMPORTANT : At the end of the month, orders not yet delivered, have to be automatically transferred to the next month.
D34: Once the orders have been invoiced (and so the amount is indicated as turnover), the orders should disappear of the table.

Sheet parameters
D1: Entity to select
A2: Group | D2: Diam India
A3: External
D4: =VLOOKUP(D2,$A$8:$C$52,3,FALSE) -> k€
A8: TO SELECT | B8: Automatic data
A9: Diam France | B9: DFR | C9: k€ | G9: W1 | H9: January | J9: January | K9: 46023
A10: Diam Lurcy | B10: DLU | C10: k€ | G10: W2 | H10: January | I10: W1 | J10: February | K10: 46054
A11: Diam Yzeure | B11: DYZ | C11: k€ | G11: W3 | H11: January | I11: W2 | J11: March | K11: 46082
A12: Diam Tunisie | B12: DTN | C12: k€ | G12: W4 | H12: January | I12: W3 | J12: April | K12: 46113
A13: Diam Tunisie Prestige | B13: DTP | C13: k€ | G13: W5 | H13: January | I13: W4 | J13: May | K13: 46143
A14: Diam Turkey | B14: DTK | C14: k€ | G14: W6 | H14: February | I14: W5 | J14: June | K14: 46174
A15: Diam Italy | B15: DIT | C15: k€ | G15: W7 | H15: February | I15: W6 | J15: July | K15: 46204
A16: Diam Prestige Europe | B16: PEM | C16: k€ | G16: W8 | H16: February | I16: W7 | J16: August | K16: 46235
A17: Diam UK | B17: DUK | C17: k£ | G17: W9 | H17: February | I17: W8 | J17: September | K17: 46266
A18: Fieldflex UK | B18: FFUK | C18: k£ | G18: W10 | H18: March | I18: W9 | J18: October | K18: 46296
A19: Diam Germany | B19: DEU | C19: k€ | G19: W11 | H19: March | I19: W10 | J19: November | K19: 46327
A20: Diam Poland | B20: DPO | C20: k€ | G20: W12 | H20: March | I20: W11 | J20: December | K20: 46357
A21: Diam Premium North America | B21: DPN | C21: k$ | G21: W13 | H21: March | I21: W12
A22: D 3 LLC | B22: D3 | C22: k$ | G22: W14 | H22: April | I22: W13
A23: CONEX US | B23: CNX | C23: k$ | G23: W15 | H23: April | I23: W14
A24: CONEX EU | B24: CNE | C24: k€ | G24: W16 | H24: April | I24: W15
A25: CONEX APAC | B25: CNA | C25: k$ | G25: W17 | H25: April | I25: W16
A26: PRUGENT US | B26: PUS | C26: k$ | G26: W18 | H26: April | I26: W17
A27: Fieldflex US | B27: FFUS | C27: k$ | G27: W19 | H27: May | I27: W18
A28: Back to Diam | B28: B2D | C28: k$ | G28: W20 | H28: May | I28: W19
A29: Diam Mexico | B29: DMX | C29: k$ | G29: W21 | H29: May | I29: W20
A30: Diam Brazil | B30: DBR | C30: k€ | G30: W22 | H30: May | I30: W21
A31: Diam CHINA | B31: DDC | C31: k€ | G31: W23 | H31: June | I31: W22
A32: DE HONG KONG | B32: DEHK | C32: k€ | G32: W24 | H32: June | I32: W23
... A52: RETAIL 3D | B52: R3D | C52: k€ | G52: W44 | H52: October | I52: W43
G53: W45 | H53: November | I53: W44
G54: W46 | H54: November | I54: W45
G55: W47 | H55: November | I55: W46
G56: W48 | H56: November | I56: W47
G57: W49 | H57: December | I57: W48
G58: W50 | H58: December | I58: W49
G59: W51 | H59: December | I59: W50
G60: W52 | H60: December | I60: W51
G61: W53 | H61: December | I61: W52

Sheet analysis week
B2: Entity | C2: =+'W1'!G2 -> Diam India | D2: =VLOOKUP(C2, parameters!A:B, 2,0) -> DDI
B4: Week | C4: W2 | D4: =VLOOKUP(C4, parameters!G:I,3,0) -> W1
B7: Var 2026 | H7: Var 2027
C9: External | D9: Group | E9: Total | I9: External | J9: Group | K9: Total
B10: ="Var in sales 2025 - "&D4&" to "&C4 -> Var in sales 2025 - W1 to W2 | C10: =+C16-C22 -> 83.29574 | D10: =+D16-D22 -> 2.39 | E10: =+E16-E22 -> 85.68574 | H10: =+"Orderbook "&$C$4 -> Orderbook W2 | I10: {=INDIRECT(ADDRESS(17,12,,,$C$4))} -> 0 | J10: {=INDIRECT(ADDRESS(18,12,,,$C$4))} -> 0 | K10: =SUM(I10:J10) -> 0
B11: ="Var in orderbook 2025 - "&D4&" to "&C4 -> Var in orderbook 2025 - W1 to W2 | C11: =+C17-C23 -> 159.68244 | D11: =+D17-D23 -> 9.676436 | E11: =+E17-E23 -> 169.35888 | H11: =+"Orderbook "&$D$4 -> Orderbook W1 | I11: {=INDIRECT(ADDRESS(17,12,,,$D$4))} -> 0 | J11: {=INDIRECT(ADDRESS(18,12,,,$D$4))} -> 0 | K11: =SUM(I11:J11) -> 0
B12: ="Var in forecast 2025 - "&D4&" to "&C4 -> Var in forecast 2025 - W1 to W2 | C12: =+C18-C24 -> 242.97818 | D12: =+D18-D24 -> 12.066436 | E12: =+E18-E24 -> 255.04462 | H12: ="Var in orderbook - "&D4&" to "&C4 -> Var in orderbook - W1 to W2 | I12: =+I10-I11 -> 0 | J12: =+J10-J11 -> 0 | K12: =+K10-K11 -> 0
C13: =+C12-SUM(C10:C11) -> 0 | D13: =+D12-SUM(D10:D11) -> 0 | E13: =+E12-SUM(E10:E11) -> 0
C15: External | D15: Group | E15: Total | H15: Somme de 2027 | I15: Étiquettes de colonnes
B16: =+"Sales "&$C$4 -> Sales W2 | C16: {=INDIRECT(ADDRESS(10,8,,,$C$4))} -> 93.43 | D16: {=INDIRECT(ADDRESS(11,8,,,$C$4))} -> 2.39 | E16: =SUM(C16:D16) -> 95.82 | H16: Étiquettes de lignes | I16: W2 | J16: W1 | K16: Var
B17: =+"Orderbook "&$C$4 -> Orderbook W2 | C17: {=INDIRECT(ADDRESS(17,11,,,$C$4))} -> 1085.1784 | D17: {=INDIRECT(ADDRESS(18,11,,,$C$4))} -> 9.676436 | E17: =SUM(C17:D17) -> 1094.8548 | H17: 0 | I17: 0 | J17: 0 | K17: =+I17-J17 -> 0
B18: =+"Forecast "&$C$4 -> Forecast W2 | C18: =SUM(C16:C17) -> 1178.6084 | D18: =SUM(D16:D17) -> 12.066436 | E18: =SUM(E16:E17) -> 1190.6748 | H18: Total général | I18: 0 | J18: 0 | K18: =+I18-J18 -> 0
K19: =+I19-J19 -> 0
K20: =+I20-J20 -> 0
C21: External | D21: Group | E21: Total | K21: =+I21-J21 -> 0
B22: =+"Sales "&$D$4 -> Sales W1 | C22: {=INDIRECT(ADDRESS(10,8,,,$D$4))} -> 10.13426 | D22: {=INDIRECT(ADDRESS(11,8,,,$D$4))} -> 0 | E22: =SUM(C22:D22) -> 10.13426 | K22: =+I22-J22 -> 0
B23: =+"Orderbook "&$D$4 -> Orderbook W1 | C23: {=INDIRECT(ADDRESS(17,11,,,$D$4))} -> 925.49593 | D23: {=INDIRECT(ADDRESS(18,11,,,$D$4))} -> 0 | E23: =SUM(C23:D23) -> 925.49593 | K23: =+I23-J23 -> 0
B24: =+"Forecast "&$D$4 -> Forecast W1 | C24: =SUM(C22:C23) -> 935.63019 | D24: =SUM(D22:D23) -> 0 | E24: =SUM(E22:E23) -> 935.63019 | K24: =+I24-J24 -> 0
K25: =+I25-J25 -> 0
K26: =+I26-J26 -> 0
B27: Somme de 2026 | C27: Étiquettes de colonnes | K27: =+I27-J27 -> 0
B28: Étiquettes de lignes | C28: W2 | D28: W1 | E28: Var | K28: =+I28-J28 -> 0
B29: 0 | C29: 0 | D29: 0 | E29: =+C29-D29 -> 0 | K29: =+I29-J29 -> 0
B30: Total général | C30: 0 | D30: 0 | E30: =+C30-D30 -> 0 | K30: =+I30-J30 -> 0
E31: =+C31-D31 -> 0 | K31: =+I31-J31 -> 0
E32: =+C32-D32 -> 0 | K32: =+I32-J32 -> 0
E33: =+C33-D33 -> 0 | K33: =+I33-J33 -> 0
E34: =+C34-D34 -> 0 | K34: =+I34-J34 -> 0
E35: =+C35-D35 -> 0 | K35: =+I35-J35 -> 0
E36: =+C36-D36 -> 0 | K36: =+I36-J36 -> 0
E37: =+C37-D37 -> 0 | K37: =+I37-J37 -> 0
E38: =+C38-D38 -> 0 | K38: =+I38-J38 -> 0
E39: =+C39-D39 -> 0 | K39: =+I39-J39 -> 0
E40: =+C40-D40 -> 0 | K40: =+I40-J40 -> 0
E41: =+C41-D41 -> 0 | K41: =+I41-J41 -> 0
E42: =+C42-D42 -> 0 | K42: =+I42-J42 -> 0
... E93: =+C93-D93 -> 0 | K93: =+I93-J93 -> 0
E94: =+C94-D94 -> 0
E95: =+C95-D95 -> 0
E96: =+C96-D96 -> 0
E97: =+C97-D97 -> 0
E98: =+C98-D98 -> 0
E99: =+C99-D99 -> 0
E100: =+C100-D100 -> 0
E101: =+C101-D101 -> 0
E102: =+C102-D102 -> 0
E103: =+C103-D103 -> 0
E104: =+C104-D104 -> 0
E105: =+C105-D105 -> 0
E106: =+C106-D106 -> 0

Sheet DB analysis orders
C2: Week | D2: =+'analysis week'!C4 -> W2 | E2: =+'analysis week'!D4 -> W1
C4: 5 | D4: =+C4+1 -> 6 | E4: =+D4+1 -> 7 | F4: =+E4+1 -> 8 | G4: =+F4+1 -> 9 | H4: =+G4+1 -> 10 | I4: =+H4+1 -> 11 | J4: =+I4+1 -> 12
B5: Week | C5: Order to be delivered | D5: External or Group | E5: Customers orders | F5: Quantity | G5: DGC | H5: TOTAL ORDERBOOK | I5: 2026 | J5: 2027
A6: =+INDEX(MATCH("X", 'W1'!D:D,0),,) -> 24 | B6: =+$D$2 -> W2 | C6: {=INDIRECT(ADDRESS($A6,C$4,,,$B6))} -> BACCAROSE PERFUMES AND BEAUTY PRODUCTS PVT LTD | D6: {=INDIRECT(ADDRESS($A6,D$4,,,$B6))} -> External | E6: {=INDIRECT(ADDRESS($A6,E$4,,,$B6))} -> Laura Mercier | F6: {=INDIRECT(ADDRESS($A6,F$4,,,$B6))} -> Prestige Cosmetic | G6: {=INDIRECT(ADDRESS($A6,G$4,,,$B6))} -> CL0540 Laura Mercier | H6: {=INDIRECT(ADDRESS($A6,H$4,,,$B6))} -> 7.2617511 | I6: {=INDIRECT(ADDRESS($A6,I$4,,,$B6))} -> 7.2617511 | J6: {=INDIRECT(ADDRESS($A6,J$4,,,$B6))} -> 0
A7: =+A6+1 -> 25 | B7: =+$D$2 -> W2 | C7: {=INDIRECT(ADDRESS($A7,C$4,,,$B7))} -> BACCAROSE PERFUMES AND BEAUTY PRODUCTS PVT LTD | D7: {=INDIRECT(ADDRESS($A7,D$4,,,$B7))} -> External | E7: {=INDIRECT(ADDRESS($A7,E$4,,,$B7))} -> Shiseido | F7: {=INDIRECT(ADDRESS($A7,F$4,,,$B7))} -> Prestige Cosmetic | G7: {=INDIRECT(ADDRESS($A7,G$4,,,$B7))} -> CL0285 Shiseido | H7: {=INDIRECT(ADDRESS($A7,H$4,,,$B7))} -> 19.0875 | I7: {=INDIRECT(ADDRESS($A7,I$4,,,$B7))} -> 19.0875 | J7: {=INDIRECT(ADDRESS($A7,J$4,,,$B7))} -> 0
A8: =+A7+1 -> 26 | B8: =+$D$2 -> W2 | C8: {=INDIRECT(ADDRESS($A8,C$4,,,$B8))} -> Beauty Impex Pvt. Ltd | D8: {=INDIRECT(ADDRESS($A8,D$4,,,$B8))} -> External | E8: {=INDIRECT(ADDRESS($A8,E$4,,,$B8))} -> Guerlain | F8: {=INDIRECT(ADDRESS($A8,F$4,,,$B8))} -> Prestige Cosmetic | G8: {=INDIRECT(ADDRESS($A8,G$4,,,$B8))} -> CL0130 Guerlain | H8: {=INDIRECT(ADDRESS($A8,H$4,,,$B8))} -> 17.317858 | I8: {=INDIRECT(ADDRESS($A8,I$4,,,$B8))} -> 17.317858 | J8: {=INDIRECT(ADDRESS($A8,J$4,,,$B8))} -> 0
A9: =+A8+1 -> 27 | B9: =+$D$2 -> W2 | C9: {=INDIRECT(ADDRESS($A9,C$4,,,$B9))} -> Best In Brands | D9: {=INDIRECT(ADDRESS($A9,D$4,,,$B9))} -> External | E9: {=INDIRECT(ADDRESS($A9,E$4,,,$B9))} -> Shiseido | F9: {=INDIRECT(ADDRESS($A9,F$4,,,$B9))} -> Prestige Cosmetic | G9: {=INDIRECT(ADDRESS($A9,G$4,,,$B9))} -> CL0285 Shiseido | H9: {=INDIRECT(ADDRESS($A9,H$4,,,$B9))} -> 8.0682141 | I9: {=INDIRECT(ADDRESS($A9,I$4,,,$B9))} -> 8.0682141 | J9: {=INDIRECT(ADDRESS($A9,J$4,,,$B9))} -> 0
A10: =+A9+1 -> 28 | B10: =+$D$2 -> W2 | C10: {=INDIRECT(ADDRESS($A10,C$4,,,$B10))} -> CHANEL INDIA | D10: {=INDIRECT(ADDRESS($A10,D$4,,,$B10))} -> External | E10: {=INDIRECT(ADDRESS($A10,E$4,,,$B10))} -> Chanel | F10: {=INDIRECT(ADDRESS($A10,F$4,,,$B10))} -> Shopfitting | G10: {=INDIRECT(ADDRESS($A10,G$4,,,$B10))} -> CL0065 Chanel | H10: {=INDIRECT(ADDRESS($A10,H$4,,,$B10))} -> 5.922258 | I10: {=INDIRECT(ADDRESS($A10,I$4,,,$B10))} -> 5.922258 | J10: {=INDIRECT(ADDRESS($A10,J$4,,,$B10))} -> 0
A11: =+A10+1 -> 29 | B11: =+$D$2 -> W2 | C11: {=INDIRECT(ADDRESS($A11,C$4,,,$B11))} -> Clarins Pte Ltd | D11: {=INDIRECT(ADDRESS($A11,D$4,,,$B11))} -> External | E11: {=INDIRECT(ADDRESS($A11,E$4,,,$B11))} -> Clarins | F11: {=INDIRECT(ADDRESS($A11,F$4,,,$B11))} -> Shopfitting | G11: {=INDIRECT(ADDRESS($A11,G$4,,,$B11))} -> CL0070 Clarins | H11: {=INDIRECT(ADDRESS($A11,H$4,,,$B11))} -> 2.8162104 | I11: {=INDIRECT(ADDRESS($A11,I$4,,,$B11))} -> 2.8162104 | J11: {=INDIRECT(ADDRESS($A11,J$4,,,$B11))} -> 0
A12: =+A11+1 -> 30 | B12: =+$D$2 -> W2 | C12: {=INDIRECT(ADDRESS($A12,C$4,,,$B12))} -> Coty | D12: {=INDIRECT(ADDRESS($A12,D$4,,,$B12))} -> External | E12: {=INDIRECT(ADDRESS($A12,E$4,,,$B12))} -> Coty Rimmel | F12: {=INDIRECT(ADDRESS($A12,F$4,,,$B12))} -> Shopfitting | G12: {=INDIRECT(ADDRESS($A12,G$4,,,$B12))} -> CL0080 Coty Rimmel | H12: {=INDIRECT(ADDRESS($A12,H$4,,,$B12))} -> 2.8140266 | I12: {=INDIRECT(ADDRESS($A12,I$4,,,$B12))} -> 2.8140266 | J12: {=INDIRECT(ADDRESS($A12,J$4,,,$B12))} -> 0
A13: =+A12+1 -> 31 | B13: =+$D$2 -> W2 | C13: {=INDIRECT(ADDRESS($A13,C$4,,,$B13))} -> DIAM Display Singapore | D13: {=INDIRECT(ADDRESS($A13,D$4,,,$B13))} -> Group | E13: {=INDIRECT(ADDRESS($A13,E$4,,,$B13))} -> Coty Rimmel | F13: {=INDIRECT(ADDRESS($A13,F$4,,,$B13))} -> Shopfitting | G13: {=INDIRECT(ADDRESS($A13,G$4,,,$B13))} -> CL0080 Coty Rimmel | H13: {=INDIRECT(ADDRESS($A13,H$4,,,$B13))} -> 9.676436 | I13: {=INDIRECT(ADDRESS($A13,I$4,,,$B13))} -> 9.676436 | J13: {=INDIRECT(ADDRESS($A13,J$4,,,$B13))} -> 0
A14: =+A13+1 -> 32 | B14: =+$D$2 -> W2 | C14: {=INDIRECT(ADDRESS($A14,C$4,,,$B14))} -> Elca Cosmetics Pvt Ltd | D14: {=INDIRECT(ADDRESS($A14,D$4,,,$B14))} -> External | E14: {=INDIRECT(ADDRESS($A14,E$4,,,$B14))} -> Too Faced | F14: {=INDIRECT(ADDRESS($A14,F$4,,,$B14))} -> Prestige Cosmetic | G14: {=INDIRECT(ADDRESS($A14,G$4,,,$B14))} -> CL0575 Too Faced | H14: {=INDIRECT(ADDRESS($A14,H$4,,,$B14))} -> 39.996064 | I14: {=INDIRECT(ADDRESS($A14,I$4,,,$B14))} -> 39.996064 | J14: {=INDIRECT(ADDRESS($A14,J$4,,,$B14))} -> 0
A15: =+A14+1 -> 33 | B15: =+$D$2 -> W2 | C15: {=INDIRECT(ADDRESS($A15,C$4,,,$B15))} -> ELCA Cosmetics Pvt. Ltd. | D15: {=INDIRECT(ADDRESS($A15,D$4,,,$B15))} -> External | E15: {=INDIRECT(ADDRESS($A15,E$4,,,$B15))} -> Clinique | F15: {=INDIRECT(ADDRESS($A15,F$4,,,$B15))} -> Prestige Cosmetic | G15: {=INDIRECT(ADDRESS($A15,G$4,,,$B15))} -> CL0075 Clinique | H15: {=INDIRECT(ADDRESS($A15,H$4,,,$B15))} -> 50.077315 | I15: {=INDIRECT(ADDRESS($A15,I$4,,,$B15))} -> 50.077315 | J15: {=INDIRECT(ADDRESS($A15,J$4,,,$B15))} -> 0
A16: =+A15+1 -> 34 | B16: =+$D$2 -> W2 | C16: {=INDIRECT(ADDRESS($A16,C$4,,,$B16))} -> ELCA Cosmetics Pvt. Ltd. | D16: {=INDIRECT(ADDRESS($A16,D$4,,,$B16))} -> External | E16: {=INDIRECT(ADDRESS($A16,E$4,,,$B16))} -> Dr Jart+ | F16: {=INDIRECT(ADDRESS($A16,F$4,,,$B16))} -> Prestige Cosmetic | G16: {=INDIRECT(ADDRESS($A16,G$4,,,$B16))} -> CL0680 Estée Lauder - other brands | H16: {=INDIRECT(ADDRESS($A16,H$4,,,$B16))} -> 3.1881163 | I16: {=INDIRECT(ADDRESS($A16,I$4,,,$B16))} -> 3.1881163 | J16: {=INDIRECT(ADDRESS($A16,J$4,,,$B16))} -> 0
A17: =+A16+1 -> 35 | B17: =+$D$2 -> W2 | C17: {=INDIRECT(ADDRESS($A17,C$4,,,$B17))} -> ELCA Cosmetics Pvt. Ltd. | D17: {=INDIRECT(ADDRESS($A17,D$4,,,$B17))} -> External | E17: {=INDIRECT(ADDRESS($A17,E$4,,,$B17))} -> Estee Lauder | F17: {=INDIRECT(ADDRESS($A17,F$4,,,$B17))} -> Prestige Cosmetic | G17: {=INDIRECT(ADDRESS($A17,G$4,,,$B17))} -> CL0110 Estée Lauder | H17: {=INDIRECT(ADDRESS($A17,H$4,,,$B17))} -> 50.54466 | I17: {=INDIRECT(ADDRESS($A17,I$4,,,$B17))} -> 50.54466 | J17: {=INDIRECT(ADDRESS($A17,J$4,,,$B17))} -> 0
A18: =+A17+1 -> 36 | B18: =+$D$2 -> W2 | C18: {=INDIRECT(ADDRESS($A18,C$4,,,$B18))} -> ELCA Cosmetics Pvt. Ltd. | D18: {=INDIRECT(ADDRESS($A18,D$4,,,$B18))} -> External | E18: {=INDIRECT(ADDRESS($A18,E$4,,,$B18))} -> Mac | F18: {=INDIRECT(ADDRESS($A18,F$4,,,$B18))} -> Prestige Cosmetic | G18: {=INDIRECT(ADDRESS($A18,G$4,,,$B18))} -> CL0395 MAC | H18: {=INDIRECT(ADDRESS($A18,H$4,,,$B18))} -> 16.992312 | I18: {=INDIRECT(ADDRESS($A18,I$4,,,$B18))} -> 16.992312 | J18: {=INDIRECT(ADDRESS($A18,J$4,,,$B18))} -> 0
... A233: =+A232+1 -> 251 | B233: =+$D$2 -> W2 | C233: {=INDIRECT(ADDRESS($A233,C$4,,,$B233))} -> 0 | D233: {=INDIRECT(ADDRESS($A233,D$4,,,$B233))} -> 0 | E233: {=INDIRECT(ADDRESS($A233,E$4,,,$B233))} -> 0 | F233: {=INDIRECT(ADDRESS($A233,F$4,,,$B233))} -> 0 | G233: {=INDIRECT(ADDRESS($A233,G$4,,,$B233))} -> 0 | H233: {=INDIRECT(ADDRESS($A233,H$4,,,$B233))} -> 0 | I233: {=INDIRECT(ADDRESS($A233,I$4,,,$B233))} -> 0 | J233: {=INDIRECT(ADDRESS($A233,J$4,,,$B233))} -> 0
A234: =+A6 -> 24 | B234: =+$E$2 -> W1 | C234: {=INDIRECT(ADDRESS($A234,C$4,,,$B234))} -> BACCAROSE PERFUMES AND BEAUTY PRODUCTS PVT LTD | D234: {=INDIRECT(ADDRESS($A234,D$4,,,$B234))} -> External | E234: {=INDIRECT(ADDRESS($A234,E$4,,,$B234))} -> Laura Mercier | F234: {=INDIRECT(ADDRESS($A234,F$4,,,$B234))} -> Prestige Cosmetic | G234: {=INDIRECT(ADDRESS($A234,G$4,,,$B234))} -> 0 | H234: {=INDIRECT(ADDRESS($A234,H$4,,,$B234))} -> 7.2617511 | I234: {=INDIRECT(ADDRESS($A234,I$4,,,$B234))} -> 7.2617511 | J234: {=INDIRECT(ADDRESS($A234,J$4,,,$B234))} -> 0
A235: =+A7 -> 25 | B235: =+$E$2 -> W1 | C235: {=INDIRECT(ADDRESS($A235,C$4,,,$B235))} -> BACCAROSE PERFUMES AND BEAUTY PRODUCTS PVT LTD | D235: {=INDIRECT(ADDRESS($A235,D$4,,,$B235))} -> External | E235: {=INDIRECT(ADDRESS($A235,E$4,,,$B235))} -> Shiseido | F235: {=INDIRECT(ADDRESS($A235,F$4,,,$B235))} -> Prestige Cosmetic | G235: {=INDIRECT(ADDRESS($A235,G$4,,,$B235))} -> 0 | H235: {=INDIRECT(ADDRESS($A235,H$4,,,$B235))} -> 19.0875 | I235: {=INDIRECT(ADDRESS($A235,I$4,,,$B235))} -> 19.0875 | J235: {=INDIRECT(ADDRESS($A235,J$4,,,$B235))} -> 0
A236: =+A8 -> 26 | B236: =+$E$2 -> W1 | C236: {=INDIRECT(ADDRESS($A236,C$4,,,$B236))} -> Beauty Impex Pvt. Ltd | D236: {=INDIRECT(ADDRESS($A236,D$4,,,$B236))} -> External | E236: {=INDIRECT(ADDRESS($A236,E$4,,,$B236))} -> Guerlain | F236: {=INDIRECT(ADDRESS($A236,F$4,,,$B236))} -> Prestige Cosmetic | G236: {=INDIRECT(ADDRESS($A236,G$4,,,$B236))} -> 0 | H236: {=INDIRECT(ADDRESS($A236,H$4,,,$B236))} -> 9.0229322 | I236: {=INDIRECT(ADDRESS($A236,I$4,,,$B236))} -> 9.0229322 | J236: {=INDIRECT(ADDRESS($A236,J$4,,,$B236))} -> 0
A237: =+A9 -> 27 | B237: =+$E$2 -> W1 | C237: {=INDIRECT(ADDRESS($A237,C$4,,,$B237))} -> Best In Brands | D237: {=INDIRECT(ADDRESS($A237,D$4,,,$B237))} -> External | E237: {=INDIRECT(ADDRESS($A237,E$4,,,$B237))} -> Shiseido | F237: {=INDIRECT(ADDRESS($A237,F$4,,,$B237))} -> Prestige Cosmetic | G237: {=INDIRECT(ADDRESS($A237,G$4,,,$B237))} -> 0 | H237: {=INDIRECT(ADDRESS($A237,H$4,,,$B237))} -> 7.9641265 | I237: {=INDIRECT(ADDRESS($A237,I$4,,,$B237))} -> 7.9641265 | J237: {=INDIRECT(ADDRESS($A237,J$4,,,$B237))} -> 0
A238: =+A10 -> 28 | B238: =+$E$2 -> W1 | C238: {=INDIRECT(ADDRESS($A238,C$4,,,$B238))} -> CHANEL INDIA | D238: {=INDIRECT(ADDRESS($A238,D$4,,,$B238))} -> External | E238: {=INDIRECT(ADDRESS($A238,E$4,,,$B238))} -> Chanel | F238: {=INDIRECT(ADDRESS($A238,F$4,,,$B238))} -> Shopfitting | G238: {=INDIRECT(ADDRESS($A238,G$4,,,$B238))} -> 0 | H238: {=INDIRECT(ADDRESS($A238,H$4,,,$B238))} -> 6.2638655 | I238: {=INDIRECT(ADDRESS($A238,I$4,,,$B238))} -> 6.2638655 | J238: {=INDIRECT(ADDRESS($A238,J$4,,,$B238))} -> 0
A239: =+A11 -> 29 | B239: =+$E$2 -> W1 | C239: {=INDIRECT(ADDRESS($A239,C$4,,,$B239))} -> Elca Cosmetics Pvt Ltd | D239: {=INDIRECT(ADDRESS($A239,D$4,,,$B239))} -> External | E239: {=INDIRECT(ADDRESS($A239,E$4,,,$B239))} -> Too Faced | F239: {=INDIRECT(ADDRESS($A239,F$4,,,$B239))} -> Prestige Cosmetic | G239: {=INDIRECT(ADDRESS($A239,G$4,,,$B239))} -> 0 | H239: {=INDIRECT(ADDRESS($A239,H$4,,,$B239))} -> 39.996064 | I239: {=INDIRECT(ADDRESS($A239,I$4,,,$B239))} -> 39.996064 | J239: {=INDIRECT(ADDRESS($A239,J$4,,,$B239))} -> 0
A240: =+A12 -> 30 | B240: =+$E$2 -> W1 | C240: {=INDIRECT(ADDRESS($A240,C$4,,,$B240))} -> ELCA Cosmetics Pvt. Ltd. | D240: {=INDIRECT(ADDRESS($A240,D$4,,,$B240))} -> External | E240: {=INDIRECT(ADDRESS($A240,E$4,,,$B240))} -> Clinique | F240: {=INDIRECT(ADDRESS($A240,F$4,,,$B240))} -> Prestige Cosmetic | G240: {=INDIRECT(ADDRESS($A240,G$4,,,$B240))} -> 0 | H240: {=INDIRECT(ADDRESS($A240,H$4,,,$B240))} -> 40.110492 | I240: {=INDIRECT(ADDRESS($A240,I$4,,,$B240))} -> 40.110492 | J240: {=INDIRECT(ADDRESS($A240,J$4,,,$B240))} -> 0
A241: =+A13 -> 31 | B241: =+$E$2 -> W1 | C241: {=INDIRECT(ADDRESS($A241,C$4,,,$B241))} -> ELCA Cosmetics Pvt. Ltd. | D241: {=INDIRECT(ADDRESS($A241,D$4,,,$B241))} -> External | E241: {=INDIRECT(ADDRESS($A241,E$4,,,$B241))} -> Dr Jart+ | F241: {=INDIRECT(ADDRESS($A241,F$4,,,$B241))} -> Prestige Cosmetic | G241: {=INDIRECT(ADDRESS($A241,G$4,,,$B241))} -> 0 | H241: {=INDIRECT(ADDRESS($A241,H$4,,,$B241))} -> 3.1881163 | I241: {=INDIRECT(ADDRESS($A241,I$4,,,$B241))} -> 3.1881163 | J241: {=INDIRECT(ADDRESS($A241,J$4,,,$B241))} -> 0
A242: =+A14 -> 32 | B242: =+$E$2 -> W1 | C242: {=INDIRECT(ADDRESS($A242,C$4,,,$B242))} -> ELCA Cosmetics Pvt. Ltd. | D242: {=INDIRECT(ADDRESS($A242,D$4,,,$B242))} -> External | E242: {=INDIRECT(ADDRESS($A242,E$4,,,$B242))} -> Estee Lauder | F242: {=INDIRECT(ADDRESS($A242,F$4,,,$B242))} -> Prestige Cosmetic | G242: {=INDIRECT(ADDRESS($A242,G$4,,,$B242))} -> 0 | H242: {=INDIRECT(ADDRESS($A242,H$4,,,$B242))} -> 41.310783 | I242: {=INDIRECT(ADDRESS($A242,I$4,,,$B242))} -> 41.310783 | J242: {=INDIRECT(ADDRESS($A242,J$4,,,$B242))} -> 0
A243: =+A15 -> 33 | B243: =+$E$2 -> W1 | C243: {=INDIRECT(ADDRESS($A243,C$4,,,$B243))} -> ELCA Cosmetics Pvt. Ltd. | D243: {=INDIRECT(ADDRESS($A243,D$4,,,$B243))} -> External | E243: {=INDIRECT(ADDRESS($A243,E$4,,,$B243))} -> Mac | F243: {=INDIRECT(ADDRESS($A243,F$4,,,$B243))} -> Prestige Cosmetic | G243: {=INDIRECT(ADDRESS($A243,G$4,,,$B243))} -> 0 | H243: {=INDIRECT(ADDRESS($A243,H$4,,,$B243))} -> 16.992312 | I243: {=INDIRECT(ADDRESS($A243,I$4,,,$B243))} -> 16.992312 | J243: {=INDIRECT(ADDRESS($A243,J$4,,,$B243))} -> 0
A244: =+A16 -> 34 | B244: =+$E$2 -> W1 | C244: {=INDIRECT(ADDRESS($A244,C$4,,,$B244))} -> ELCA Cosmetics Pvt. Ltd. | D244: {=INDIRECT(ADDRESS($A244,D$4,,,$B244))} -> External | E244: {=INDIRECT(ADDRESS($A244,E$4,,,$B244))} -> The Ordinary | F244: {=INDIRECT(ADDRESS($A244,F$4,,,$B244))} -> Prestige Cosmetic | G244: {=INDIRECT(ADDRESS($A244,G$4,,,$B244))} -> 0 | H244: {=INDIRECT(ADDRESS($A244,H$4,,,$B244))} -> 30.265831 | I244: {=INDIRECT(ADDRESS($A244,I$4,,,$B244))} -> 30.265831 | J244: {=INDIRECT(ADDRESS($A244,J$4,,,$B244))} -> 0
A245: =+A17 -> 35 | B245: =+$E$2 -> W1 | C245: {=INDIRECT(ADDRESS($A245,C$4,,,$B245))} -> ELCA Cosmetics Pvt. Ltd. | D245: {=INDIRECT(ADDRESS($A245,D$4,,,$B245))} -> External | E245: {=INDIRECT(ADDRESS($A245,E$4,,,$B245))} -> Tom Ford | F245: {=INDIRECT(ADDRESS($A245,F$4,,,$B245))} -> Prestige Cosmetic | G245: {=INDIRECT(ADDRESS($A245,G$4,,,$B245))} -> 0 | H245: {=INDIRECT(ADDRESS($A245,H$4,,,$B245))} -> 24.496051 | I245: {=INDIRECT(ADDRESS($A245,I$4,,,$B245))} -> 24.496051 | J245: {=INDIRECT(ADDRESS($A245,J$4,,,$B245))} -> 0
... A461: =+A233 -> 251 | B461: =+$E$2 -> W1 | C461: {=INDIRECT(ADDRESS($A461,C$4,,,$B461))} -> 0 | D461: {=INDIRECT(ADDRESS($A461,D$4,,,$B461))} -> 0 | E461: {=INDIRECT(ADDRESS($A461,E$4,,,$B461))} -> 0 | F461: {=INDIRECT(ADDRESS($A461,F$4,,,$B461))} -> 0 | G461: {=INDIRECT(ADDRESS($A461,G$4,,,$B461))} -> 0 | H461: {=INDIRECT(ADDRESS($A461,H$4,,,$B461))} -> 0 | I461: {=INDIRECT(ADDRESS($A461,I$4,,,$B461))} -> 0 | J461: {=INDIRECT(ADDRESS($A461,J$4,,,$B461))} -> 0

Sheet Synth
A1: SYNTHESIS
A3: To be filled in (TURNOVER = BO)
A5: YTD : Year to date turnover. This means the cumulated turnover since the begining of the year.
A6: This turnover should the same as the turnover fill in Business Object (BO). See with your local accountant to know this turnover.
A8: TURNOVER | D8: ORDERBOOK 2026 | F8: FORECAST 2026 | H8: NEW ORDERS 2026 | J8: ORDERBOOK 2027
A10: W52 2025
A12: W1 | B12: =+'W1'!$J$12 -> 10.13426 | D12: =+'W1'!$K$19 -> 925.49593 | F12: =+B12+D12 -> 935.63019 | H12: =D12+B12-D10 -> 935.63019 | J12: =+'W1'!$L$19 -> 0
A13: W2 | B13: =+'W2'!$J$12 -> 95.82 | D13: =+'W2'!$K$19 -> 1094.8548 | F13: =+B13+D13 -> 1190.6748 | H13: =F13-F12 -> 255.04462 | J13: =+'W2'!$L$19 -> 0
A14: W3 | B14: =+'W3'!$J$12 -> 230.38956 | D14: =+'W3'!$K$19 -> 1262.1782 | F14: =+B14+D14 -> 1492.5677 | H14: =F14-F13 -> 301.89292 | J14: =+'W3'!$L$19 -> 0
A15: W4 | B15: =+'W4'!$J$12 -> 352.24882 | D15: =+'W4'!$K$19 -> 1263.81 | F15: =+B15+D15 -> 1616.0588 | H15: =F15-F14 -> 123.49109 | J15: =+'W4'!$L$19 -> 0
A16: W5 | B16: =+'W5'!$J$12 -> 542.53 | D16: =+'W5'!$K$19 -> 1055.63 | F16: =+B16+D16 -> 1598.16 | H16: =F16-F15 -> -17.89882 | J16: =+'W5'!$L$19 -> 0
A17: January YTD
A18: W6 | B18: =+'W6'!$J$12 -> 69.68 | D18: =+'W6'!$K$19 -> 869.1505 | F18: =+B17+B18+D18 -> 938.8305 | H18: =F18-F16 -> -659.3295 | J18: =+'W6'!$L$19 -> 0
A19: W7 | B19: =+'W7'!$J$12 -> 83 | D19: =+'W7'!$K$19 -> 1009.6434 | F19: =+B17+B19+D19 -> 1092.6434 | H19: =F19-F18 -> 153.81289 | J19: =+'W7'!$L$19 -> 0
A20: W8 | B20: =+'W8'!$J$12 -> 156.24735 | D20: =+'W8'!$K$19 -> 1266.28 | F20: =+B17+B20+D20 -> 1422.5273 | H20: =F20-F19 -> 329.88395 | J20: =+'W8'!$L$19 -> 0
A21: W9 | B21: =+'W9'!$J$12 -> 573 | D21: =+'W9'!$K$19 -> 2302.9324 | F21: =+B22+B21+D21 -> 2875.9324 | H21: =F21-F20 -> 1453.4051 | J21: =+'W9'!$L$19 -> 0
A22: February YTD
A23: W10 | B23: =+'W10'!$J$12 -> 31 | D23: =+'W10'!$K$19 -> 2342.7469 | F23: =+B22+B23+D23 -> 2373.7469 | H23: =F23-F21 -> -502.18548 | J23: =+'W10'!$L$19 -> 0
A24: W11 | B24: =+'W11'!$J$12 -> 78 | D24: =+'W11'!$K$19 -> 2998.0455 | F24: =+B22+B24+D24 -> 3076.0455 | H24: =F24-F23 -> 702.29861 | J24: =+'W11'!$L$19 -> 0
A25: W12 | B25: =+'W12'!$J$12 -> 197.22 | D25: =+'W12'!$K$19 -> 2975.9453 | F25: =+B22+B25+D25 -> 3173.1653 | H25: =F25-F24 -> 97.11976 | J25: =+'W12'!$L$19 -> 0
A26: W13 | B26: =+'W13'!$J$12 -> 441.52 | D26: =+'W13'!$K$19 -> 3365.0094 | F26: =+B22+B26+D26 -> 3806.5294 | H26: =F26-F25 -> 633.36414 | J26: =+'W13'!$L$19 -> 0
A27: March YTD
A28: W14 | B28: =+'W14'!$J$12 -> 6.5 | D28: =+'W14'!$K$19 -> 3097.8574 | F28: =+B27+B28+D28 -> 3104.3574 | H28: =F28-F26 -> -702.17198 | J28: =+'W14'!$L$19 -> 0
A29: W15 | B29: =+'W15'!$J$12 -> 59.37 | D29: =+'W15'!$K$19 -> 3181.8574 | F29: =+B27+B29+D29 -> 3241.2274 | H29: =F29-F28 -> 136.87 | J29: =+'W15'!$L$19 -> 0
A30: W16 | B30: =+'W16'!$J$12 -> 177 | D30: =+'W16'!$K$19 -> 3286.2972 | F30: =+B27+B30+D30 -> 3463.2972 | H30: =F30-F29 -> 222.06979 | J30: =+'W16'!$L$19 -> 0
A31: W17 | B31: =+'W17'!$J$12 -> 278.27815 | D31: =+'W17'!$K$19 -> 3398.1054 | F31: =+B27+B31+D31 -> 3676.3836 | H31: =F31-F30 -> 213.08637 | J31: =+'W17'!$L$19 -> 0
A32: W18 | B32: =+'W18'!$J$12 -> 472 | D32: =+'W18'!$K$19 -> 3501.5122 | F32: =+B33+B32+D32 -> 3973.5122 | H32: =F32-F31 -> 297.12863 | J32: =+'W18'!$L$19 -> 0
A33: April YTD
A34: W19 | B34: =+'W19'!$J$12 -> 117 | D34: =+'W19'!$K$19 -> 3494.8518 | F34: =+B33+B34+D34 -> 3611.8518 | H34: =F34-F32 -> -361.66047 | J34: =+'W19'!$L$19 -> 0
A35: W20 | B35: =+'W20'!$J$12 -> 152 | D35: =+'W20'!$K$19 -> 3709.0806 | F35: =+B33+B35+D35 -> 3861.0806 | H35: =F35-F34 -> 249.2288 | J35: =+'W20'!$L$19 -> 0
A36: W21 | B36: =+'W21'!$J$12 -> 272 | D36: =+'W21'!$K$19 -> 3657.2127 | F36: =+B33+B36+D36 -> 3929.2127 | H36: =F36-F35 -> 68.132142 | J36: =+'W21'!$L$19 -> 0
A37: W22 | B37: =+'W22'!$J$12 -> 466 | D37: =+'W22'!$K$19 -> 3649.4797 | F37: =+B38+B37+D37 -> 4115.4797 | H37: =F37-F36 -> 186.26703 | J37: =+'W22'!$L$19 -> 0
A38: May YTD
A39: W23 | B39: =+'W23'!$J$12 -> 158 | D39: =+'W23'!$K$19 -> 3464.4907 | F39: =+B38+B39+D39 -> 3622.4907 | H39: =F39-F37 -> -492.98899 | J39: =+'W23'!$L$19 -> 0
A40: W24 | B40: =+'W24'!$J$12 -> 311 | D40: =+'W24'!$K$19 -> 3343.2065 | F40: =+B38+B40+D40 -> 3654.2065 | H40: =F40-F39 -> 31.715812 | J40: =+'W24'!$L$19 -> 0
A41: W25 | B41: =+'W25'!$J$12 -> 488 | D41: =+'W25'!$K$19 -> 3338.7145 | F41: =+B38+B41+D41 -> 3826.7145 | H41: =F41-F40 -> 172.50798 | J41: =+'W25'!$L$19 -> 0
A42: W26 | B42: =+'W26'!$J$12 -> 656 | D42: =+'W26'!$K$19 -> 3502.0385 | F42: =+B38+B42+D42 -> 4158.0385 | H42: =F42-F41 -> 331.32396 | J42: =+'W26'!$L$19 -> 0
A43: June YTD
A44: W27 | B44: =+'W27'!$J$12 -> 215 | D44: =+'W27'!$K$19 -> 3246.6092 | F44: =+B43+B44+D44 -> 3461.6092 | H44: =F44-F42 -> -696.42933 | J44: =+'W27'!$L$19 -> 0
A45: W28 | B45: =+'W28'!$J$12 -> 407 | D45: =+'W28'!$K$19 -> 3233.1982 | F45: =+B43+B45+D45 -> 3640.1982 | H45: =F45-F44 -> 178.58909 | J45: =+'W28'!$L$19 -> 0
A46: W29 | B46: =+'W29'!$J$12 -> 749 | D46: =+'W29'!$K$19 -> 3228.0778 | F46: =+B43+B46+D46 -> 3977.0778 | H46: =F46-F45 -> 336.87951 | J46: =+'W29'!$L$19 -> 0
A47: W30 | B47: =+'W30'!$J$12 -> 870 | D47: =+'W30'!$K$19 -> 3244.469 | F47: =+B43+B47+D47 -> 4114.469 | H47: =F47-F46 -> 137.39124 | J47: =+'W30'!$L$19 -> 0
A48: W31 | B48: =+'W31'!$J$12 -> 929 | D48: =+'W31'!$K$19 -> 3178.6204 | F48: =+B43+B48+D48 -> 4107.6204 | H48: =F48-F47 -> -6.8485763 | J48: =+'W31'!$L$19 -> 0
A49: July YTD
A50: W32 | B50: =+'W32'!$J$12 -> 106 | D50: =+'W32'!$K$19 -> 3035.6395 | F50: =+B49+B50+D50 -> 3141.6395 | H50: =F50-F48 -> -965.98095 | J50: =+'W32'!$L$19 -> 0
A51: W33 | B51: =+'W33'!$J$12 -> 227 | D51: =+'W33'!$K$19 -> 2944.7055 | F51: =+B49+B51+D51 -> 3171.7055 | H51: =F51-F50 -> 30.066045 | J51: =+'W33'!$L$19 -> 0
A52: W34 | B52: =+'W34'!$J$12 -> 388 | D52: =+'W34'!$K$19 -> 3060.5815 | F52: =+B49+B52+D52 -> 3448.5815 | H52: =F52-F51 -> 276.87599 | J52: =+'W34'!$L$19 -> 0
A53: W35 | B53: =+'W35'!$J$12 -> 699 | D53: =+'W35'!$K$19 -> 3809.5392 | F53: =+B48+B53+D53 -> 5437.5392 | H53: =F53-F52 -> 1988.9577 | J53: =+'W35'!$L$19 -> 0
A54: August YTD
A55: W36 | B55: =+'W36'!$J$12 -> 98 | D55: =+'W36'!$K$19 -> 3867.6947 | F55: =+B54+B55+D55 -> 3965.6947 | H55: =F55-F53 -> -1471.8445 | J55: =+'W36'!$L$19 -> 0
A56: W37 | B56: =+'W37'!$J$12 -> 338 | D56: =+'W37'!$K$19 -> 3694.1929 | F56: =+B54+B56+D56 -> 4032.1929 | H56: =F56-F55 -> 66.498158 | J56: =+'W37'!$L$19 -> 0
A57: W38 | B57: =+'W38'!$J$12 -> 486 | D57: =+'W38'!$K$19 -> 3625.8805 | F57: =+B54+B57+D57 -> 4111.8805 | H57: =F57-F56 -> 79.687613 | J57: =+'W38'!$L$19 -> 0
A58: W39 | B58: =+'W39'!$J$12 -> 868 | D58: =+'W39'!$K$19 -> 3135.5063 | F58: =+B54+B58+D58 -> 4003.5063 | H58: =F58-F57 -> -108.37419 | J58: =+'W39'!$L$19 -> 0
A59: September YTD
A60: W40 | B60: =+'W40'!$J$12 -> 120 | D60: =+'W40'!$K$19 -> 2995.1083 | F60: =+B59+B60+D60 -> 3115.1083 | H60: =F60-F58 -> -888.39798 | J60: =+'W40'!$L$19 -> 109.15973
A61: W41 | B61: =+'W41'!$J$12 -> 306 | D61: =+'W41'!$K$19 -> 2909.3516 | F61: =+B59+B61+D61 -> 3215.3516 | H61: =F61-F60 -> 100.24324 | J61: =+'W41'!$L$19 -> 109.15973
A62: W42 | B62: =+'W42'!$J$12 -> 0 | D62: =+'W42'!$K$19 -> 0 | F62: =+B59+B62+D62 -> 0 | H62: =F62-F61 -> -3215.3516 | J62: =+'W42'!$L$19 -> 0
A63: W43 | B63: =+'W43'!$J$12 -> 0 | D63: =+'W43'!$K$19 -> 0 | F63: =+B59+B63+D63 -> 0 | H63: =F63-F62 -> 0 | J63: =+'W43'!$L$19 -> 0
A64: W44 | B64: =+'W44'!$J$12 -> 0 | D64: =+'W44'!$K$19 -> 0 | F64: =+B65+B64+D64 -> 0 | H64: =F64-F62 -> 0 | J64: =+'W44'!$L$19 -> 0
A65: October YTD
A66: W45 | B66: =+'W45'!$J$12 -> 0 | D66: =+'W45'!$K$19 -> 0 | F66: =+B65+B66+D66 -> 0 | H66: =F66-F65 -> 0 | J66: =+'W45'!$L$19 -> 0
A67: W46 | B67: =+'W46'!$J$12 -> 0 | D67: =+'W46'!$K$19 -> 0 | F67: =+B65+B67+D67 -> 0 | H67: =F67-F66 -> 0 | J67: =+'W46'!$L$19 -> 0
A68: W47 | B68: =+'W47'!$J$12 -> 0 | D68: =+'W47'!$K$19 -> 0 | F68: =+B65+B68+D68 -> 0 | H68: =F68-F67 -> 0 | J68: =+'W47'!$L$19 -> 0
A69: W48 | B69: =+'W48'!$J$12 -> 0 | D69: =+'W48'!$K$19 -> 0 | F69: =+B65+B69+D69 -> 0 | H69: =F69-F68 -> 0 | J69: =+'W48'!$L$19 -> 0
A70: November YTD
A71: W49 | B71: =+'W49'!$J$12 -> 0 | D71: =+'W49'!$K$19 -> 0 | F71: =+B70+B71+D71 -> 0 | H71: =F71-F69 -> 0 | J71: =+'W49'!$L$19 -> 0
A72: W50 | B72: =+'W50'!$J$12 -> 0 | D72: =+'W50'!$K$19 -> 0 | F72: =+B70+B72+D72 -> 0 | H72: =F72-F71 -> 0 | J72: =+'W50'!$L$19 -> 0
A73: W51 | B73: =+'W51'!$J$12 -> 0 | D73: =+'W51'!$K$19 -> 0 | F73: =+B70+B73+D73 -> 0 | H73: =F73-F72 -> 0 | J73: =+'W51'!$L$19 -> 0
A74: W52 | B74: =+'W52'!$J$12 -> 0 | D74: =+'W52'!$K$19 -> 0 | F74: =+B70+B74+D74 -> 0 | H74: =F74-F73 -> 0 | J74: =+'W52'!$L$19 -> 0
A75: December YTD

Sheet W1
E2: ENTITY NAME : | G2: =+parameters!D2 -> Diam India | I2: ORDER BOOK SYNTHESIS in K€
E4: WEEK : | G4: W1 | I4: Cells to be filled in
E6: MONTH : | G6: =+VLOOKUP(G4, parameters!G:H, 2, 0) -> January
E8: TURNOVER | F8: =parameters!D4 -> k€ | H8: YTD Turnover | J8: =+G6&" Turnover" -> January Turnover | L8: Last estim. for the month: | O8: Forecast 2026
H9: =+"from January 1 until end of "&G4 -> from January 1 until end of W1 | J9: =+"from "&G6&" 1 until end of "&G4 -> from January 1 until end of W1 | L9: =+G6 -> January | O9: =+G4 -> W1
E10: EXTERNAL SALES INVOICED (=outside group) | H10: =J10 -> 10.13426 | J10: =1013426/100000 -> 10.13426 | L10: =J10+N19 -> 507.82698 | O10: =+H10+K17 -> 935.63019
E11: GROUP SALES INVOICED | H11: =J11 -> 0 | J11: 0 | L11: 0 | O11: =+H11+K18 -> 0 | S11: Definition orders : you consider the orders which are sure even if the order customers paper order is not yet received
E12: TOTAL | H12: =SUM(H10:H11) -> 10.13426 | J12: =SUM(J10:J11) -> 10.13426 | L12: =SUM(L10:L11) -> 507.82698 | O12: =SUM(O10:O11) -> 935.63019 | S12: The quantity, value, and delivery date can be changed before final delivery
E16: ORDERBOOK | F16: =+F8 -> k€ | J16: TOTAL ORDERBOOK | K16: Total amount 2026 | L16: Total amount 2027 | N16: 46023 | O16: 46054 | P16: 46082 | Q16: 46113 | R16: 46143 | S16: 46174 | T16: 46204 | U16: 46235 | V16: 46266 | W16: 46296 | X16: 46327 | Y16: 46357 | AA16: 46388 | AB16: 46419 | AC16: 46447 | AD16: 46478 | AE16: 46508 | AF16: 46539 | AG16: 46569 | AH16: 46600 | AI16: 46631 | AJ16: 46661 | AK16: 46692 | AL16: 46722
E17: External | J17: =+SUMIF($F$24:$F$252,"External",$J$24:$J$252) -> 925.49593 | K17: =+SUMIF($F$24:$F$252,"External",$K$24:$K$252) -> 925.49593 | L17: =+SUMIF($F$24:$F$252,"External",$L$24:$L$252) -> 0 | N17: =+SUMIF($F$24:$F$252,"External",N$24:N$252) -> 497.69272 | O17: =+SUMIF($F$24:$F$252,"External",O$24:O$252) -> 279.30503 | P17: =+SUMIF($F$24:$F$252,"External",P$24:P$252) -> 27.305477 | Q17: =+SUMIF($F$24:$F$252,"External",Q$24:Q$252) -> 39.714621 | R17: =+SUMIF($F$24:$F$252,"External",R$24:R$252) -> 81.478071 | S17: =+SUMIF($F$24:$F$252,"External",S$24:S$252) -> 0 | T17: =+SUMIF($F$24:$F$252,"External",T$24:T$252) -> 0 | U17: =+SUMIF($F$24:$F$252,"External",U$24:U$252) -> 0 | ... Y17: =+SUMIF($F$24:$F$252,"External",Y$24:Y$252) -> 0 | AA17: =+SUMIF($F$24:$F$252,"External",AA$24:AA$252) -> 0 | AB17: =+SUMIF($F$24:$F$252,"External",AB$24:AB$252) -> 0 | AC17: =+SUMIF($F$24:$F$252,"External",AC$24:AC$252) -> 0 | AD17: =+SUMIF($F$24:$F$252,"External",AD$24:AD$252) -> 0 | AE17: =+SUMIF($F$24:$F$252,"External",AE$24:AE$252) -> 0 | AF17: =+SUMIF($F$24:$F$252,"External",AF$24:AF$252) -> 0 | AG17: =+SUMIF($F$24:$F$252,"External",AG$24:AG$252) -> 0 | AH17: =+SUMIF($F$24:$F$252,"External",AH$24:AH$252) -> 0 | ... AL17: =+SUMIF($F$24:$F$252,"External",AL$24:AL$252) -> 0
E18: Group | J18: =+SUMIF($F$24:$F$252,"Group",$J$24:$J$252) -> 0 | K18: =+SUMIF($F$24:$F$252,"Group",$K$24:$K$252) -> 0 | L18: =SUMIF($F$24:$F$252,"Group",$L$24:$L$252) -> 0 | N18: =+SUMIF($F$24:$F$252,"Group",N$24:N$252) -> 0 | O18: =+SUMIF($F$24:$F$252,"Group",O$24:O$252) -> 0 | P18: =+SUMIF($F$24:$F$252,"Group",P$24:P$252) -> 0 | Q18: =+SUMIF($F$24:$F$252,"Group",Q$24:Q$252) -> 0 | R18: =+SUMIF($F$24:$F$252,"Group",R$24:R$252) -> 0 | S18: =+SUMIF($F$24:$F$252,"Group",S$24:S$252) -> 0 | T18: =+SUMIF($F$24:$F$252,"Group",T$24:T$252) -> 0 | U18: =+SUMIF($F$24:$F$252,"Group",U$24:U$252) -> 0 | ... Y18: =+SUMIF($F$24:$F$252,"Group",Y$24:Y$252) -> 0 | AA18: =+SUMIF($F$24:$F$252,"Group",AA$24:AA$252) -> 0 | AB18: =+SUMIF($F$24:$F$252,"Group",AB$24:AB$252) -> 0 | AC18: =+SUMIF($F$24:$F$252,"Group",AC$24:AC$252) -> 0 | AD18: =+SUMIF($F$24:$F$252,"Group",AD$24:AD$252) -> 0 | AE18: =+SUMIF($F$24:$F$252,"Group",AE$24:AE$252) -> 0 | AF18: =+SUMIF($F$24:$F$252,"Group",AF$24:AF$252) -> 0 | AG18: =+SUMIF($F$24:$F$252,"Group",AG$24:AG$252) -> 0 | AH18: =+SUMIF($F$24:$F$252,"Group",AH$24:AH$252) -> 0 | ... AL18: =+SUMIF($F$24:$F$252,"Group",AL$24:AL$252) -> 0
E19: TOTAL | J19: =SUM(J17:J18) -> 925.49593 | K19: =SUM(K17:K18) -> 925.49593 | L19: =SUM(L17:L18) -> 0 | N19: =SUM(N17:N18) -> 497.69272 | O19: =SUM(O17:O18) -> 279.30503 | P19: =SUM(P17:P18) -> 27.305477 | Q19: =SUM(Q17:Q18) -> 39.714621 | R19: =SUM(R17:R18) -> 81.478071 | S19: =SUM(S17:S18) -> 0 | T19: =SUM(T17:T18) -> 0 | U19: =SUM(U17:U18) -> 0 | ... Y19: =SUM(Y17:Y18) -> 0 | AA19: =SUM(AA17:AA18) -> 0 | AB19: =SUM(AB17:AB18) -> 0 | AC19: =SUM(AC17:AC18) -> 0 | AD19: =SUM(AD17:AD18) -> 0 | AE19: =SUM(AE17:AE18) -> 0 | AF19: =SUM(AF17:AF18) -> 0 | AG19: =SUM(AG17:AG18) -> 0 | AH19: =SUM(AH17:AH18) -> 0 | ... AL19: =SUM(AL17:AL18) -> 0
I21: check | J21: =IF(SUM(J24:J252)=J19, "OK", "Please correct: the sum of orders below is not equal to the total calculated above. Make sure to pick External or Group for each order and don't change the formulas in columns K and L") -> OK | N21: 2026 | AA21: 2027
E23: Order (Tooling including) to be delivered | F23: External or Group | G23: Customers orders | H23: Quantity | I23: DGC | J23: TOTAL ORDERBOOK | K23: Total amount 2026 | L23: Total amount 2026 | N23: 46023 | O23: 46054 | P23: 46082 | Q23: 46113 | R23: 46143 | S23: 46174 | T23: 46204 | U23: 46235 | V23: 46266 | W23: 46296 | X23: 46327 | Y23: 46357 | AA23: 46388 | AB23: 46419 | AC23: 46447 | AD23: 46478 | AE23: 46508 | AF23: 46539 | AG23: 46569 | AH23: 46600 | AI23: 46631 | AJ23: 46661 | AK23: 46692 | AL23: 46722
D24: X | E24: BACCAROSE PERFUMES AND BEAUTY PRODUCTS PVT LTD | F24: External | G24: Laura Mercier | H24: Prestige Cosmetic | J24: =+K24+L24 -> 7.2617511 | K24: =SUM(N24:Y24) -> 7.2617511 | L24: =SUM(AA24:AL24) -> 0 | Q24: 7.2617511
E25: BACCAROSE PERFUMES AND BEAUTY PRODUCTS PVT LTD | F25: External | G25: Shiseido | H25: Prestige Cosmetic | J25: =+K25+L25 -> 19.0875 | K25: =SUM(N25:Y25) -> 19.0875 | L25: =SUM(AA25:AL25) -> 0 | P25: 19.0875
E26: Beauty Impex Pvt. Ltd | F26: External | G26: Guerlain | H26: Prestige Cosmetic | J26: =+K26+L26 -> 9.0229322 | K26: =SUM(N26:Y26) -> 9.0229322 | L26: =SUM(AA26:AL26) -> 0 | N26: 9.0229322
E27: Best In Brands | F27: External | G27: Shiseido | H27: Prestige Cosmetic | J27: =+K27+L27 -> 7.9641265 | K27: =SUM(N27:Y27) -> 7.9641265 | L27: =SUM(AA27:AL27) -> 0 | P27: 7.9641265
E28: CHANEL INDIA | F28: External | G28: Chanel | H28: Shopfitting | J28: =+K28+L28 -> 6.2638655 | K28: =SUM(N28:Y28) -> 6.2638655 | L28: =SUM(AA28:AL28) -> 0 | N28: 6.2638655
E29: Elca Cosmetics Pvt Ltd | F29: External | G29: Too Faced | H29: Prestige Cosmetic | J29: =+K29+L29 -> 39.996064 | K29: =SUM(N29:Y29) -> 39.996064 | L29: =SUM(AA29:AL29) -> 0 | R29: 39.996064
E30: ELCA Cosmetics Pvt. Ltd. | F30: External | G30: Clinique | H30: Prestige Cosmetic | J30: =+K30+L30 -> 40.110492 | K30: =SUM(N30:Y30) -> 40.110492 | L30: =SUM(AA30:AL30) -> 0 | N30: 40.110492
E31: ELCA Cosmetics Pvt. Ltd. | F31: External | G31: Dr Jart+ | H31: Prestige Cosmetic | J31: =+K31+L31 -> 3.1881163 | K31: =SUM(N31:Y31) -> 3.1881163 | L31: =SUM(AA31:AL31) -> 0 | N31: 3.1881163
E32: ELCA Cosmetics Pvt. Ltd. | F32: External | G32: Estee Lauder | H32: Prestige Cosmetic | J32: =+K32+L32 -> 41.310783 | K32: =SUM(N32:Y32) -> 41.310783 | L32: =SUM(AA32:AL32) -> 0 | N32: 41.310783
E33: ELCA Cosmetics Pvt. Ltd. | F33: External | G33: Mac | H33: Prestige Cosmetic | J33: =+K33+L33 -> 16.992312 | K33: =SUM(N33:Y33) -> 16.992312 | L33: =SUM(AA33:AL33) -> 0 | N33: 7.9570146 | R33: 9.035297
E34: ELCA Cosmetics Pvt. Ltd. | F34: External | G34: The Ordinary | H34: Prestige Cosmetic | J34: =+K34+L34 -> 30.265831 | K34: =SUM(N34:Y34) -> 30.265831 | L34: =SUM(AA34:AL34) -> 0 | N34: 30.265831
E35: ELCA Cosmetics Pvt. Ltd. | F35: External | G35: Tom Ford | H35: Prestige Cosmetic | J35: =+K35+L35 -> 24.496051 | K35: =SUM(N35:Y35) -> 24.496051 | L35: =SUM(AA35:AL35) -> 0 | N35: 24.496051
E36: ELCA Cosmetics Pvt. Ltd. | F36: External | G36: Too Faced | H36: Prestige Cosmetic | J36: =+K36+L36 -> 146.6935 | K36: =SUM(N36:Y36) -> 146.6935 | L36: =SUM(AA36:AL36) -> 0 | O36: 146.6935
E37: Estee Lauder AG Lachen | F37: External | G37: Jo Malone | H37: Prestige Cosmetic | J37: =+K37+L37 -> 1.8251618 | K37: =SUM(N37:Y37) -> 1.8251618 | L37: =SUM(AA37:AL37) -> 0 | N37: 1.8251618
E38: Global Shoppers Stop Beauty Brands Ltd | F38: External | G38: Nars | H38: Prestige Cosmetic | J38: =+K38+L38 -> 112.31055 | K38: =SUM(N38:Y38) -> 112.31055 | L38: =SUM(AA38:AL38) -> 0 | N38: 0.84615 | O38: 46.31097 | P38: 0.25385 | Q38: 32.45287 | R38: 32.44671
E39: Indosing Distribution | F39: External | G39: Benefit | H39: Prestige Cosmetic | J39: =+K39+L39 -> 2.12327 | K39: =SUM(N39:Y39) -> 2.12327 | L39: =SUM(AA39:AL39) -> 0 | N39: 2.12327
E40: L Beauty Pte | F40: External | G40: Benefit | H40: Prestige Cosmetic | J40: =+K40+L40 -> 17.255213 | K40: =SUM(N40:Y40) -> 17.255213 | L40: =SUM(AA40:AL40) -> 0 | N40: 5.963903 | O40: 11.29131
E41: L'Oreal India | F41: External | G41: Lancome | H41: Prestige Cosmetic | J41: =+K41+L41 -> 23.444373 | K41: =SUM(N41:Y41) -> 23.444373 | L41: =SUM(AA41:AL41) -> 0 | N41: 23.444373
E42: L'Oreal India | F42: External | G42: Lancome | H42: Shopfitting | J42: =+K42+L42 -> 11.615179 | K42: =SUM(N42:Y42) -> 11.615179 | L42: =SUM(AA42:AL42) -> 0 | N42: 11.615179
E43: L'Oreal India | F43: External | G43: YSL | H43: Shopfitting | J43: =+K43+L43 -> 83.958234 | K43: =SUM(N43:Y43) -> 83.958234 | L43: =SUM(AA43:AL43) -> 0 | N43: 83.958234
E44: L'Oreal Travel Retail | F44: External | G44: Armani | H44: Shopfitting | J44: =+K44+L44 -> 25.675854 | K44: =SUM(N44:Y44) -> 25.675854 | L44: =SUM(AA44:AL44) -> 0 | N44: 25.675854
E45: L'Oreal Travel Retail | F45: External | G45: Lancome | H45: Shopfitting | J45: =+K45+L45 -> 13.609436 | K45: =SUM(N45:Y45) -> 13.609436 | L45: =SUM(AA45:AL45) -> 0 | N45: 13.609436
E46: L'Oreal Travel Retail | F46: External | G46: Loreal Paris | H46: Shopfitting | J46: =+K46+L46 -> 7.748713 | K46: =SUM(N46:Y46) -> 7.748713 | L46: =SUM(AA46:AL46) -> 0 | N46: 7.748713
E47: L'Oreal Travel Retail | F47: External | G47: Multi | H47: Shopfitting | J47: =+K47+L47 -> 49.267677 | K47: =SUM(N47:Y47) -> 49.267677 | L47: =SUM(AA47:AL47) -> 0 | N47: 49.267677
E48: L'Oreal Travel Retail | F48: External | G48: OAP | H48: Shopfitting | J48: =+K48+L48 -> 7.50618 | K48: =SUM(N48:Y48) -> 7.50618 | L48: =SUM(AA48:AL48) -> 0 | N48: 7.50618
E49: Rare Beauty LLC | F49: External | G49: Rare Beauty | H49: Prestige Cosmetic | J49: =+K49+L49 -> 101.96075 | K49: =SUM(N49:Y49) -> 101.96075 | L49: =SUM(AA49:AL49) -> 0 | N49: 48.488266 | O49: 53.47248
E50: Reliance Luxe Beauty Limited | F50: External | G50: Rare Beauty | H50: Prestige Cosmetic | J50: =+K50+L50 -> 15.972842 | K50: =SUM(N50:Y50) -> 15.972842 | L50: =SUM(AA50:AL50) -> 0 | N50: 15.972842
E51: Shoppers Stop Ltd | F51: External | G51: Clinique | H51: Prestige Cosmetic | J51: =+K51+L51 -> 3.321 | K51: =SUM(N51:Y51) -> 3.321 | L51: =SUM(AA51:AL51) -> 0 | O51: 3.321
E52: Shoppers Stop Ltd | F52: External | G52: ELCA Brand | H52: Prestige Cosmetic | J52: =+K52+L52 -> 37.0324 | K52: =SUM(N52:Y52) -> 37.0324 | L52: =SUM(AA52:AL52) -> 0 | N52: 37.0324
E53: Shoppers Stop Ltd | F53: External | G53: Tom Ford | H53: Shopfitting | J53: =+K53+L53 -> 18.215771 | K53: =SUM(N53:Y53) -> 18.215771 | L53: =SUM(AA53:AL53) -> 0 | O53: 18.215771
J54: =+K54+L54 -> 0 | K54: =SUM(N54:Y54) -> 0 | L54: =SUM(AA54:AL54) -> 0
J55: =+K55+L55 -> 0 | K55: =SUM(N55:Y55) -> 0 | L55: =SUM(AA55:AL55) -> 0
J56: =+K56+L56 -> 0 | K56: =SUM(N56:Y56) -> 0 | L56: =SUM(AA56:AL56) -> 0
J57: =+K57+L57 -> 0 | K57: =SUM(N57:Y57) -> 0 | L57: =SUM(AA57:AL57) -> 0
J58: =+K58+L58 -> 0 | K58: =SUM(N58:Y58) -> 0 | L58: =SUM(AA58:AL58) -> 0
J59: =+K59+L59 -> 0 | K59: =SUM(N59:Y59) -> 0 | L59: =SUM(AA59:AL59) -> 0
J60: =+K60+L60 -> 0 | K60: =SUM(N60:Y60) -> 0 | L60: =SUM(AA60:AL60) -> 0
J61: =+K61+L61 -> 0 | K61: =SUM(N61:Y61) -> 0 | L61: =SUM(AA61:AL61) -> 0
J62: =+K62+L62 -> 0 | K62: =SUM(N62:Y62) -> 0 | L62: =SUM(AA62:AL62) -> 0
J63: =+K63+L63 -> 0 | K63: =SUM(N63:Y63) -> 0 | L63: =SUM(AA63:AL63) -> 0
J64: =+K64+L64 -> 0 | K64: =SUM(N64:Y64) -> 0 | L64: =SUM(AA64:AL64) -> 0
J65: =+K65+L65 -> 0 | K65: =SUM(N65:Y65) -> 0 | L65: =SUM(AA65:AL65) -> 0
... J252: =+K252+L252 -> 0 | K252: =SUM(N252:Y252) -> 0 | L252: =SUM(AA252:AL252) -> 0

Sheet W2
E2: ENTITY NAME : | G2: =+parameters!D2 -> Diam India | I2: ORDER BOOK SYNTHESIS in K€
E4: WEEK : | G4: W2 | I4: Cells to be filled in
E6: MONTH : | G6: =+VLOOKUP(G4, parameters!G:H, 2, 0) -> January
E8: TURNOVER | F8: =parameters!D4 -> k€ | H8: YTD Turnover | J8: =+G6&" Turnover" -> January Turnover | L8: Last estim. for the month: | O8: Forecast 2026
H9: =+"from January 1 until end of "&G4 -> from January 1 until end of W2 | J9: =+"from "&G6&" 1 until end of "&G4 -> from January 1 until end of W2 | L9: =+G6 -> January | O9: =+G4 -> W2 | P9: =+VLOOKUP(G4, parameters!$G$9:$I$61,3,0) -> W1 | Q9: Var
E10: EXTERNAL SALES INVOICED (=outside group) | H10: =J10 -> 93.43 | J10: 93.43 | L10: =J10+N17 -> 541.53462 | O10: =+H10+K17 -> 1178.6084 | P10: {=INDIRECT(ADDRESS(10,15,,,VLOOKUP($G$4,parameters!$G:$I,3,0)))} -> 935.63019 | Q10: =O10-P10 -> 242.97818
E11: GROUP SALES INVOICED | H11: =J11 -> 2.39 | J11: 2.39 | L11: =J11+N18 -> 5.2762906 | O11: =+H11+K18 -> 12.066436 | P11: {=INDIRECT(ADDRESS(11,15,,,VLOOKUP($G$4,parameters!$G:$I,3,0)))} -> 0 | Q11: =O11-P11 -> 12.066436 | S11: Definition orders : you consider the orders which are sure even if the order customers paper order is not yet received
E12: TOTAL | H12: =SUM(H10:H11) -> 95.82 | J12: =SUM(J10:J11) -> 95.82 | L12: =SUM(L10:L11) -> 546.81091 | O12: =SUM(O10:O11) -> 1190.6748 | P12: =SUM(P10:P11) -> 935.63019 | Q12: =O12-P12 -> 255.04462 | S12: The quantity, value, and delivery date can be changed before final delivery
E16: ORDERBOOK | F16: =+F8 -> k€ | J16: TOTAL ORDERBOOK | K16: Total amount 2026 | L16: Total amount 2027 | N16: 46023 | O16: 46054 | P16: 46082 | Q16: 46113 | R16: 46143 | S16: 46174 | T16: 46204 | U16: 46235 | V16: 46266 | W16: 46296 | X16: 46327 | Y16: 46357 | AA16: 46388 | AB16: 46419 | AC16: 46447 | AD16: 46478 | AE16: 46508 | AF16: 46539 | AG16: 46569 | AH16: 46600 | AI16: 46631 | AJ16: 46661 | AK16: 46692 | AL16: 46722
E17: External | J17: =+SUMIF($F$24:$F$251,"External",$J$24:$J$251) -> 1085.1784 | K17: =+SUMIF($F$24:$F$251,"External",$K$24:$K$251) -> 1085.1784 | L17: =+SUMIF($F$24:$F$251,"External",$L$24:$L$251) -> 0 | N17: =+SUMIF($F$24:$F$251,"External",N$24:N$251) -> 448.10462 | O17: =+SUMIF($F$24:$F$251,"External",O$24:O$251) -> 388.30574 | P17: =+SUMIF($F$24:$F$251,"External",P$24:P$251) -> 39.398119 | Q17: =+SUMIF($F$24:$F$251,"External",Q$24:Q$251) -> 155.89933 | R17: =+SUMIF($F$24:$F$251,"External",R$24:R$251) -> 41.482007 | S17: =+SUMIF($F$24:$F$251,"External",S$24:S$251) -> 11.988554 | T17: =+SUMIF($F$24:$F$251,"External",T$24:T$251) -> 0 | U17: =+SUMIF($F$24:$F$251,"External",U$24:U$251) -> 0 | ... Y17: =+SUMIF($F$24:$F$251,"External",Y$24:Y$251) -> 0 | AA17: =+SUMIF($F$24:$F$251,"External",AA$24:AA$251) -> 0 | AB17: =+SUMIF($F$24:$F$251,"External",AB$24:AB$251) -> 0 | AC17: =+SUMIF($F$24:$F$251,"External",AC$24:AC$251) -> 0 | AD17: =+SUMIF($F$24:$F$251,"External",AD$24:AD$251) -> 0 | AE17: =+SUMIF($F$24:$F$251,"External",AE$24:AE$251) -> 0 | AF17: =+SUMIF($F$24:$F$251,"External",AF$24:AF$251) -> 0 | AG17: =+SUMIF($F$24:$F$251,"External",AG$24:AG$251) -> 0 | AH17: =+SUMIF($F$24:$F$251,"External",AH$24:AH$251) -> 0 | ... AL17: =+SUMIF($F$24:$F$251,"External",AL$24:AL$251) -> 0
E18: Group | J18: =+SUMIF($F$24:$F$251,"Group",$J$24:$J$251) -> 9.676436 | K18: =+SUMIF($F$24:$F$251,"Group",$K$24:$K$251) -> 9.676436 | L18: =SUMIF($F$24:$F$251,"Group",$L$24:$L$251) -> 0 | N18: =+SUMIF($F$24:$F$251,"Group",N$24:N$251) -> 2.8862906 | O18: =+SUMIF($F$24:$F$251,"Group",O$24:O$251) -> 0 | P18: =+SUMIF($F$24:$F$251,"Group",P$24:P$251) -> 6.7901454 | Q18: =+SUMIF($F$24:$F$251,"Group",Q$24:Q$251) -> 0 | R18: =+SUMIF($F$24:$F$251,"Group",R$24:R$251) -> 0 | S18: =+SUMIF($F$24:$F$251,"Group",S$24:S$251) -> 0 | T18: =+SUMIF($F$24:$F$251,"Group",T$24:T$251) -> 0 | U18: =+SUMIF($F$24:$F$251,"Group",U$24:U$251) -> 0 | ... Y18: =+SUMIF($F$24:$F$251,"Group",Y$24:Y$251) -> 0 | AA18: =+SUMIF($F$24:$F$251,"Group",AA$24:AA$251) -> 0 | AB18: =+SUMIF($F$24:$F$251,"Group",AB$24:AB$251) -> 0 | AC18: =+SUMIF($F$24:$F$251,"Group",AC$24:AC$251) -> 0 | AD18: =+SUMIF($F$24:$F$251,"Group",AD$24:AD$251) -> 0 | AE18: =+SUMIF($F$24:$F$251,"Group",AE$24:AE$251) -> 0 | AF18: =+SUMIF($F$24:$F$251,"Group",AF$24:AF$251) -> 0 | AG18: =+SUMIF($F$24:$F$251,"Group",AG$24:AG$251) -> 0 | AH18: =+SUMIF($F$24:$F$251,"Group",AH$24:AH$251) -> 0 | ... AL18: =+SUMIF($F$24:$F$251,"Group",AL$24:AL$251) -> 0
E19: TOTAL | J19: =SUM(J17:J18) -> 1094.8548 | K19: =SUM(K17:K18) -> 1094.8548 | L19: =SUM(L17:L18) -> 0 | N19: =SUM(N17:N18) -> 450.99091 | O19: =SUM(O17:O18) -> 388.30574 | P19: =SUM(P17:P18) -> 46.188264 | Q19: =SUM(Q17:Q18) -> 155.89933 | R19: =SUM(R17:R18) -> 41.482007 | S19: =SUM(S17:S18) -> 11.988554 | T19: =SUM(T17:T18) -> 0 | U19: =SUM(U17:U18) -> 0 | ... Y19: =SUM(Y17:Y18) -> 0 | AA19: =SUM(AA17:AA18) -> 0 | AB19: =SUM(AB17:AB18) -> 0 | AC19: =SUM(AC17:AC18) -> 0 | AD19: =SUM(AD17:AD18) -> 0 | AE19: =SUM(AE17:AE18) -> 0 | AF19: =SUM(AF17:AF18) -> 0 | AG19: =SUM(AG17:AG18) -> 0 | AH19: =SUM(AH17:AH18) -> 0 | ... AL19: =SUM(AL17:AL18) -> 0
I21: check | J21: =IF(SUM(J24:J251)=J19, "OK", "Please correct: the sum of orders below is not equal to the total calculated above. Make sure to pick External or Group for each order and don't change the formulas in columns K and L") -> OK | N21: 2026 | AA21: 2027
E23: Order (Tooling including) to be delivered | F23: External or Group | G23: Brand Name | H23: Segment | I23: Outgroup | J23: TOTAL ORDERBOOK | K23: Total amount 2026 | L23: Total amount 2026 | N23: 46023 | O23: 46054 | P23: 46082 | Q23: 46113 | R23: 46143 | S23: 46174 | T23: 46204 | U23: 46235 | V23: 46266 | W23: 46296 | X23: 46327 | Y23: 46357 | AA23: 46388 | AB23: 46419 | AC23: 46447 | AD23: 46478 | AE23: 46508 | AF23: 46539 | AG23: 46569 | AH23: 46600 | AI23: 46631 | AJ23: 46661 | AK23: 46692 | AL23: 46722
D24: X | E24: BACCAROSE PERFUMES AND BEAUTY PRODUCTS PVT LTD | F24: External | G24: Laura Mercier | H24: Prestige Cosmetic | I24: CL0540 Laura Mercier | J24: =+K24+L24 -> 7.2617511 | K24: =SUM(N24:Y24) -> 7.2617511 | L24: =SUM(AA24:AL24) -> 0 | Q24: 7.2617511
E25: BACCAROSE PERFUMES AND BEAUTY PRODUCTS PVT LTD | F25: External | G25: Shiseido | H25: Prestige Cosmetic | I25: CL0285 Shiseido | J25: =+K25+L25 -> 19.0875 | K25: =SUM(N25:Y25) -> 19.0875 | L25: =SUM(AA25:AL25) -> 0 | P25: 19.0875
E26: Beauty Impex Pvt. Ltd | F26: External | G26: Guerlain | H26: Prestige Cosmetic | I26: CL0130 Guerlain | J26: =+K26+L26 -> 17.317858 | K26: =SUM(N26:Y26) -> 17.317858 | L26: =SUM(AA26:AL26) -> 0 | N26: 5.9515956 | O26: 11.366263
E27: Best In Brands | F27: External | G27: Shiseido | H27: Prestige Cosmetic | I27: CL0285 Shiseido | J27: =+K27+L27 -> 8.0682141 | K27: =SUM(N27:Y27) -> 8.0682141 | L27: =SUM(AA27:AL27) -> 0 | P27: 8.0682141
E28: CHANEL INDIA | F28: External | G28: Chanel | H28: Shopfitting | I28: CL0065 Chanel | J28: =+K28+L28 -> 5.922258 | K28: =SUM(N28:Y28) -> 5.922258 | L28: =SUM(AA28:AL28) -> 0 | N28: 5.922258
E29: Clarins Pte Ltd | F29: External | G29: Clarins | H29: Shopfitting | I29: CL0070 Clarins | J29: =+K29+L29 -> 2.8162104 | K29: =SUM(N29:Y29) -> 2.8162104 | L29: =SUM(AA29:AL29) -> 0 | N29: 2.8162104
E30: Coty | F30: External | G30: Coty Rimmel | H30: Shopfitting | I30: CL0080 Coty Rimmel | J30: =+K30+L30 -> 2.8140266 | K30: =SUM(N30:Y30) -> 2.8140266 | L30: =SUM(AA30:AL30) -> 0 | N30: 2.8140266
E31: DIAM Display Singapore | F31: Group | G31: Coty Rimmel | H31: Shopfitting | I31: CL0080 Coty Rimmel | J31: =+K31+L31 -> 9.676436 | K31: =SUM(N31:Y31) -> 9.676436 | L31: =SUM(AA31:AL31) -> 0 | N31: 2.8862906 | P31: 6.7901454
E32: Elca Cosmetics Pvt Ltd | F32: External | G32: Too Faced | H32: Prestige Cosmetic | I32: CL0575 Too Faced | J32: =+K32+L32 -> 39.996064 | K32: =SUM(N32:Y32) -> 39.996064 | L32: =SUM(AA32:AL32) -> 0 | N32: 39.996064
E33: ELCA Cosmetics Pvt. Ltd. | F33: External | G33: Clinique | H33: Prestige Cosmetic | I33: CL0075 Clinique | J33: =+K33+L33 -> 50.077315 | K33: =SUM(N33:Y33) -> 50.077315 | L33: =SUM(AA33:AL33) -> 0 | N33: 40.735585 | P33: 4.6708654 | S33: 4.6708654
E34: ELCA Cosmetics Pvt. Ltd. | F34: External | G34: Dr Jart+ | H34: Prestige Cosmetic | I34: CL0680 Estée Lauder - other brands | J34: =+K34+L34 -> 3.1881163 | K34: =SUM(N34:Y34) -> 3.1881163 | L34: =SUM(AA34:AL34) -> 0 | N34: 3.1881163
E35: ELCA Cosmetics Pvt. Ltd. | F35: External | G35: Estee Lauder | H35: Prestige Cosmetic | I35: CL0110 Estée Lauder | J35: =+K35+L35 -> 50.54466 | K35: =SUM(N35:Y35) -> 50.54466 | L35: =SUM(AA35:AL35) -> 0 | N35: 43.172395 | O35: 2.7014 | P35: 2.3354327 | S35: 2.3354327
E36: ELCA Cosmetics Pvt. Ltd. | F36: External | G36: Mac | H36: Prestige Cosmetic | I36: CL0395 MAC | J36: =+K36+L36 -> 16.992312 | K36: =SUM(N36:Y36) -> 16.992312 | L36: =SUM(AA36:AL36) -> 0 | N36: 7.9570146 | R36: 9.035297
E37: ELCA Cosmetics Pvt. Ltd. | F37: External | G37: Smashbox | H37: Prestige Cosmetic | I37: CL0525 Smashbox | J37: =+K37+L37 -> 3.2735576 | K37: =SUM(N37:Y37) -> 3.2735576 | L37: =SUM(AA37:AL37) -> 0 | P37: 1.6367788 | S37: 1.6367788
E38: ELCA Cosmetics Pvt. Ltd. | F38: External | G38: The Ordinary | H38: Prestige Cosmetic | I38: CL0680 Estée Lauder - other brands | J38: =+K38+L38 -> 18.166287 | K38: =SUM(N38:Y38) -> 18.166287 | L38: =SUM(AA38:AL38) -> 0 | N38: 15.152247 | P38: 1.50702 | S38: 1.50702
E39: ELCA Cosmetics Pvt. Ltd. | F39: External | G39: Tom Ford | H39: Prestige Cosmetic | I39: CL0570 Tom Ford | J39: =+K39+L39 -> 26.053007 | K39: =SUM(N39:Y39) -> 26.053007 | L39: =SUM(AA39:AL39) -> 0 | N39: 24.496051 | P39: 0.7784776 | S39: 0.7784776
E40: ELCA Cosmetics Pvt. Ltd. | F40: External | G40: Too Faced | H40: Prestige Cosmetic | I40: CL0575 Too Faced | J40: =+K40+L40 -> 157.2171 | K40: =SUM(N40:Y40) -> 157.2171 | L40: =SUM(AA40:AL40) -> 0 | O40: 155.09714 | P40: 1.05998 | S40: 1.05998
E41: Estee Lauder AG Lachen | F41: External | G41: Jo Malone | H41: Prestige Cosmetic | I41: CL0535 Joe Malone | J41: =+K41+L41 -> 0.2784152 | K41: =SUM(N41:Y41) -> 0.2784152 | L41: =SUM(AA41:AL41) -> 0 | N41: 0.2784152
E42: Fenty Beauty LLC | F42: External | G42: Fenty | H42: Prestige Cosmetic | I42: CL0550 Kendo - Fenty | J42: =+K42+L42 -> 9.0120765 | K42: =SUM(N42:Y42) -> 9.0120765 | L42: =SUM(AA42:AL42) -> 0 | N42: 9.0120765
E43: Forma Brands, LLC f/k/a FB Acquisition LLC | F43: External | G43: Forma | H43: Prestige Cosmetic | I43: CL0735 Morphe | J43: =+K43+L43 -> 53.752461 | K43: =SUM(N43:Y43) -> 53.752461 | L43: =SUM(AA43:AL43) -> 0 | O43: 53.752461
E44: Global Shoppers Stop Beauty Brands Ltd | F44: External | G44: Clarins | H44: Shopfitting | I44: CL0070 Clarins | J44: =+K44+L44 -> 3.0947403 | K44: =SUM(N44:Y44) -> 3.0947403 | L44: =SUM(AA44:AL44) -> 0 | N44: 3.0947403
E45: Global Shoppers Stop Beauty Brands Ltd | F45: External | G45: Nars | H45: Prestige Cosmetic | I45: CL0226 Nars | J45: =+K45+L45 -> 112.31055 | K45: =SUM(N45:Y45) -> 112.31055 | L45: =SUM(AA45:AL45) -> 0 | N45: 0.84615 | O45: 46.31097 | P45: 0.25385 | Q45: 32.45287 | R45: 32.44671
E46: Global Shoppers Stop Beauty Brands Ltd | F46: External | G46: Prada | H46: Shopfitting | I46: CL0180 L'Oréal Divers | J46: =+K46+L46 -> 23.23065 | K46: =SUM(N46:Y46) -> 23.23065 | L46: =SUM(AA46:AL46) -> 0 | N46: 23.23065
E47: Indosing Distribution | F47: External | G47: Benefit | H47: Prestige Cosmetic | I47: CL0315 Benefit | J47: =+K47+L47 -> 10.12327 | K47: =SUM(N47:Y47) -> 10.12327 | L47: =SUM(AA47:AL47) -> 0 | N47: 10.12327
E48: L Beauty Pte | F48: External | G48: Benefit | H48: Prestige Cosmetic | I48: CL0315 Benefit | J48: =+K48+L48 -> 17.257267 | K48: =SUM(N48:Y48) -> 17.257267 | L48: =SUM(AA48:AL48) -> 0 | N48: 5.9646117 | O48: 11.292655
E49: L'Oreal India | F49: External | G49: Lancome | H49: Prestige Cosmetic | I49: CL0155 Lancôme | J49: =+K49+L49 -> 32.380149 | K49: =SUM(N49:Y49) -> 32.380149 | L49: =SUM(AA49:AL49) -> 0 | N49: 26.343352 | O49: 6.0367966
E50: L'Oreal India | F50: External | G50: Lancome | H50: Shopfitting | I50: CL0155 Lancôme | J50: =+K50+L50 -> 10.102618 | K50: =SUM(N50:Y50) -> 10.102618 | L50: =SUM(AA50:AL50) -> 0 | N50: 10.102618
E51: L'Oreal India | F51: External | G51: YSL | H51: Shopfitting | I51: CL0310 YSL | J51: =+K51+L51 -> 59.01295 | K51: =SUM(N51:Y51) -> 59.01295 | L51: =SUM(AA51:AL51) -> 0 | N51: 59.01295
E52: L'Oreal Travel Retail | F52: External | G52: Armani | H52: Shopfitting | I52: CL0345 Armani | J52: =+K52+L52 -> 33.203858 | K52: =SUM(N52:Y52) -> 33.203858 | L52: =SUM(AA52:AL52) -> 0 | O52: 2.0697759 | Q52: 31.134083
E53: L'Oreal Travel Retail | F53: External | G53: Lancome | H53: Shopfitting | I53: CL0155 Lancôme | J53: =+K53+L53 -> 16.502558 | K53: =SUM(N53:Y53) -> 16.502558 | L53: =SUM(AA53:AL53) -> 0 | Q53: 16.502558
E54: L'Oreal Travel Retail | F54: External | G54: Loreal Paris | H54: Shopfitting | I54: CL0170 L'Oréal Paris (L'OAP) | J54: =+K54+L54 -> 8.9014259 | K54: =SUM(N54:Y54) -> 8.9014259 | L54: =SUM(AA54:AL54) -> 0 | O54: 8.9014259
E55: L'Oreal Travel Retail | F55: External | G55: Multi | H55: Shopfitting | I55: CL0180 L'Oréal Divers | J55: =+K55+L55 -> 59.741114 | K55: =SUM(N55:Y55) -> 59.741114 | L55: =SUM(AA55:AL55) -> 0 | Q55: 59.741114
E56: L'Oreal Travel Retail | F56: External | G56: OAP | H56: Shopfitting | I56: CL0180 L'Oréal Divers | J56: =+K56+L56 -> 8.8069593 | K56: =SUM(N56:Y56) -> 8.8069593 | L56: =SUM(AA56:AL56) -> 0 | Q56: 8.8069593
E57: L'Oreal Travel Retail | F57: External | G57: RALPH LAUREN | H57: Shopfitting | I57: CL0405 Ralph Lauren | J57: =+K57+L57 -> 1.7512968 | K57: =SUM(N57:Y57) -> 1.7512968 | L57: =SUM(AA57:AL57) -> 0 | O57: 1.7512968
E58: Puig India | F58: External | G58: PUIG Brands | H58: Shopfitting | I58: CL0840 Puig - other brands | J58: =+K58+L58 -> 41.48435 | K58: =SUM(N58:Y58) -> 41.48435 | L58: =SUM(AA58:AL58) -> 0 | N58: 41.48435
E59: Rare Beauty LLC | F59: External | G59: Rare Beauty | H59: Prestige Cosmetic | I59: CL0765 Rare Beauty | J59: =+K59+L59 -> 97.434975 | K59: =SUM(N59:Y59) -> 97.434975 | L59: =SUM(AA59:AL59) -> 0 | N59: 40.899213 | O59: 56.535761
E60: Reliance Luxe Beauty Limited | F60: External | G60: Rare Beauty | H60: Prestige Cosmetic | I60: CL0765 Rare Beauty | J60: =+K60+L60 -> 15.972842 | K60: =SUM(N60:Y60) -> 15.972842 | L60: =SUM(AA60:AL60) -> 0 | O60: 15.972842
E61: Shoppers Stop Ltd | F61: External | G61: Clinique | H61: Prestige Cosmetic | I61: CL0075 Clinique | J61: =+K61+L61 -> 3.321 | K61: =SUM(N61:Y61) -> 3.321 | L61: =SUM(AA61:AL61) -> 0 | O61: 3.321
E62: Shoppers Stop Ltd | F62: External | G62: Estee Lauder - Multi Brands | H62: Prestige Cosmetic | I62: CL9999 Other | J62: =+K62+L62 -> 25.510656 | K62: =SUM(N62:Y62) -> 25.510656 | L62: =SUM(AA62:AL62) -> 0 | N62: 25.510656
E63: Shoppers Stop Ltd | F63: External | G63: Tom Ford | H63: Shopfitting | I63: CL0570 Tom Ford | J63: =+K63+L63 -> 13.19595 | K63: =SUM(N63:Y63) -> 13.19595 | L63: =SUM(AA63:AL63) -> 0 | O63: 13.19595
J64: =+K64+L64 -> 0 | K64: =SUM(N64:Y64) -> 0 | L64: =SUM(AA64:AL64) -> 0
J65: =+K65+L65 -> 0 | K65: =SUM(N65:Y65) -> 0 | L65: =SUM(AA65:AL65) -> 0
J66: =+K66+L66 -> 0 | K66: =SUM(N66:Y66) -> 0 | L66: =SUM(AA66:AL66) -> 0
J67: =+K67+L67 -> 0 | K67: =SUM(N67:Y67) -> 0 | L67: =SUM(AA67:AL67) -> 0
J68: =+K68+L68 -> 0 | K68: =SUM(N68:Y68) -> 0 | L68: =SUM(AA68:AL68) -> 0
J69: =+K69+L69 -> 0 | K69: =SUM(N69:Y69) -> 0 | L69: =SUM(AA69:AL69) -> 0
J70: =+K70+L70 -> 0 | K70: =SUM(N70:Y70) -> 0 | L70: =SUM(AA70:AL70) -> 0
J71: =+K71+L71 -> 0 | K71: =SUM(N71:Y71) -> 0 | L71: =SUM(AA71:AL71) -> 0
J72: =+K72+L72 -> 0 | K72: =SUM(N72:Y72) -> 0 | L72: =SUM(AA72:AL72) -> 0
J73: =+K73+L73 -> 0 | K73: =SUM(N73:Y73) -> 0 | L73: =SUM(AA73:AL73) -> 0
J74: =+K74+L74 -> 0 | K74: =SUM(N74:Y74) -> 0 | L74: =SUM(AA74:AL74) -> 0
J75: =+K75+L75 -> 0 | K75: =SUM(N75:Y75) -> 0 | L75: =SUM(AA75:AL75) -> 0
... J252: =+K252+L252 -> 0 | K252: =SUM(N252:Y252) -> 0 | L252: =SUM(AA252:AL252) -> 0
E255: Deferred revenue balance as on | F255: 45992 | G255: 271.35 | H255: K Euro
E256: Add: Deferred revenue addition during Dec-25 | G256: 138.52 | H256: K Euro
E257: Less: Deferred revenue reversed during Dec-25 | G257: 192.25 | H257: K Euro
E258: Deferred revenue balance as on | F258: 46022 | G258: =G255+G256-G257 -> 217.62 | H258: K Euro
E260: Brand | H260: Amt. in K Euro
E261: ARMANI PRIVE | H261: 2.0697759
E262: Benefit | H262: 29.209133
E263: CH, RB & JPG | H263: 41.48435
E264: Clarins | H264: 5.9109507
E265: Clinique | H265: 9.9668237
E266: Coty | H266: 12.218725
E267: Estee Lauder | H267: 9.233877
E268: Fenty Beauty | H268: 10.634785
E269: Forma | H269: 53.752461
E270: Guerlain | H270: 11.366263
E271: Lancome | H271: 7.7886
E272: Prada | H272: 23.23065
... E278: Too Faced | H278: 2.11996
E281: Actual Orderbook of last week | H281: ='W1'!K19 -> 925.49593
E282: New Orders in Current Week | H282: =#REF! -> #REF!
E283: Sales booked in current week | H283: =J12-'W1'!J12 -> 85.68574
E284: Standard Orderbook should be in Current Week | H284: =H281+H282-H283 -> #REF!
E285: Actual Orderbook in Current Week | H285: =K19 -> 1094.8548
E286: Difference | H286: =H284-H285 -> #REF! | I286: Check whether new orders are reported correctly or invoiced order have been removed from the sales dashboard.
I287: deferred revenue

Sheet W3
E2: ENTITY NAME : | G2: =+parameters!D2 -> Diam India | I2: ORDER BOOK SYNTHESIS in K€
E4: WEEK : | G4: W3 | I4: Cells to be filled in
E6: MONTH : | G6: =+VLOOKUP(G4, parameters!G:H, 2, 0) -> January
E8: TURNOVER | F8: =parameters!D4 -> k€ | H8: YTD Turnover | J8: =+G6&" Turnover" -> January Turnover | L8: Last estim. for the month: | O8: Forecast 2026
H9: =+"from January 1 until end of "&G4 -> from January 1 until end of W3 | J9: =+"from "&G6&" 1 until end of "&G4 -> from January 1 until end of W3 | L9: =+G6 -> January | O9: =+G4 -> W3 | P9: =+VLOOKUP(G4, parameters!$G$9:$I$61,3,0) -> W2 | Q9: Var
E10: EXTERNAL SALES INVOICED (=outside group) | H10: 228 | J10: 228 | L10: =J10+N17 -> 659.92081 | O10: =+H10+K17 -> 1474.7035 | P10: {=INDIRECT(ADDRESS(10,15,,,VLOOKUP($G$4,parameters!$G:$I,3,0)))} -> 1178.6084 | Q10: =O10-P10 -> 296.0951
E11: GROUP SALES INVOICED | H11: 2.38956 | J11: 2.38956 | L11: =J11+N18 -> 11.074109 | O11: =+H11+K18 -> 17.864254 | P11: {=INDIRECT(ADDRESS(11,15,,,VLOOKUP($G$4,parameters!$G:$I,3,0)))} -> 12.066436 | Q11: =O11-P11 -> 5.7978183 | S11: Definition orders : you consider the orders which are sure even if the order customers paper order is not yet received
E12: TOTAL | H12: =SUM(H10:H11) -> 230.38956 | J12: =SUM(J10:J11) -> 230.38956 | L12: =SUM(L10:L11) -> 670.99492 | O12: =SUM(O10:O11) -> 1492.5677 | P12: =SUM(P10:P11) -> 1190.6748 | Q12: =O12-P12 -> 301.89292 | S12: The quantity, value, and delivery date can be changed before final delivery
E16: ORDERBOOK | F16: =+F8 -> k€ | J16: TOTAL ORDERBOOK | K16: Total amount 2026 | L16: Total amount 2027 | N16: 46023 | O16: 46054 | P16: 46082 | Q16: 46113 | R16: 46143 | S16: 46174 | T16: 46204 | U16: 46235 | V16: 46266 | W16: 46296 | X16: 46327 | Y16: 46357 | AA16: 46388 | AB16: 46419 | AC16: 46447 | AD16: 46478 | AE16: 46508 | AF16: 46539 | AG16: 46569 | AH16: 46600 | AI16: 46631 | AJ16: 46661 | AK16: 46692 | AL16: 46722
E17: External | J17: =+SUMIF($F$24:$F$251,"External",$J$24:$J$251) -> 1246.7035 | K17: =+SUMIF($F$24:$F$251,"External",$K$24:$K$251) -> 1246.7035 | L17: =+SUMIF($F$24:$F$251,"External",$L$24:$L$251) -> 0 | N17: =+SUMIF($F$24:$F$251,"External",N$24:N$251) -> 431.92081 | O17: =+SUMIF($F$24:$F$251,"External",O$24:O$251) -> 467.13681 | P17: =+SUMIF($F$24:$F$251,"External",P$24:P$251) -> 164.10562 | Q17: =+SUMIF($F$24:$F$251,"External",Q$24:Q$251) -> 123.44646 | R17: =+SUMIF($F$24:$F$251,"External",R$24:R$251) -> 9.035297 | S17: =+SUMIF($F$24:$F$251,"External",S$24:S$251) -> 39.069912 | T17: =+SUMIF($F$24:$F$251,"External",T$24:T$251) -> 11.988554 | U17: =+SUMIF($F$24:$F$251,"External",U$24:U$251) -> 0 | ... Y17: =+SUMIF($F$24:$F$251,"External",Y$24:Y$251) -> 0 | AA17: =+SUMIF($F$24:$F$251,"External",AA$24:AA$251) -> 0 | AB17: =+SUMIF($F$24:$F$251,"External",AB$24:AB$251) -> 0 | AC17: =+SUMIF($F$24:$F$251,"External",AC$24:AC$251) -> 0 | AD17: =+SUMIF($F$24:$F$251,"External",AD$24:AD$251) -> 0 | AE17: =+SUMIF($F$24:$F$251,"External",AE$24:AE$251) -> 0 | AF17: =+SUMIF($F$24:$F$251,"External",AF$24:AF$251) -> 0 | AG17: =+SUMIF($F$24:$F$251,"External",AG$24:AG$251) -> 0 | AH17: =+SUMIF($F$24:$F$251,"External",AH$24:AH$251) -> 0 | ... AL17: =+SUMIF($F$24:$F$251,"External",AL$24:AL$251) -> 0
E18: Group | J18: =+SUMIF($F$24:$F$251,"Group",$J$24:$J$251) -> 15.474694 | K18: =+SUMIF($F$24:$F$251,"Group",$K$24:$K$251) -> 15.474694 | L18: =SUMIF($F$24:$F$251,"Group",$L$24:$L$251) -> 0 | N18: =+SUMIF($F$24:$F$251,"Group",N$24:N$251) -> 8.6845489 | O18: =+SUMIF($F$24:$F$251,"Group",O$24:O$251) -> 0 | P18: =+SUMIF($F$24:$F$251,"Group",P$24:P$251) -> 6.7901454 | Q18: =+SUMIF($F$24:$F$251,"Group",Q$24:Q$251) -> 0 | R18: =+SUMIF($F$24:$F$251,"Group",R$24:R$251) -> 0 | S18: =+SUMIF($F$24:$F$251,"Group",S$24:S$251) -> 0 | T18: =+SUMIF($F$24:$F$251,"Group",T$24:T$251) -> 0 | U18: =+SUMIF($F$24:$F$251,"Group",U$24:U$251) -> 0 | ... Y18: =+SUMIF($F$24:$F$251,"Group",Y$24:Y$251) -> 0 | AA18: =+SUMIF($F$24:$F$251,"Group",AA$24:AA$251) -> 0 | AB18: =+SUMIF($F$24:$F$251,"Group",AB$24:AB$251) -> 0 | AC18: =+SUMIF($F$24:$F$251,"Group",AC$24:AC$251) -> 0 | AD18: =+SUMIF($F$24:$F$251,"Group",AD$24:AD$251) -> 0 | AE18: =+SUMIF($F$24:$F$251,"Group",AE$24:AE$251) -> 0 | AF18: =+SUMIF($F$24:$F$251,"Group",AF$24:AF$251) -> 0 | AG18: =+SUMIF($F$24:$F$251,"Group",AG$24:AG$251) -> 0 | AH18: =+SUMIF($F$24:$F$251,"Group",AH$24:AH$251) -> 0 | ... AL18: =+SUMIF($F$24:$F$251,"Group",AL$24:AL$251) -> 0
E19: TOTAL | J19: =SUM(J17:J18) -> 1262.1782 | K19: =SUM(K17:K18) -> 1262.1782 | L19: =SUM(L17:L18) -> 0 | N19: =SUM(N17:N18) -> 440.60536 | O19: =SUM(O17:O18) -> 467.13681 | P19: =SUM(P17:P18) -> 170.89577 | Q19: =SUM(Q17:Q18) -> 123.44646 | R19: =SUM(R17:R18) -> 9.035297 | S19: =SUM(S17:S18) -> 39.069912 | T19: =SUM(T17:T18) -> 11.988554 | U19: =SUM(U17:U18) -> 0 | ... Y19: =SUM(Y17:Y18) -> 0 | AA19: =SUM(AA17:AA18) -> 0 | AB19: =SUM(AB17:AB18) -> 0 | AC19: =SUM(AC17:AC18) -> 0 | AD19: =SUM(AD17:AD18) -> 0 | AE19: =SUM(AE17:AE18) -> 0 | AF19: =SUM(AF17:AF18) -> 0 | AG19: =SUM(AG17:AG18) -> 0 | AH19: =SUM(AH17:AH18) -> 0 | ... AL19: =SUM(AL17:AL18) -> 0
I21: check | J21: =IF(SUM(J24:J251)=J19, "OK", "Please correct: the sum of orders below is not equal to the total calculated above. Make sure to pick External or Group for each order and don't change the formulas in columns K and L") -> OK | N21: 2026 | AA21: 2027
E23: Order (Tooling including) to be delivered | F23: External or Group | G23: Customers orders | H23: Segment | I23: Outgroup | J23: TOTAL ORDERBOOK | K23: Total amount 2026 | L23: Total amount 2026 | N23: 46023 | O23: 46054 | P23: 46082 | Q23: 46113 | R23: 46143 | S23: 46174 | T23: 46204 | U23: 46235 | V23: 46266 | W23: 46296 | X23: 46327 | Y23: 46357 | AA23: 46388 | AB23: 46419 | AC23: 46447 | AD23: 46478 | AE23: 46508 | AF23: 46539 | AG23: 46569 | AH23: 46600 | AI23: 46631 | AJ23: 46661 | AK23: 46692 | AL23: 46722
D24: X | E24: Gucci | F24: External | G24: BACCAROSE PERFUMES AND BEAUTY PRODUCTS PVT LTD | H24: Shopfitting | I24: CL0920 Coty - other brands | J24: =+K24+L24 -> 1.52838 | K24: =SUM(N24:Y24) -> 1.52838 | L24: =SUM(AA24:AL24) -> 0 | N24: 1.52838
E25: Laura Mercier | F25: External | G25: BACCAROSE PERFUMES AND BEAUTY PRODUCTS PVT LTD | H25: Prestige Cosmetic | I25: CL0540 Laura Mercier | J25: =+K25+L25 -> 7.2617511 | K25: =SUM(N25:Y25) -> 7.2617511 | L25: =SUM(AA25:AL25) -> 0 | Q25: 7.2617511
E26: Shiseido | F26: External | G26: BACCAROSE PERFUMES AND BEAUTY PRODUCTS PVT LTD | H26: Prestige Cosmetic | I26: CL0285 Shiseido | J26: =+K26+L26 -> 19.0875 | K26: =SUM(N26:Y26) -> 19.0875 | L26: =SUM(AA26:AL26) -> 0 | P26: 19.0875
E27: Guerlain | F27: External | G27: Beauty Impex Pvt. Ltd | H27: Prestige Cosmetic | I27: CL0130 Guerlain | J27: =+K27+L27 -> 29.542426 | K27: =SUM(N27:Y27) -> 29.542426 | L27: =SUM(AA27:AL27) -> 0 | N27: 18.176164 | O27: 11.366263
E28: Shiseido | F28: External | G28: Best In Brands | H28: Prestige Cosmetic | I28: CL0285 Shiseido | J28: =+K28+L28 -> 8.0682141 | K28: =SUM(N28:Y28) -> 8.0682141 | L28: =SUM(AA28:AL28) -> 0 | P28: 8.0682141
E29: Chanel | F29: External | G29: CHANEL INDIA | H29: Shopfitting | I29: CL0065 Chanel | J29: =+K29+L29 -> 5.922258 | K29: =SUM(N29:Y29) -> 5.922258 | L29: =SUM(AA29:AL29) -> 0 | N29: 5.922258
E30: Clarins | F30: External | G30: Clarins Pte Ltd | H30: Shopfitting | I30: CL0070 Clarins | J30: =+K30+L30 -> 2.8162104 | K30: =SUM(N30:Y30) -> 2.8162104 | L30: =SUM(AA30:AL30) -> 0 | N30: 2.8162104
E31: L'Oreal TR | F31: External | G31: Connectiv FZCO | H31: Shopfitting | I31: CL0170 L'Oréal Paris (L'OAP) | J31: =+K31+L31 -> 0.8584046 | K31: =SUM(N31:Y31) -> 0.8584046 | L31: =SUM(AA31:AL31) -> 0 | P31: 0.8584046
E32: Coty | F32: External | G32: Coty | H32: Shopfitting | I32: CL0920 Coty - other brands | J32: =+K32+L32 -> 2.7684359 | K32: =SUM(N32:Y32) -> 2.7684359 | L32: =SUM(AA32:AL32) -> 0 | N32: 2.7684359
E33: Coty | F33: Group | G33: DIAM Display Singapore | H33: Shopfitting | I33: CL0920 Coty - other brands | J33: =+K33+L33 -> 8.3150404 | K33: =SUM(N33:Y33) -> 8.3150404 | L33: =SUM(AA33:AL33) -> 0 | N33: 1.524895 | P33: 6.7901454
E34: Fenty Beauty | F34: Group | G34: DIAM Turkey | H34: Prestige Cosmetic | I34: CL0550 Kendo - Fenty | J34: =+K34+L34 -> 7.1596539 | K34: =SUM(N34:Y34) -> 7.1596539 | L34: =SUM(AA34:AL34) -> 0 | N34: 7.1596539
E35: Too Faced | F35: External | G35: Elca Cosmetics Pvt Ltd | H35: Prestige Cosmetic | I35: CL0575 Too Faced | J35: =+K35+L35 -> 39.069912 | K35: =SUM(N35:Y35) -> 39.069912 | L35: =SUM(AA35:AL35) -> 0 | S35: 39.069912
E36: Clinique | F36: External | G36: ELCA Cosmetics Pvt. Ltd. | H36: Prestige Cosmetic | I36: CL0075 Clinique | J36: =+K36+L36 -> 59.043613 | K36: =SUM(N36:Y36) -> 59.043613 | L36: =SUM(AA36:AL36) -> 0 | N36: 54.372748 | P36: 2.3354327 | T36: 2.3354327
E37: Dr Jart+ | F37: External | G37: ELCA Cosmetics Pvt. Ltd. | H37: Prestige Cosmetic | I37: CL0680 Estée Lauder - other brands | J37: =+K37+L37 -> 3.1881163 | K37: =SUM(N37:Y37) -> 3.1881163 | L37: =SUM(AA37:AL37) -> 0 | P37: 3.1881163
E38: Estee Lauder | F38: External | G38: ELCA Cosmetics Pvt. Ltd. | H38: Prestige Cosmetic | I38: CL0110 Estée Lauder | J38: =+K38+L38 -> 170.93034 | K38: =SUM(N38:Y38) -> 170.93034 | L38: =SUM(AA38:AL38) -> 0 | N38: 77.954743 | O38: 88.304735 | P38: 2.3354327 | T38: 2.3354327
E39: Mac | F39: External | G39: ELCA Cosmetics Pvt. Ltd. | H39: Prestige Cosmetic | I39: CL0395 MAC | J39: =+K39+L39 -> 13.706164 | K39: =SUM(N39:Y39) -> 13.706164 | L39: =SUM(AA39:AL39) -> 0 | N39: 2e-06 | P39: 2.3354327 | R39: 9.035297 | T39: 2.3354327
E40: Smashbox | F40: External | G40: ELCA Cosmetics Pvt. Ltd. | H40: Prestige Cosmetic | I40: CL0525 Smashbox | J40: =+K40+L40 -> 3.2735576 | K40: =SUM(N40:Y40) -> 3.2735576 | L40: =SUM(AA40:AL40) -> 0 | P40: 1.6367788 | T40: 1.6367788
E41: The Ordinary | F41: External | G41: ELCA Cosmetics Pvt. Ltd. | H41: Prestige Cosmetic | I41: CL0680 Estée Lauder - other brands | J41: =+K41+L41 -> 14.566856 | K41: =SUM(N41:Y41) -> 14.566856 | L41: =SUM(AA41:AL41) -> 0 | N41: 0.0386618 | P41: 13.021174 | T41: 1.50702
E42: Tom Ford | F42: External | G42: ELCA Cosmetics Pvt. Ltd. | H42: Prestige Cosmetic | I42: CL0570 Tom Ford | J42: =+K42+L42 -> 26.053007 | K42: =SUM(N42:Y42) -> 26.053007 | L42: =SUM(AA42:AL42) -> 0 | P42: 25.274529 | T42: 0.7784776
E43: Too Faced | F43: External | G43: ELCA Cosmetics Pvt. Ltd. | H43: Prestige Cosmetic | I43: CL0575 Too Faced | J43: =+K43+L43 -> 157.2171 | K43: =SUM(N43:Y43) -> 157.2171 | L43: =SUM(AA43:AL43) -> 0 | O43: 155.09714 | P43: 1.05998 | T43: 1.05998
E44: Jo Malone | F44: External | G44: Estee Lauder AG Lachen | H44: Prestige Cosmetic | I44: CL0535 Joe Malone | J44: =+K44+L44 -> 0.2784152 | K44: =SUM(N44:Y44) -> 0.2784152 | L44: =SUM(AA44:AL44) -> 0 | N44: 0.2784152
E45: Fenty Beauty | F45: External | G45: Fenty Beauty LLC | H45: Prestige Cosmetic | I45: CL0550 Kendo - Fenty | J45: =+K45+L45 -> 66.905009 | K45: =SUM(N45:Y45) -> 66.905009 | L45: =SUM(AA45:AL45) -> 0 | N45: 66.905009
E46: Forma | F46: External | G46: Forma Brands, LLC f/k/a FB Acquisition LLC | H46: Prestige Cosmetic | I46: CL0735 Morphe | J46: =+K46+L46 -> 53.752461 | K46: =SUM(N46:Y46) -> 53.752461 | L46: =SUM(AA46:AL46) -> 0 | O46: 53.752461
E47: Clarins | F47: External | G47: Global Shoppers Stop Beauty Brands Ltd | H47: Shopfitting | I47: CL0070 Clarins | J47: =+K47+L47 -> 0 | K47: =SUM(N47:Y47) -> 0 | L47: =SUM(AA47:AL47) -> 0 | N47: 0
E48: Nars | F48: External | G48: Global Shoppers Stop Beauty Brands Ltd | H48: Prestige Cosmetic | I48: CL0226 Nars | J48: =+K48+L48 -> 111.4644 | K48: =SUM(N48:Y48) -> 111.4644 | L48: =SUM(AA48:AL48) -> 0 | N48: -3.8e-06 | O48: 32.2061 | P48: 79.2583
E49: Prada | F49: External | G49: Global Shoppers Stop Beauty Brands Ltd | H49: Shopfitting | I49: CL0180 L'Oréal Divers | J49: =+K49+L49 -> 0.7934307 | K49: =SUM(N49:Y49) -> 0.7934307 | L49: =SUM(AA49:AL49) -> 0 | N49: 0.7934307
E50: Benefit | F50: External | G50: Indosing Distribution | H50: Prestige Cosmetic | I50: CL0315 Benefit | J50: =+K50+L50 -> 10.12327 | K50: =SUM(N50:Y50) -> 10.12327 | L50: =SUM(AA50:AL50) -> 0 | N50: 10.12327
E51: Benefit | F51: External | G51: L Beauty Pte | H51: Prestige Cosmetic | I51: CL0315 Benefit | J51: =+K51+L51 -> 17.257267 | K51: =SUM(N51:Y51) -> 17.257267 | L51: =SUM(AA51:AL51) -> 0 | N51: 5.9646117 | O51: 5.6463275 | P51: 5.6463275
E52: Lancome | F52: External | G52: L'Oreal India | H52: Prestige Cosmetic | I52: CL0155 Lancôme | J52: =+K52+L52 -> 14.834826 | K52: =SUM(N52:Y52) -> 14.834826 | L52: =SUM(AA52:AL52) -> 0 | N52: 7.1145315 | O52: 7.7202947
E53: Lancome | F53: External | G53: L'Oreal India | H53: Shopfitting | I53: CL0155 Lancôme | J53: =+K53+L53 -> 10.102618 | K53: =SUM(N53:Y53) -> 10.102618 | L53: =SUM(AA53:AL53) -> 0 | O53: 10.102618
E54: Lancome | F54: External | G54: L'Oreal India | H54: Prestige Cosmetic | I54: CL0155 Lancôme | J54: =+K54+L54 -> 6.6643161 | K54: =SUM(N54:Y54) -> 6.6643161 | L54: =SUM(AA54:AL54) -> 0 | N54: 6.6643161
E55: YSL | F55: External | G55: L'Oreal India | H55: Shopfitting | I55: CL0310 YSL | J55: =+K55+L55 -> 64.308334 | K55: =SUM(N55:Y55) -> 64.308334 | L55: =SUM(AA55:AL55) -> 0 | N55: 63.115516 | O55: 1.1928188
E56: Armani | F56: External | G56: L'Oreal Travel Retail | H56: Shopfitting | I56: CL0345 Armani | J56: =+K56+L56 -> 31.134083 | K56: =SUM(N56:Y56) -> 31.134083 | L56: =SUM(AA56:AL56) -> 0 | Q56: 31.134083
E57: ARMANI PRIVE | F57: External | G57: L'Oreal Travel Retail | H57: Shopfitting | I57: CL0180 L'Oréal Divers | J57: =+K57+L57 -> 2.0697759 | K57: =SUM(N57:Y57) -> 2.0697759 | L57: =SUM(AA57:AL57) -> 0 | O57: 2.0697759
E58: Lancome | F58: External | G58: L'Oreal Travel Retail | H58: Shopfitting | I58: CL0155 Lancôme | J58: =+K58+L58 -> 16.502558 | K58: =SUM(N58:Y58) -> 16.502558 | L58: =SUM(AA58:AL58) -> 0 | Q58: 16.502558
E59: Loreal Paris | F59: External | G59: L'Oreal Travel Retail | H59: Shopfitting | I59: CL0170 L'Oréal Paris (L'OAP) | J59: =+K59+L59 -> 8.9014259 | K59: =SUM(N59:Y59) -> 8.9014259 | L59: =SUM(AA59:AL59) -> 0 | O59: 8.9014259
E60: Multi | F60: External | G60: L'Oreal Travel Retail | H60: Shopfitting | I60: CL0180 L'Oréal Divers | J60: =+K60+L60 -> 59.741114 | K60: =SUM(N60:Y60) -> 59.741114 | L60: =SUM(AA60:AL60) -> 0 | Q60: 59.741114
E61: OAP | F61: External | G61: L'Oreal Travel Retail | H61: Shopfitting | I61: CL0180 L'Oréal Divers | J61: =+K61+L61 -> 8.8069593 | K61: =SUM(N61:Y61) -> 8.8069593 | L61: =SUM(AA61:AL61) -> 0 | Q61: 8.8069593
E62: RALPH LAUREN | F62: External | G62: L'Oreal Travel Retail | H62: Shopfitting | I62: CL0405 Ralph Lauren | J62: =+K62+L62 -> 1.7512968 | K62: =SUM(N62:Y62) -> 1.7512968 | L62: =SUM(AA62:AL62) -> 0 | O62: 1.7512968
E63: CH, RB & JPG | F63: External | G63: Puig India | H63: Shopfitting | I63: CL0061 Carolina Herrera | J63: =+K63+L63 -> 41.48435 | K63: =SUM(N63:Y63) -> 41.48435 | L63: =SUM(AA63:AL63) -> 0 | N63: 41.48435
E64: Rare Beauty | F64: External | G64: Rare Beauty LLC | H64: Prestige Cosmetic | I64: CL0765 Rare Beauty | J64: =+K64+L64 -> 95.832343 | K64: =SUM(N64:Y64) -> 95.832343 | L64: =SUM(AA64:AL64) -> 0 | N64: 39.296581 | O64: 56.535761
E65: Rare Beauty | F65: External | G65: Reliance Luxe Beauty Limited | H65: Prestige Cosmetic | I65: CL0765 Rare Beauty | J65: =+K65+L65 -> 15.972842 | K65: =SUM(N65:Y65) -> 15.972842 | L65: =SUM(AA65:AL65) -> 0 | O65: 15.972842
E66: Clinique | F66: External | G66: Shoppers Stop Ltd | H66: Prestige Cosmetic | I66: CL0075 Clinique | J66: =+K66+L66 -> 3.321 | K66: =SUM(N66:Y66) -> 3.321 | L66: =SUM(AA66:AL66) -> 0 | O66: 3.321
E67: ELCA Brand | F67: External | G67: Shoppers Stop Ltd | H67: Prestige Cosmetic | I67: CL0680 Estée Lauder - other brands | J67: =+K67+L67 -> 25.510656 | K67: =SUM(N67:Y67) -> 25.510656 | L67: =SUM(AA67:AL67) -> 0 | N67: 25.510656
E68: Tom Ford | F68: External | G68: Shoppers Stop Ltd | H68: Shopfitting | I68: CL0570 Tom Ford | J68: =+K68+L68 -> 14.288472 | K68: =SUM(N68:Y68) -> 14.288472 | L68: =SUM(AA68:AL68) -> 0 | N68: 1.0925225 | O68: 13.19595
J69: =+K69+L69 -> 0 | K69: =SUM(N69:Y69) -> 0 | L69: =SUM(AA69:AL69) -> 0
J70: =+K70+L70 -> 0 | K70: =SUM(N70:Y70) -> 0 | L70: =SUM(AA70:AL70) -> 0
J71: =+K71+L71 -> 0 | K71: =SUM(N71:Y71) -> 0 | L71: =SUM(AA71:AL71) -> 0
J72: =+K72+L72 -> 0 | K72: =SUM(N72:Y72) -> 0 | L72: =SUM(AA72:AL72) -> 0
J73: =+K73+L73 -> 0 | K73: =SUM(N73:Y73) -> 0 | L73: =SUM(AA73:AL73) -> 0
J74: =+K74+L74 -> 0 | K74: =SUM(N74:Y74) -> 0 | L74: =SUM(AA74:AL74) -> 0
J75: =+K75+L75 -> 0 | K75: =SUM(N75:Y75) -> 0 | L75: =SUM(AA75:AL75) -> 0
J76: =+K76+L76 -> 0 | K76: =SUM(N76:Y76) -> 0 | L76: =SUM(AA76:AL76) -> 0
J77: =+K77+L77 -> 0 | K77: =SUM(N77:Y77) -> 0 | L77: =SUM(AA77:AL77) -> 0
J78: =+K78+L78 -> 0 | K78: =SUM(N78:Y78) -> 0 | L78: =SUM(AA78:AL78) -> 0
J79: =+K79+L79 -> 0 | K79: =SUM(N79:Y79) -> 0 | L79: =SUM(AA79:AL79) -> 0
J80: =+K80+L80 -> 0 | K80: =SUM(N80:Y80) -> 0 | L80: =SUM(AA80:AL80) -> 0
... J252: =+K252+L252 -> 0 | K252: =SUM(N252:Y252) -> 0 | L252: =SUM(AA252:AL252) -> 0
E255: Deferred revenue balance as on | F255: 45992 | G255: 271.35 | H255: K Euro
E256: Add: Deferred revenue addition during Dec-25 | G256: 138.52 | H256: K Euro
E257: Less: Deferred revenue reversed during Dec-25 | G257: 192.25 | H257: K Euro
E258: Deferred revenue balance as on | F258: 46022 | G258: =G255+G256-G257 -> 217.62 | H258: K Euro
E260: Brand | H260: Amt. in K Euro
E261: Clinique | H261: 26.50018
E262: Estee Lauder | H262: 141.17576
E263: Fenty Beauty | H263: 65.052587
E264: Guerlain | H264: 12.224568
E265: Lancome | H265: 2.34
E266: L'Oreal TR | H266: 0.8584046
E267: Mac | H267: 2e-06
E268: Prada | H268: 0.79343
E269: The Ordinary | H269: 0.0193309
E270: YSL | H270: 5.2953845
E271: Grand Total | H271: =SUM(H261:H270) -> 254.25965
E274: Actual Orderbook of last week | H274: ='W2'!J19 -> 1094.8548
E275: New Orders in Current Week | H275: =H271 -> 254.25965
E276: Sales booked in current week | H276: =J12-'W2'!J12 -> 134.56956
E277: Standard Orderbook should be in Current Week | H277: =H274+H275-H276 -> 1214.5449
E278: Actual Orderbook in Current Week | H278: =J19 -> 1262.1782
E279: Difference | H279: =H277-H278 -> -47.63327 | I279: Check whether new orders are reported correctly or invoiced order have been removed from the sales dashboard.
I280: deferred revenue

Sheet W4
E2: ENTITY NAME : | G2: =+parameters!D2 -> Diam India | I2: ORDER BOOK SYNTHESIS in K€
E4: WEEK : | G4: W4 | I4: Cells to be filled in
E6: MONTH : | G6: =+VLOOKUP(G4, parameters!G:H, 2, 0) -> January
E8: TURNOVER | F8: =parameters!D4 -> k€ | H8: YTD Turnover | J8: =+G6&" Turnover" -> January Turnover | L8: Last estim. for the month: | O8: Forecast 2026
H9: =+"from January 1 until end of "&G4 -> from January 1 until end of W4 | J9: =+"from "&G6&" 1 until end of "&G4 -> from January 1 until end of W4 | L9: =+G6 -> January | O9: =+G4 -> W4 | P9: =+VLOOKUP(G4, parameters!$G$9:$I$61,3,0) -> W3 | Q9: Var
E10: EXTERNAL SALES INVOICED (=outside group) | H10: =352.2488195-H11 -> 349.12008 | J10: =352.2488195-J11 -> 349.12008 | L10: =J10+N17 -> 598.56008 | O10: =+H10+K17 -> 1605.7701 | P10: {=INDIRECT(ADDRESS(10,15,,,VLOOKUP($G$4,parameters!$G:$I,3,0)))} -> 1474.7035 | Q10: =O10-P10 -> 131.06661
E11: GROUP SALES INVOICED | H11: 3.1287355 | J11: 3.1287355 | L11: =J11+N18 -> 10.288735 | O11: =+H11+K18 -> 10.288735 | P11: {=INDIRECT(ADDRESS(11,15,,,VLOOKUP($G$4,parameters!$G:$I,3,0)))} -> 17.864254 | Q11: =O11-P11 -> -7.5755188 | S11: Definition orders : you consider the orders which are sure even if the order customers paper order is not yet received
E12: TOTAL | H12: =SUM(H10:H11) -> 352.24882 | J12: =SUM(J10:J11) -> 352.24882 | L12: =SUM(L10:L11) -> 608.84882 | O12: =SUM(O10:O11) -> 1616.0588 | P12: =SUM(P10:P11) -> 1492.5677 | Q12: =O12-P12 -> 123.49109 | S12: The quantity, value, and delivery date can be changed before final delivery
E16: ORDERBOOK | F16: =+F8 -> k€ | J16: TOTAL ORDERBOOK | K16: Total amount 2026 | L16: Total amount 2027 | N16: 46023 | O16: 46054 | P16: 46082 | Q16: 46113 | R16: 46143 | S16: 46174 | T16: 46204 | U16: 46235 | V16: 46266 | W16: 46296 | X16: 46327 | Y16: 46357 | AA16: 46388 | AB16: 46419 | AC16: 46447 | AD16: 46478 | AE16: 46508 | AF16: 46539 | AG16: 46569 | AH16: 46600 | AI16: 46631 | AJ16: 46661 | AK16: 46692 | AL16: 46722
E17: External | J17: =+SUMIF($F$24:$F$251,"External",$J$24:$J$251) -> 1256.65 | K17: =+SUMIF($F$24:$F$251,"External",$K$24:$K$251) -> 1256.65 | L17: =+SUMIF($F$24:$F$251,"External",$L$24:$L$251) -> 0 | N17: =+SUMIF($F$24:$F$251,"External",N$24:N$251) -> 249.44 | O17: =+SUMIF($F$24:$F$251,"External",O$24:O$251) -> 636.03 | P17: =+SUMIF($F$24:$F$251,"External",P$24:P$251) -> 180.82 | Q17: =+SUMIF($F$24:$F$251,"External",Q$24:Q$251) -> 130.23 | R17: =+SUMIF($F$24:$F$251,"External",R$24:R$251) -> 9.05 | S17: =+SUMIF($F$24:$F$251,"External",S$24:S$251) -> 39.07 | T17: =+SUMIF($F$24:$F$251,"External",T$24:T$251) -> 12.01 | U17: =+SUMIF($F$24:$F$251,"External",U$24:U$251) -> 0 | ... Y17: =+SUMIF($F$24:$F$251,"External",Y$24:Y$251) -> 0 | AA17: =+SUMIF($F$24:$F$251,"External",AA$24:AA$251) -> 0 | AB17: =+SUMIF($F$24:$F$251,"External",AB$24:AB$251) -> 0 | AC17: =+SUMIF($F$24:$F$251,"External",AC$24:AC$251) -> 0 | AD17: =+SUMIF($F$24:$F$251,"External",AD$24:AD$251) -> 0 | AE17: =+SUMIF($F$24:$F$251,"External",AE$24:AE$251) -> 0 | AF17: =+SUMIF($F$24:$F$251,"External",AF$24:AF$251) -> 0 | AG17: =+SUMIF($F$24:$F$251,"External",AG$24:AG$251) -> 0 | AH17: =+SUMIF($F$24:$F$251,"External",AH$24:AH$251) -> 0 | ... AL17: =+SUMIF($F$24:$F$251,"External",AL$24:AL$251) -> 0
E18: Group | J18: =+SUMIF($F$24:$F$251,"Group",$J$24:$J$251) -> 7.16 | K18: =+SUMIF($F$24:$F$251,"Group",$K$24:$K$251) -> 7.16 | L18: =SUMIF($F$24:$F$251,"Group",$L$24:$L$251) -> 0 | N18: =+SUMIF($F$24:$F$251,"Group",N$24:N$251) -> 7.16 | O18: =+SUMIF($F$24:$F$251,"Group",O$24:O$251) -> 0 | P18: =+SUMIF($F$24:$F$251,"Group",P$24:P$251) -> 0 | Q18: =+SUMIF($F$24:$F$251,"Group",Q$24:Q$251) -> 0 | R18: =+SUMIF($F$24:$F$251,"Group",R$24:R$251) -> 0 | S18: =+SUMIF($F$24:$F$251,"Group",S$24:S$251) -> 0 | T18: =+SUMIF($F$24:$F$251,"Group",T$24:T$251) -> 0 | U18: =+SUMIF($F$24:$F$251,"Group",U$24:U$251) -> 0 | ... Y18: =+SUMIF($F$24:$F$251,"Group",Y$24:Y$251) -> 0 | AA18: =+SUMIF($F$24:$F$251,"Group",AA$24:AA$251) -> 0 | AB18: =+SUMIF($F$24:$F$251,"Group",AB$24:AB$251) -> 0 | AC18: =+SUMIF($F$24:$F$251,"Group",AC$24:AC$251) -> 0 | AD18: =+SUMIF($F$24:$F$251,"Group",AD$24:AD$251) -> 0 | AE18: =+SUMIF($F$24:$F$251,"Group",AE$24:AE$251) -> 0 | AF18: =+SUMIF($F$24:$F$251,"Group",AF$24:AF$251) -> 0 | AG18: =+SUMIF($F$24:$F$251,"Group",AG$24:AG$251) -> 0 | AH18: =+SUMIF($F$24:$F$251,"Group",AH$24:AH$251) -> 0 | ... AL18: =+SUMIF($F$24:$F$251,"Group",AL$24:AL$251) -> 0
E19: TOTAL | J19: =SUM(J17:J18) -> 1263.81 | K19: =SUM(K17:K18) -> 1263.81 | L19: =SUM(L17:L18) -> 0 | N19: =SUM(N17:N18) -> 256.6 | O19: =SUM(O17:O18) -> 636.03 | P19: =SUM(P17:P18) -> 180.82 | Q19: =SUM(Q17:Q18) -> 130.23 | R19: =SUM(R17:R18) -> 9.05 | S19: =SUM(S17:S18) -> 39.07 | T19: =SUM(T17:T18) -> 12.01 | U19: =SUM(U17:U18) -> 0 | ... Y19: =SUM(Y17:Y18) -> 0 | AA19: =SUM(AA17:AA18) -> 0 | AB19: =SUM(AB17:AB18) -> 0 | AC19: =SUM(AC17:AC18) -> 0 | AD19: =SUM(AD17:AD18) -> 0 | AE19: =SUM(AE17:AE18) -> 0 | AF19: =SUM(AF17:AF18) -> 0 | AG19: =SUM(AG17:AG18) -> 0 | AH19: =SUM(AH17:AH18) -> 0 | ... AL19: =SUM(AL17:AL18) -> 0
I21: check | J21: =IF(SUM(J24:J251)=J19, "OK", "Please correct: the sum of orders below is not equal to the total calculated above. Make sure to pick External or Group for each order and don't change the formulas in columns K and L") -> OK | N21: 2026 | AA21: 2027
E23: Brand | F23: Group | G23: Customer Name | H23: Segment | I23: Outgroup | J23: TOTAL ORDERBOOK | K23: Total amount 2026 | L23: Total amount 2026 | N23: 46023 | O23: 46054 | P23: 46082 | Q23: 46113 | R23: 46143 | S23: 46174 | T23: 46204 | U23: 46235 | V23: 46266 | W23: 46296 | X23: 46327 | Y23: 46357 | AA23: 46388 | AB23: 46419 | AC23: 46447 | AD23: 46478 | AE23: 46508 | AF23: 46539 | AG23: 46569 | AH23: 46600 | AI23: 46631 | AJ23: 46661 | AK23: 46692 | AL23: 46722
D24: X | E24: Shiseido | F24: External | G24: BACCAROSE PERFUMES AND BEAUTY PRODUCTS PVT LTD | H24: Prestige Cosmetic | I24: CL0285 Shiseido | J24: =+K24+L24 -> 19.09 | K24: =SUM(N24:Y24) -> 19.09 | L24: =SUM(AA24:AL24) -> 0 | P24: 19.09
E25: Laura Mercier | F25: External | G25: BACCAROSE PERFUMES AND BEAUTY PRODUCTS PVT LTD | H25: Prestige Cosmetic | I25: CL0540 Laura Mercier | J25: =+K25+L25 -> 7.26 | K25: =SUM(N25:Y25) -> 7.26 | L25: =SUM(AA25:AL25) -> 0 | Q25: 7.26
E26: Gucci | F26: External | G26: BACCAROSE PERFUMES AND BEAUTY PRODUCTS PVT LTD | H26: Shopfitting | I26: CL0920 Coty - other brands | J26: =+K26+L26 -> 1.53 | K26: =SUM(N26:Y26) -> 1.53 | L26: =SUM(AA26:AL26) -> 0 | N26: 1.53
E27: Guerlain | F27: External | G27: Beauty Impex Pvt. Ltd | H27: Prestige Cosmetic | I27: CL0130 Guerlain | J27: =+K27+L27 -> 27.76 | K27: =SUM(N27:Y27) -> 27.76 | L27: =SUM(AA27:AL27) -> 0 | N27: 16.39 | O27: 11.37
E28: Shiseido | F28: External | G28: Best In Brands | H28: Prestige Cosmetic | I28: CL0285 Shiseido | J28: =+K28+L28 -> 8.07 | K28: =SUM(N28:Y28) -> 8.07 | L28: =SUM(AA28:AL28) -> 0 | P28: 8.07
E29: Chanel | F29: External | G29: CHANEL INDIA | H29: Shopfitting | I29: CL0065 Chanel | J29: =+K29+L29 -> 5.89 | K29: =SUM(N29:Y29) -> 5.89 | L29: =SUM(AA29:AL29) -> 0 | N29: 0 | O29: 5.89
E30: Clarins | F30: External | G30: Clarins Pte Ltd | H30: Shopfitting | I30: CL0070 Clarins | J30: =+K30+L30 -> 0.43 | K30: =SUM(N30:Y30) -> 0.43 | L30: =SUM(AA30:AL30) -> 0 | N30: 0.43
E31: L'Oreal TR | F31: External | G31: Connectiv FZCO | H31: Shopfitting | I31: CL9999 Other | J31: =+K31+L31 -> 0.86 | K31: =SUM(N31:Y31) -> 0.86 | L31: =SUM(AA31:AL31) -> 0 | P31: 0.86
E32: Coty Rimmel | F32: External | G32: Coty | H32: Shopfitting | I32: CL0080 Coty Rimmel | J32: =+K32+L32 -> 2.3 | K32: =SUM(N32:Y32) -> 2.3 | L32: =SUM(AA32:AL32) -> 0 | N32: 2.3
E33: Kylie Cosmetics | F33: External | G33: Coty | H33: Shopfitting | I33: CL0705 Coty KJ | J33: =+K33+L33 -> 0 | K33: =SUM(N33:Y33) -> 0 | L33: =SUM(AA33:AL33) -> 0 | N33: 0
E34: Coty Rimmel | F34: External | G34: DDS | H34: Shopfitting | I34: CL0080 Coty Rimmel | J34: =+K34+L34 -> 8.31 | K34: =SUM(N34:Y34) -> 8.31 | L34: =SUM(AA34:AL34) -> 0 | N34: 1.52 | Q34: 6.79
E35: Fenty Beauty | F35: Group | G35: DIAM Turkey | H35: Prestige Cosmetic | I35: CL0550 Kendo - Fenty | J35: =+K35+L35 -> 7.16 | K35: =SUM(N35:Y35) -> 7.16 | L35: =SUM(AA35:AL35) -> 0 | N35: 7.16
E36: Joe Malone | F36: External | G36: Estee Lauder AG Lachen | H36: Prestige Cosmetic | I36: CL0535 Joe Malone | J36: =+K36+L36 -> 0.27 | K36: =SUM(N36:Y36) -> 0.27 | L36: =SUM(AA36:AL36) -> 0 | N36: 0.27
E37: Too Faced | F37: External | G37: Estee Lauder Middle East FZE | H37: Prestige Cosmetic | I37: CL0575 Too Faced | J37: =+K37+L37 -> 155.09 | K37: =SUM(N37:Y37) -> 155.09 | L37: =SUM(AA37:AL37) -> 0 | O37: 155.09
E38: Clinique | F38: External | G38: Estee Lauder Saudi Limited | H38: Prestige Cosmetic | I38: CL0075 Clinique | J38: =+K38+L38 -> 3.55 | K38: =SUM(N38:Y38) -> 3.55 | L38: =SUM(AA38:AL38) -> 0 | O38: 3.55
E39: Fenty Beauty | F39: External | G39: Fenty Beauty LLC | H39: Prestige Cosmetic | I39: CL0550 Kendo - Fenty | J39: =+K39+L39 -> 66.91 | K39: =SUM(N39:Y39) -> 66.91 | L39: =SUM(AA39:AL39) -> 0 | N39: 66.91
E40: Forma | F40: External | G40: Forma Brands, LLC f/k/a FB Acquisition LLC | H40: Prestige Cosmetic | I40: CL0735 Morphe | J40: =+K40+L40 -> 55.18 | K40: =SUM(N40:Y40) -> 55.18 | L40: =SUM(AA40:AL40) -> 0 | N40: 0.99 | O40: 54.19
E41: Nars | F41: External | G41: Global Shoppers Stop Beauty Brands Ltd | H41: Prestige Cosmetic | I41: CL0226 Nars | J41: =+K41+L41 -> 111.48 | K41: =SUM(N41:Y41) -> 111.48 | L41: =SUM(AA41:AL41) -> 0 | N41: 0 | O41: 32.21 | P41: 79.27
E42: Maison Margiela | F42: External | G42: Global Shoppers Stop Beauty Brands Ltd | H42: Shopfitting | I42: CL9999 Other | J42: =+K42+L42 -> 0 | K42: =SUM(N42:Y42) -> 0 | L42: =SUM(AA42:AL42) -> 0 | N42: 0
E43: Prada | F43: External | G43: Global Shoppers Stop Beauty Brands Ltd | H43: Shopfitting | I43: CL9999 Other | J43: =+K43+L43 -> 17.79 | K43: =SUM(N43:Y43) -> 17.79 | L43: =SUM(AA43:AL43) -> 0 | N43: 1.12 | P43: 16.67
E44: Clarins | F44: External | G44: Global Shoppers Stop Beauty Brands Ltd | H44: Shopfitting | I44: CL0070 Clarins | J44: =+K44+L44 -> 0 | K44: =SUM(N44:Y44) -> 0 | L44: =SUM(AA44:AL44) -> 0 | N44: 0
E45: Benefit | F45: External | G45: Indosing Distribution | H45: Prestige Cosmetic | I45: CL0315 Benefit | J45: =+K45+L45 -> 31.33 | K45: =SUM(N45:Y45) -> 31.33 | L45: =SUM(AA45:AL45) -> 0 | N45: 8 | O45: 23.33
E46: Benefit | F46: External | G46: L Beauty Pte | H46: Prestige Cosmetic | I46: CL0315 Benefit | J46: =+K46+L46 -> 17.26 | K46: =SUM(N46:Y46) -> 17.26 | L46: =SUM(AA46:AL46) -> 0 | N46: 5.96 | O46: 5.65 | P46: 5.65
E47: Lancome | F47: External | G47: L'Oreal India | H47: Shopfitting | I47: CL0155 Lancôme | J47: =+K47+L47 -> 10.1 | K47: =SUM(N47:Y47) -> 10.1 | L47: =SUM(AA47:AL47) -> 0 | O47: 10.1
E48: Lancome | F48: External | G48: L'Oreal India | H48: Prestige Cosmetic | I48: CL0155 Lancôme | J48: =+K48+L48 -> 19.48 | K48: =SUM(N48:Y48) -> 19.48 | L48: =SUM(AA48:AL48) -> 0 | N48: 11.25 | O48: 8.23
E49: YSL | F49: External | G49: L'Oreal India | H49: Shopfitting | I49: CL0310 YSL | J49: =+K49+L49 -> 64.31 | K49: =SUM(N49:Y49) -> 64.31 | L49: =SUM(AA49:AL49) -> 0 | N49: 63.12 | O49: 1.19
E50: Lancome | F50: External | G50: L'Oreal Travel Retail | H50: Shopfitting | I50: CL0155 Lancôme | J50: =+K50+L50 -> 16.5 | K50: =SUM(N50:Y50) -> 16.5 | L50: =SUM(AA50:AL50) -> 0 | Q50: 16.5
E51: YSL | F51: External | G51: L'Oreal Travel Retail | H51: Shopfitting | I51: CL0310 YSL | J51: =+K51+L51 -> 6.08 | K51: =SUM(N51:Y51) -> 6.08 | L51: =SUM(AA51:AL51) -> 0 | N51: 6.08
E52: Multi | F52: External | G52: L'Oreal Travel Retail | H52: Shopfitting | I52: CL0180 L'Oréal Divers | J52: =+K52+L52 -> 59.74 | K52: =SUM(N52:Y52) -> 59.74 | L52: =SUM(AA52:AL52) -> 0 | Q52: 59.74
E53: Loreal Paris | F53: External | G53: L'Oreal Travel Retail | H53: Shopfitting | I53: CL0180 L'Oréal Divers | J53: =+K53+L53 -> 8.9 | K53: =SUM(N53:Y53) -> 8.9 | L53: =SUM(AA53:AL53) -> 0 | O53: 8.9
E54: Armani | F54: External | G54: L'Oreal Travel Retail | H54: Shopfitting | I54: CL0345 Armani | J54: =+K54+L54 -> 33.2 | K54: =SUM(N54:Y54) -> 33.2 | L54: =SUM(AA54:AL54) -> 0 | O54: 2.07 | Q54: 31.13
E55: OAP | F55: External | G55: L'Oreal Travel Retail | H55: Shopfitting | I55: CL0180 L'Oréal Divers | J55: =+K55+L55 -> 8.81 | K55: =SUM(N55:Y55) -> 8.81 | L55: =SUM(AA55:AL55) -> 0 | Q55: 8.81
E56: RALPH LAUREN | F56: External | G56: L'Oreal Travel Retail | H56: Shopfitting | I56: CL0405 Ralph Lauren | J56: =+K56+L56 -> 1.75 | K56: =SUM(N56:Y56) -> 1.75 | L56: =SUM(AA56:AL56) -> 0 | O56: 1.75
E57: PUIG Brands | F57: External | G57: Puig India | H57: Shopfitting | I57: CL0840 Puig - other brands | J57: =+K57+L57 -> 41.48 | K57: =SUM(N57:Y57) -> 41.48 | L57: =SUM(AA57:AL57) -> 0 | N57: 26.63 | O57: 14.85
E58: Rare Beauty | F58: External | G58: Rare Beauty LLC | H58: Prestige Cosmetic | I58: CL0765 Rare Beauty | J58: =+K58+L58 -> 57.11 | K58: =SUM(N58:Y58) -> 57.11 | L58: =SUM(AA58:AL58) -> 0 | N58: 0.57 | O58: 56.54
E59: Rare Beauty | F59: External | G59: Reliance Luxe Beauty Limited | H59: Prestige Cosmetic | I59: CL0765 Rare Beauty | J59: =+K59+L59 -> 42.93 | K59: =SUM(N59:Y59) -> 42.93 | L59: =SUM(AA59:AL59) -> 0 | O59: 42.93
E60: Clinique | F60: External | G60: Shoppers Stop Ltd | H60: Prestige Cosmetic | I60: CL0075 Clinique | J60: =+K60+L60 -> 3.32 | K60: =SUM(N60:Y60) -> 3.32 | L60: =SUM(AA60:AL60) -> 0 | O60: 3.32
E61: Tom Ford | F61: External | G61: Shoppers Stop Ltd | H61: Shopfitting | I61: CL0570 Tom Ford | J61: =+K61+L61 -> 14.29 | K61: =SUM(N61:Y61) -> 14.29 | L61: =SUM(AA61:AL61) -> 0 | N61: 1.09 | O61: 13.2
E62: Estée Lauder - other brands | F62: External | G62: Shoppers Stop Ltd | H62: Prestige Cosmetic | I62: CL0680 Estée Lauder - other brands | J62: =+K62+L62 -> 25.51 | K62: =SUM(N62:Y62) -> 25.51 | L62: =SUM(AA62:AL62) -> 0 | N62: 25.51
E63: Clinique | F63: External | G63: ELCA Cosmetics Pvt. Ltd. | H63: Prestige Cosmetic | I63: CL0075 Clinique | J63: =+K63+L63 -> 62.98 | K63: =SUM(N63:Y63) -> 62.98 | L63: =SUM(AA63:AL63) -> 0 | N63: 0.49 | O63: 57.81 | P63: 2.34 | T63: 2.34
E64: Estée Lauder | F64: External | G64: ELCA Cosmetics Pvt. Ltd. | H64: Prestige Cosmetic | I64: CL0110 Estée Lauder | J64: =+K64+L64 -> 127.28 | K64: =SUM(N64:Y64) -> 127.28 | L64: =SUM(AA64:AL64) -> 0 | N64: 8.7 | O64: 113.9 | P64: 2.34 | T64: 2.34
E65: Mac | F65: External | G65: ELCA Cosmetics Pvt. Ltd. | H65: Prestige Cosmetic | I65: CL0395 MAC | J65: =+K65+L65 -> 22.05 | K65: =SUM(N65:Y65) -> 22.05 | L65: =SUM(AA65:AL65) -> 0 | N65: 0.18 | O65: 8.14 | P65: 2.34 | R65: 9.05 | T65: 2.34
E66: Tom Ford | F66: External | G66: ELCA Cosmetics Pvt. Ltd. | H66: Prestige Cosmetic | I66: CL0570 Tom Ford | J66: =+K66+L66 -> 27.45 | K66: =SUM(N66:Y66) -> 27.45 | L66: =SUM(AA66:AL66) -> 0 | N66: 0.38 | O66: 1.01 | P66: 25.28 | T66: 0.78
E67: Dr Jart+ | F67: External | G67: ELCA Cosmetics Pvt. Ltd. | H67: Prestige Cosmetic | I67: CL0680 Estée Lauder - other brands | J67: =+K67+L67 -> 3.19 | K67: =SUM(N67:Y67) -> 3.19 | L67: =SUM(AA67:AL67) -> 0 | P67: 3.19
E68: The Ordinary | F68: External | G68: ELCA Cosmetics Pvt. Ltd. | H68: Prestige Cosmetic | I68: CL0680 Estée Lauder - other brands | J68: =+K68+L68 -> 15.36 | K68: =SUM(N68:Y68) -> 15.36 | L68: =SUM(AA68:AL68) -> 0 | N68: 0.02 | O68: 0.81 | P68: 13.02 | T68: 1.51
E69: Too Faced | F69: External | G69: ELCA Cosmetics Pvt. Ltd. | H69: Prestige Cosmetic | I69: CL0575 Too Faced | J69: =+K69+L69 -> 41.19 | K69: =SUM(N69:Y69) -> 41.19 | L69: =SUM(AA69:AL69) -> 0 | P69: 1.06 | S69: 39.07 | T69: 1.06
E70: Smashbox | F70: External | G70: ELCA Cosmetics Pvt. Ltd. | H70: Prestige Cosmetic | I70: CL0525 Smashbox | J70: =+K70+L70 -> 3.28 | K70: =SUM(N70:Y70) -> 3.28 | L70: =SUM(AA70:AL70) -> 0 | N70: 0 | P70: 1.64 | T70: 1.64
J71: =+K71+L71 -> 0 | K71: =SUM(N71:Y71) -> 0 | L71: =SUM(AA71:AL71) -> 0
J72: =+K72+L72 -> 0 | K72: =SUM(N72:Y72) -> 0 | L72: =SUM(AA72:AL72) -> 0
J73: =+K73+L73 -> 0 | K73: =SUM(N73:Y73) -> 0 | L73: =SUM(AA73:AL73) -> 0
J74: =+K74+L74 -> 0 | K74: =SUM(N74:Y74) -> 0 | L74: =SUM(AA74:AL74) -> 0
J75: =+K75+L75 -> 0 | K75: =SUM(N75:Y75) -> 0 | L75: =SUM(AA75:AL75) -> 0
J76: =+K76+L76 -> 0 | K76: =SUM(N76:Y76) -> 0 | L76: =SUM(AA76:AL76) -> 0
J77: =+K77+L77 -> 0 | K77: =SUM(N77:Y77) -> 0 | L77: =SUM(AA77:AL77) -> 0
J78: =+K78+L78 -> 0 | K78: =SUM(N78:Y78) -> 0 | L78: =SUM(AA78:AL78) -> 0
J79: =+K79+L79 -> 0 | K79: =SUM(N79:Y79) -> 0 | L79: =SUM(AA79:AL79) -> 0
J80: =+K80+L80 -> 0 | K80: =SUM(N80:Y80) -> 0 | L80: =SUM(AA80:AL80) -> 0
J81: =+K81+L81 -> 0 | K81: =SUM(N81:Y81) -> 0 | L81: =SUM(AA81:AL81) -> 0
J82: =+K82+L82 -> 0 | K82: =SUM(N82:Y82) -> 0 | L82: =SUM(AA82:AL82) -> 0
... J252: =+K252+L252 -> 0 | K252: =SUM(N252:Y252) -> 0 | L252: =SUM(AA252:AL252) -> 0
E255: Deferred revenue balance as on | F255: 45992 | G255: 271.35 | H255: K Euro
E256: Add: Deferred revenue addition during Dec-25 | G256: 138.52 | H256: K Euro
E257: Less: Deferred revenue reversed during Dec-25 | G257: 192.25 | H257: K Euro
E258: Deferred revenue balance as on | F258: 46022 | G258: =G255+G256-G257 -> 217.62 | H258: K Euro
E260: Brand | H260: Amt. in K Euro
E261: Clinique | H261: 16.09
E262: Coty | H262: 2.3
E263: Estee Lauder | H263: 5.44
E264: Forma | H264: 0.99
E265: Gucci | H265: 1.53
E266: Mac | H266: 8.32
E267: Prada | H267: 17
E268: Rare Beauty | H268: 26.96
E269: The Ordinary | H269: 0.81
E270: Tom Ford | H270: 1.39
E271: YSL | H271: 6.08
E272: Grand Total | H272: =SUM(H261:H271) -> 86.91
E275: Actual Orderbook of last week | H275: ='W3'!J19 -> 1262.1782
E276: New Orders in Current Week | H276: =H272 -> 86.91
E277: Sales booked in current week | H277: =J12-'W3'!J12 -> 121.85926
E278: Standard Orderbook should be in Current Week | H278: =H275+H276-H277 -> 1227.2289
E279: Actual Orderbook in Current Week | H279: =J19 -> 1263.81
E280: Difference | H280: =H278-H279 -> -36.581094 | I280: Check whether new orders are reported correctly or invoiced order have been removed from the sales dashboard.
I281: deferred revenue

Sheet W5
E2: ENTITY NAME : | G2: =+parameters!D2 -> Diam India | I2: ORDER BOOK SYNTHESIS in K€
E4: WEEK : | G4: W5 | I4: Cells to be filled in
E6: MONTH : | G6: =+VLOOKUP(G4, parameters!G:H, 2, 0) -> January
E8: TURNOVER | F8: =parameters!D4 -> k€ | H8: YTD Turnover | J8: =+G6&" Turnover" -> January Turnover | L8: Last estim. for the month: | O8: Forecast 2026
H9: =+"from January 1 until end of "&G4 -> from January 1 until end of W5 | J9: =+"from "&G6&" 1 until end of "&G4 -> from January 1 until end of W5 | L9: =+G6 -> January | O9: =+G4 -> W5 | P9: =+VLOOKUP(G4, parameters!$G$9:$I$61,3,0) -> W4 | Q9: Var
E10: EXTERNAL SALES INVOICED (=outside group) | H10: =529.36 -> 529.36 | J10: =529.36 -> 529.36 | L10: =J10+N17 -> 529.36 | O10: =+H10+K17 -> 1578.2 | P10: {=INDIRECT(ADDRESS(10,15,,,VLOOKUP($G$4,parameters!$G:$I,3,0)))} -> 1605.7701 | Q10: =O10-P10 -> -27.570084
E11: GROUP SALES INVOICED | H11: 13.17 | J11: 13.17 | L11: =J11+N18 -> 13.17 | O11: =+H11+K18 -> 19.96 | P11: {=INDIRECT(ADDRESS(11,15,,,VLOOKUP($G$4,parameters!$G:$I,3,0)))} -> 10.288735 | Q11: =O11-P11 -> 9.6712645 | S11: Definition orders : you consider the orders which are sure even if the order customers paper order is not yet received
E12: TOTAL | H12: =SUM(H10:H11) -> 542.53 | J12: =SUM(J10:J11) -> 542.53 | L12: =SUM(L10:L11) -> 542.53 | O12: =SUM(O10:O11) -> 1598.16 | P12: =SUM(P10:P11) -> 1616.0588 | Q12: =O12-P12 -> -17.898819 | S12: The quantity, value, and delivery date can be changed before final delivery
E16: ORDERBOOK | F16: =+F8 -> k€ | J16: TOTAL ORDERBOOK | K16: Total amount 2026 | L16: Total amount 2027 | N16: 46023 | O16: 46054 | P16: 46082 | Q16: 46113 | R16: 46143 | S16: 46174 | T16: 46204 | U16: 46235 | V16: 46266 | W16: 46296 | X16: 46327 | Y16: 46357 | AA16: 46388 | AB16: 46419 | AC16: 46447 | AD16: 46478 | AE16: 46508 | AF16: 46539 | AG16: 46569 | AH16: 46600 | AI16: 46631 | AJ16: 46661 | AK16: 46692 | AL16: 46722
E17: External | J17: =+SUMIF($F$24:$F$63,"External",$J$24:$J$63) -> 1048.84 | K17: =+SUMIF($F$24:$F$63,"External",$K$24:$K$63) -> 1048.84 | L17: =+SUMIF($F$24:$F$63,"External",$L$24:$L$63) -> 0 | N17: =+SUMIF($F$24:$F$63,"External",N$24:N$63) -> 0 | O17: =+SUMIF($F$24:$F$63,"External",O$24:O$63) -> 459.83 | P17: =+SUMIF($F$24:$F$63,"External",P$24:P$63) -> 355.25 | Q17: =+SUMIF($F$24:$F$63,"External",Q$24:Q$63) -> 173.63 | R17: =+SUMIF($F$24:$F$63,"External",R$24:R$63) -> 9.05 | S17: =+SUMIF($F$24:$F$63,"External",S$24:S$63) -> 39.07 | T17: =+SUMIF($F$24:$F$63,"External",T$24:T$63) -> 12.01 | U17: =+SUMIF($F$24:$F$63,"External",U$24:U$63) -> 0 | ... Y17: =+SUMIF($F$24:$F$63,"External",Y$24:Y$63) -> 0 | AA17: =+SUMIF($F$24:$F$63,"External",AA$24:AA$63) -> 0 | AB17: =+SUMIF($F$24:$F$63,"External",AB$24:AB$63) -> 0 | AC17: =+SUMIF($F$24:$F$63,"External",AC$24:AC$63) -> 0 | AD17: =+SUMIF($F$24:$F$63,"External",AD$24:AD$63) -> 0 | AE17: =+SUMIF($F$24:$F$63,"External",AE$24:AE$63) -> 0 | AF17: =+SUMIF($F$24:$F$63,"External",AF$24:AF$63) -> 0 | AG17: =+SUMIF($F$24:$F$63,"External",AG$24:AG$63) -> 0 | AH17: =+SUMIF($F$24:$F$63,"External",AH$24:AH$63) -> 0 | ... AL17: =+SUMIF($F$24:$F$63,"External",AL$24:AL$63) -> 0
E18: Group | J18: =+SUMIF($F$24:$F$63,"Group",$J$24:$J$63) -> 6.79 | K18: =+SUMIF($F$24:$F$63,"Group",$K$24:$K$63) -> 6.79 | L18: =SUMIF($F$24:$F$63,"Group",$L$24:$L$63) -> 0 | N18: =+SUMIF($F$24:$F$63,"Group",N$24:N$63) -> 0 | O18: =+SUMIF($F$24:$F$63,"Group",O$24:O$63) -> 0 | P18: =+SUMIF($F$24:$F$63,"Group",P$24:P$63) -> 0 | Q18: =+SUMIF($F$24:$F$63,"Group",Q$24:Q$63) -> 6.79 | R18: =+SUMIF($F$24:$F$63,"Group",R$24:R$63) -> 0 | S18: =+SUMIF($F$24:$F$63,"Group",S$24:S$63) -> 0 | T18: =+SUMIF($F$24:$F$63,"Group",T$24:T$63) -> 0 | U18: =+SUMIF($F$24:$F$63,"Group",U$24:U$63) -> 0 | ... Y18: =+SUMIF($F$24:$F$63,"Group",Y$24:Y$63) -> 0 | AA18: =+SUMIF($F$24:$F$63,"Group",AA$24:AA$63) -> 0 | AB18: =+SUMIF($F$24:$F$63,"Group",AB$24:AB$63) -> 0 | AC18: =+SUMIF($F$24:$F$63,"Group",AC$24:AC$63) -> 0 | AD18: =+SUMIF($F$24:$F$63,"Group",AD$24:AD$63) -> 0 | AE18: =+SUMIF($F$24:$F$63,"Group",AE$24:AE$63) -> 0 | AF18: =+SUMIF($F$24:$F$63,"Group",AF$24:AF$63) -> 0 | AG18: =+SUMIF($F$24:$F$63,"Group",AG$24:AG$63) -> 0 | AH18: =+SUMIF($F$24:$F$63,"Group",AH$24:AH$63) -> 0 | ... AL18: =+SUMIF($F$24:$F$63,"Group",AL$24:AL$63) -> 0
E19: TOTAL | J19: =SUM(J17:J18) -> 1055.63 | K19: =SUM(K17:K18) -> 1055.63 | L19: =SUM(L17:L18) -> 0 | N19: =SUM(N17:N18) -> 0 | O19: =SUM(O17:O18) -> 459.83 | P19: =SUM(P17:P18) -> 355.25 | Q19: =SUM(Q17:Q18) -> 180.42 | R19: =SUM(R17:R18) -> 9.05 | S19: =SUM(S17:S18) -> 39.07 | T19: =SUM(T17:T18) -> 12.01 | U19: =SUM(U17:U18) -> 0 | ... Y19: =SUM(Y17:Y18) -> 0 | AA19: =SUM(AA17:AA18) -> 0 | AB19: =SUM(AB17:AB18) -> 0 | AC19: =SUM(AC17:AC18) -> 0 | AD19: =SUM(AD17:AD18) -> 0 | AE19: =SUM(AE17:AE18) -> 0 | AF19: =SUM(AF17:AF18) -> 0 | AG19: =SUM(AG17:AG18) -> 0 | AH19: =SUM(AH17:AH18) -> 0 | ... AL19: =SUM(AL17:AL18) -> 0
I21: check | J21: =IF(SUM(J24:J63)=J19, "OK", "Please correct: the sum of orders below is not equal to the total calculated above. Make sure to pick External or Group for each order and don't change the formulas in columns K and L") -> OK | N21: 2026 | AA21: 2027
E23: Order (Tooling including) to be delivered | F23: External or Group | G23: Customers orders | H23: Segment | I23: Outgroup | J23: TOTAL ORDERBOOK | K23: Total amount 2026 | L23: Total amount 2026 | N23: 46023 | O23: 46054 | P23: 46082 | Q23: 46113 | R23: 46143 | S23: 46174 | T23: 46204 | U23: 46235 | V23: 46266 | W23: 46296 | X23: 46327 | Y23: 46357 | AA23: 46388 | AB23: 46419 | AC23: 46447 | AD23: 46478 | AE23: 46508 | AF23: 46539 | AG23: 46569 | AH23: 46600 | AI23: 46631 | AJ23: 46661 | AK23: 46692 | AL23: 46722
E24: Laura Mercier | F24: External | G24: BACCAROSE PERFUMES AND BEAUTY PRODUCTS PVT LTD | H24: Prestige Cosmetic | I24: CL0540 Laura Mercier | J24: =+K24+L24 -> 7.26 | K24: =SUM(N24:Y24) -> 7.26 | L24: =SUM(AA24:AL24) -> 0 | Q24: 7.26
E25: Shiseido | F25: External | G25: BACCAROSE PERFUMES AND BEAUTY PRODUCTS PVT LTD | H25: Prestige Cosmetic | I25: CL0285 Shiseido | J25: =+K25+L25 -> 19.09 | K25: =SUM(N25:Y25) -> 19.09 | L25: =SUM(AA25:AL25) -> 0 | P25: 19.09
E26: Shiseido | F26: External | G26: Best In Brands | H26: Prestige Cosmetic | I26: CL0285 Shiseido | J26: =+K26+L26 -> 8.07 | K26: =SUM(N26:Y26) -> 8.07 | L26: =SUM(AA26:AL26) -> 0 | P26: 8.07
E27: Chanel | F27: External | G27: CHANEL INDIA | H27: Shopfitting | I27: CL0065 Chanel | J27: =+K27+L27 -> 5.89 | K27: =SUM(N27:Y27) -> 5.89 | L27: =SUM(AA27:AL27) -> 0 | O27: 5.89
E28: L'Oreal TR | F28: External | G28: Connectiv FZCO | H28: Shopfitting | I28: CL9999 Other | J28: =+K28+L28 -> 0.86 | K28: =SUM(N28:Y28) -> 0.86 | L28: =SUM(AA28:AL28) -> 0 | P28: 0.86
E29: Coty Rimmel | F29: Group | G29: DDS | H29: Shopfitting | I29: CL0080 Coty Rimmel | J29: =+K29+L29 -> 6.79 | K29: =SUM(N29:Y29) -> 6.79 | L29: =SUM(AA29:AL29) -> 0 | Q29: 6.79
E30: Too Faced | F30: External | G30: Elca Cosmetics Pvt Ltd | H30: Prestige Cosmetic | I30: CL0575 Too Faced | J30: =+K30+L30 -> 39.07 | K30: =SUM(N30:Y30) -> 39.07 | L30: =SUM(AA30:AL30) -> 0 | S30: 39.07
E31: Clinique | F31: External | G31: ELCA Cosmetics Pvt. Ltd. | H31: Prestige Cosmetic | I31: CL0075 Clinique | J31: =+K31+L31 -> 43.43 | K31: =SUM(N31:Y31) -> 43.43 | L31: =SUM(AA31:AL31) -> 0 | O31: 38.75 | P31: 2.34 | T31: 2.34
E32: Dr Jart+ | F32: External | G32: ELCA Cosmetics Pvt. Ltd. | H32: Prestige Cosmetic | I32: CL0680 Estée Lauder - other brands | J32: =+K32+L32 -> 3.19 | K32: =SUM(N32:Y32) -> 3.19 | L32: =SUM(AA32:AL32) -> 0 | P32: 3.19
E33: Estee Lauder | F33: External | G33: ELCA Cosmetics Pvt. Ltd. | H33: Prestige Cosmetic | I33: CL0110 Estée Lauder | J33: =+K33+L33 -> 91.86 | K33: =SUM(N33:Y33) -> 91.86 | L33: =SUM(AA33:AL33) -> 0 | O33: 87.18 | P33: 2.34 | T33: 2.34
E34: Mac | F34: External | G34: ELCA Cosmetics Pvt. Ltd. | H34: Prestige Cosmetic | I34: CL0395 MAC | J34: =+K34+L34 -> 22.14 | K34: =SUM(N34:Y34) -> 22.14 | L34: =SUM(AA34:AL34) -> 0 | O34: 8.41 | P34: 2.34 | R34: 9.05 | T34: 2.34
E35: Smashbox | F35: External | G35: ELCA Cosmetics Pvt. Ltd. | H35: Prestige Cosmetic | I35: CL0525 Smashbox | J35: =+K35+L35 -> 3.37 | K35: =SUM(N35:Y35) -> 3.37 | L35: =SUM(AA35:AL35) -> 0 | O35: 0.09 | P35: 1.64 | T35: 1.64
E36: The Ordinary | F36: External | G36: ELCA Cosmetics Pvt. Ltd. | H36: Prestige Cosmetic | I36: CL0680 Estée Lauder - other brands | J36: =+K36+L36 -> 15.43 | K36: =SUM(N36:Y36) -> 15.43 | L36: =SUM(AA36:AL36) -> 0 | O36: 0.9 | P36: 13.02 | T36: 1.51
E37: Tom Ford | F37: External | G37: ELCA Cosmetics Pvt. Ltd. | H37: Prestige Cosmetic | I37: CL0570 Tom Ford | J37: =+K37+L37 -> 27.07 | K37: =SUM(N37:Y37) -> 27.07 | L37: =SUM(AA37:AL37) -> 0 | O37: 1.01 | P37: 25.28 | T37: 0.78
E38: Too Faced | F38: External | G38: ELCA Cosmetics Pvt. Ltd. | H38: Prestige Cosmetic | I38: CL0575 Too Faced | J38: =+K38+L38 -> 2.12 | K38: =SUM(N38:Y38) -> 2.12 | L38: =SUM(AA38:AL38) -> 0 | P38: 1.06 | T38: 1.06
E39: Joe Malone | F39: External | G39: Estee Lauder AG Lachen | H39: Prestige Cosmetic | I39: CL0535 Joe Malone | J39: =+K39+L39 -> 0.07 | K39: =SUM(N39:Y39) -> 0.07 | L39: =SUM(AA39:AL39) -> 0 | O39: 0.07
E40: Too Faced | F40: External | G40: Estee Lauder Middle East FZE | H40: Prestige Cosmetic | I40: CL0575 Too Faced | J40: =+K40+L40 -> 155.09 | K40: =SUM(N40:Y40) -> 155.09 | L40: =SUM(AA40:AL40) -> 0 | P40: 155.09
E41: Clinique | F41: External | G41: Estee Lauder Saudi Limited | H41: Prestige Cosmetic | I41: CL0075 Clinique | J41: =+K41+L41 -> 3.55 | K41: =SUM(N41:Y41) -> 3.55 | L41: =SUM(AA41:AL41) -> 0 | O41: 3.55
E42: Forma | F42: External | G42: Forma Brands, LLC f/k/a FB Acquisition LLC | H42: Prestige Cosmetic | I42: CL0735 Morphe | J42: =+K42+L42 -> 54.19 | K42: =SUM(N42:Y42) -> 54.19 | L42: =SUM(AA42:AL42) -> 0 | O42: 54.19
E43: Nars | F43: External | G43: Global Shoppers Stop Beauty Brands Ltd | H43: Prestige Cosmetic | I43: CL0226 Nars | J43: =+K43+L43 -> 111.48 | K43: =SUM(N43:Y43) -> 111.48 | L43: =SUM(AA43:AL43) -> 0 | O43: 32.21 | P43: 79.27
E44: Prada | F44: External | G44: Global Shoppers Stop Beauty Brands Ltd | H44: Shopfitting | I44: CL9999 Other | J44: =+K44+L44 -> 17 | K44: =SUM(N44:Y44) -> 17 | L44: =SUM(AA44:AL44) -> 0 | O44: 0.33 | P44: 16.67
E45: Benefit | F45: External | G45: Indosing Distribution | H45: Prestige Cosmetic | I45: CL0315 Benefit | J45: =+K45+L45 -> 24.02 | K45: =SUM(N45:Y45) -> 24.02 | L45: =SUM(AA45:AL45) -> 0 | O45: 24.02
E46: Benefit | F46: External | G46: L Beauty Pte | H46: Prestige Cosmetic | I46: CL0315 Benefit | J46: =+K46+L46 -> 38.24 | K46: =SUM(N46:Y46) -> 38.24 | L46: =SUM(AA46:AL46) -> 0 | O46: 5.65 | P46: 10.14 | Q46: 22.45
E47: Lancome | F47: External | G47: L'Oreal India | H47: Shopfitting | I47: CL0155 Lancôme | J47: =+K47+L47 -> 10.1 | K47: =SUM(N47:Y47) -> 10.1 | L47: =SUM(AA47:AL47) -> 0 | O47: 10.1
E48: Lancome | F48: External | G48: L'Oreal India | H48: Prestige Cosmetic | I48: CL0155 Lancôme | J48: =+K48+L48 -> 19.48 | K48: =SUM(N48:Y48) -> 19.48 | L48: =SUM(AA48:AL48) -> 0 | O48: 19.48
E49: YSL | F49: External | G49: L'Oreal India | H49: Shopfitting | I49: CL0310 YSL | J49: =+K49+L49 -> 1.19 | K49: =SUM(N49:Y49) -> 1.19 | L49: =SUM(AA49:AL49) -> 0 | O49: 1.19
E50: Armani | F50: External | G50: L'Oreal Travel Retail | H50: Shopfitting | I50: CL0345 Armani | J50: =+K50+L50 -> 33.2 | K50: =SUM(N50:Y50) -> 33.2 | L50: =SUM(AA50:AL50) -> 0 | O50: 2.07 | Q50: 31.13
E51: Lancome | F51: External | G51: L'Oreal Travel Retail | H51: Shopfitting | I51: CL0155 Lancôme | J51: =+K51+L51 -> 16.5 | K51: =SUM(N51:Y51) -> 16.5 | L51: =SUM(AA51:AL51) -> 0 | Q51: 16.5
E52: Loreal Paris | F52: External | G52: L'Oreal Travel Retail | H52: Shopfitting | I52: CL0180 L'Oréal Divers | J52: =+K52+L52 -> 8.9 | K52: =SUM(N52:Y52) -> 8.9 | L52: =SUM(AA52:AL52) -> 0 | O52: 8.9
E53: Multi | F53: External | G53: L'Oreal Travel Retail | H53: Shopfitting | I53: CL0180 L'Oréal Divers | J53: =+K53+L53 -> 59.74 | K53: =SUM(N53:Y53) -> 59.74 | L53: =SUM(AA53:AL53) -> 0 | Q53: 59.74
E54: OAP | F54: External | G54: L'Oreal Travel Retail | H54: Shopfitting | I54: CL0180 L'Oréal Divers | J54: =+K54+L54 -> 8.81 | K54: =SUM(N54:Y54) -> 8.81 | L54: =SUM(AA54:AL54) -> 0 | Q54: 8.81
E55: RALPH LAUREN | F55: External | G55: L'Oreal Travel Retail | H55: Shopfitting | I55: CL0405 Ralph Lauren | J55: =+K55+L55 -> 1.75 | K55: =SUM(N55:Y55) -> 1.75 | L55: =SUM(AA55:AL55) -> 0 | O55: 1.75
E56: YSL | F56: External | G56: L'Oreal Travel Retail | H56: Shopfitting | I56: CL0310 YSL | J56: =+K56+L56 -> 27.74 | K56: =SUM(N56:Y56) -> 27.74 | L56: =SUM(AA56:AL56) -> 0 | Q56: 27.74
E57: PUIG Brands | F57: External | G57: Puig India | H57: Shopfitting | I57: CL0840 Puig - other brands | J57: =+K57+L57 -> 14.85 | K57: =SUM(N57:Y57) -> 14.85 | L57: =SUM(AA57:AL57) -> 0 | P57: 14.85
E58: Rare Beauty | F58: External | G58: Rare Beauty LLC | H58: Prestige Cosmetic | I58: CL0765 Rare Beauty | J58: =+K58+L58 -> 57.11 | K58: =SUM(N58:Y58) -> 57.11 | L58: =SUM(AA58:AL58) -> 0 | O58: 57.11
E59: Rare Beauty | F59: External | G59: Reliance Luxe Beauty Limited | H59: Prestige Cosmetic | I59: CL0765 Rare Beauty | J59: =+K59+L59 -> 42.93 | K59: =SUM(N59:Y59) -> 42.93 | L59: =SUM(AA59:AL59) -> 0 | O59: 42.93
E60: Clinique | F60: External | G60: Shoppers Stop Ltd | H60: Prestige Cosmetic | I60: CL0075 Clinique | J60: =+K60+L60 -> 3.32 | K60: =SUM(N60:Y60) -> 3.32 | L60: =SUM(AA60:AL60) -> 0 | O60: 3.32
E61: Tom Ford | F61: External | G61: Shoppers Stop Ltd | H61: Shopfitting | I61: CL0570 Tom Ford | J61: =+K61+L61 -> 22.86 | K61: =SUM(N61:Y61) -> 22.86 | L61: =SUM(AA61:AL61) -> 0 | O61: 22.86
E62: Clinique | F62: External | G62: ELCA Cosmetics Pvt. Ltd. | H62: Prestige Cosmetic | I62: CL0075 Clinique | J62: =+K62+L62 -> 27.87 | K62: =SUM(N62:Y62) -> 27.87 | L62: =SUM(AA62:AL62) -> 0 | O62: 27.87
J63: =+K63+L63 -> 0 | K63: =SUM(N63:Y63) -> 0 | L63: =SUM(AA63:AL63) -> 0
E65: Deferred revenue balance as on | F65: 45992 | G65: 271.35 | H65: K Euro
E66: Add: Deferred revenue addition during Dec-25 | G66: 138.52 | H66: K Euro
E67: Less: Deferred revenue reversed during Dec-25 | G67: 192.25 | H67: K Euro
E68: Deferred revenue balance as on | F68: 46022 | G68: =G65+G66-G67 -> 217.62 | H68: K Euro
E70: Brand | H70: Amt. in K Euro
E71: Benefit | H71: 27.63
E72: Nars | H72: 13.96
E73: Tom Ford | H73: 9.66
E74: YSL | H74: 27.74
E76: Grand Total | H76: =SUM(H71:H75) -> 78.99
E79: Actual Orderbook of last week | H79: ='W4'!J19 -> 1263.81
E80: New Orders in Current Week | H80: =H76 -> 78.99
E81: Sales booked in current week | H81: =J12-'W4'!J12 -> 190.28118
E82: Standard Orderbook should be in Current Week | H82: =H79+H80-H81 -> 1152.5188
E83: Actual Orderbook in Current Week | H83: =J19 -> 1055.63
E84: Difference | H84: =H82-H83 -> 96.88882 | I84: Check whether new orders are reported correctly or invoiced order have been removed from the sales dashboard.
I85: deferred revenue
E95: New Orders in Current Week | R95: 10

Sheet W6
E2: ENTITY NAME : | G2: =+parameters!D2 -> Diam India | I2: ORDER BOOK SYNTHESIS in K€
E4: WEEK : | G4: W6 | I4: Cells to be filled in
E6: MONTH : | G6: =+VLOOKUP(G4, parameters!G:H, 2, 0) -> February
E8: TURNOVER | F8: =parameters!D4 -> k€ | H8: YTD Turnover | J8: =+G6&" Turnover" -> February Turnover | L8: Last estim. for the month: | O8: Forecast 2026
H9: =+"from January 1 until end of "&G4 -> from January 1 until end of W6 | J9: =+"from "&G6&" 1 until end of "&G4 -> from February 1 until end of W6 | L9: =+G6 -> February | O9: =+G4 -> W6 | P9: =+VLOOKUP(G4, parameters!$G$9:$I$61,3,0) -> W5 | Q9: Var
E10: EXTERNAL SALES INVOICED (=outside group) | H10: =600+J10 -> 667.29 | J10: 67.29 | L10: =J10+O17 -> 508.44043 | O10: =+H10+K17 -> 1529.6503 | P10: {=INDIRECT(ADDRESS(10,15,,,VLOOKUP($G$4,parameters!$G:$I,3,0)))} -> 1578.2 | Q10: =O10-P10 -> -48.549665
E11: GROUP SALES INVOICED | H11: =13+J11 -> 15.39 | J11: 2.39 | L11: =J11+O18 -> 2.39001 | O11: =+H11+K18 -> 22.18016 | P11: {=INDIRECT(ADDRESS(11,15,,,VLOOKUP($G$4,parameters!$G:$I,3,0)))} -> 19.96 | Q11: =O11-P11 -> 2.22016 | S11: Definition orders : you consider the orders which are sure even if the order customers paper order is not yet received
E12: TOTAL | H12: =SUM(H10:H11) -> 682.68 | J12: =SUM(J10:J11) -> 69.68 | L12: =SUM(L10:L11) -> 510.83044 | O12: =SUM(O10:O11) -> 1551.8305 | P12: =SUM(P10:P11) -> 1598.16 | Q12: =O12-P12 -> -46.329505 | S12: The quantity, value, and delivery date can be changed before final delivery
E16: ORDERBOOK | F16: =+F8 -> k€ | I16: =H12-J12 -> 613 | J16: TOTAL ORDERBOOK | K16: Total amount 2026 | L16: Total amount 2027 | N16: 46023 | O16: 46054 | P16: 46082 | Q16: 46113 | R16: 46143 | S16: 46174 | T16: 46204 | U16: 46235 | V16: 46266 | W16: 46296 | X16: 46327 | Y16: 46357 | AA16: 46388 | AB16: 46419 | AC16: 46447 | AD16: 46478 | AE16: 46508 | AF16: 46539 | AG16: 46569 | AH16: 46600 | AI16: 46631 | AJ16: 46661 | AK16: 46692 | AL16: 46722
E17: External | J17: =+SUMIF($F$24:$F$70,"External",$J$24:$J$70) -> 1045.8097 | K17: =+SUMIF($F$24:$F$63,"External",$K$24:$K$63) -> 862.36034 | L17: =+SUMIF($F$24:$F$63,"External",$L$24:$L$63) -> 0 | N17: =+SUMIF($F$24:$F$70,"External",N$24:N$70) -> 0 | O17: =+SUMIF($F$24:$F$70,"External",O$24:O$70) -> 441.15043 | P17: =+SUMIF($F$24:$F$70,"External",P$24:P$70) -> 355.22217 | Q17: =+SUMIF($F$24:$F$70,"External",Q$24:Q$70) -> 199.32363 | R17: =+SUMIF($F$24:$F$70,"External",R$24:R$70) -> 9.0353 | S17: =+SUMIF($F$24:$F$70,"External",S$24:S$70) -> 29.08964 | T17: =+SUMIF($F$24:$F$70,"External",T$24:T$70) -> 11.98855 | U17: =+SUMIF($F$24:$F$70,"External",U$24:U$70) -> 0 | V17: =+SUMIF($F$24:$F$63,"External",V$24:V$63) -> 0 | W17: =+SUMIF($F$24:$F$63,"External",W$24:W$63) -> 0 | X17: =+SUMIF($F$24:$F$63,"External",X$24:X$63) -> 0 | Y17: =+SUMIF($F$24:$F$63,"External",Y$24:Y$63) -> 0 | AA17: =+SUMIF($F$24:$F$63,"External",AA$24:AA$63) -> 0 | AB17: =+SUMIF($F$24:$F$63,"External",AB$24:AB$63) -> 0 | AC17: =+SUMIF($F$24:$F$63,"External",AC$24:AC$63) -> 0 | AD17: =+SUMIF($F$24:$F$63,"External",AD$24:AD$63) -> 0 | AE17: =+SUMIF($F$24:$F$63,"External",AE$24:AE$63) -> 0 | AF17: =+SUMIF($F$24:$F$63,"External",AF$24:AF$63) -> 0 | AG17: =+SUMIF($F$24:$F$63,"External",AG$24:AG$63) -> 0 | AH17: =+SUMIF($F$24:$F$63,"External",AH$24:AH$63) -> 0 | ... AL17: =+SUMIF($F$24:$F$63,"External",AL$24:AL$63) -> 0
E18: Group | J18: =+SUMIF($F$24:$F$63,"Group",$J$24:$J$63) -> 6.79016 | K18: =+SUMIF($F$24:$F$63,"Group",$K$24:$K$63) -> 6.79016 | L18: =SUMIF($F$24:$F$63,"Group",$L$24:$L$63) -> 0 | N18: =+SUMIF($F$24:$F$70,"Group",N$24:N$70) -> 0 | O18: =+SUMIF($F$24:$F$70,"Group",O$24:O$70) -> 1e-05 | P18: =+SUMIF($F$24:$F$63,"Group",P$24:P$63) -> 0 | Q18: =+SUMIF($F$24:$F$63,"Group",Q$24:Q$63) -> 6.79015 | R18: =+SUMIF($F$24:$F$63,"Group",R$24:R$63) -> 0 | S18: =+SUMIF($F$24:$F$63,"Group",S$24:S$63) -> 0 | T18: =+SUMIF($F$24:$F$63,"Group",T$24:T$63) -> 0 | U18: =+SUMIF($F$24:$F$63,"Group",U$24:U$63) -> 0 | V18: =+SUMIF($F$24:$F$63,"Group",V$24:V$63) -> 0 | W18: =+SUMIF($F$24:$F$63,"Group",W$24:W$63) -> 0 | ... Y18: =+SUMIF($F$24:$F$63,"Group",Y$24:Y$63) -> 0 | AA18: =+SUMIF($F$24:$F$63,"Group",AA$24:AA$63) -> 0 | AB18: =+SUMIF($F$24:$F$63,"Group",AB$24:AB$63) -> 0 | AC18: =+SUMIF($F$24:$F$63,"Group",AC$24:AC$63) -> 0 | AD18: =+SUMIF($F$24:$F$63,"Group",AD$24:AD$63) -> 0 | AE18: =+SUMIF($F$24:$F$63,"Group",AE$24:AE$63) -> 0 | AF18: =+SUMIF($F$24:$F$63,"Group",AF$24:AF$63) -> 0 | AG18: =+SUMIF($F$24:$F$63,"Group",AG$24:AG$63) -> 0 | AH18: =+SUMIF($F$24:$F$63,"Group",AH$24:AH$63) -> 0 | ... AL18: =+SUMIF($F$24:$F$63,"Group",AL$24:AL$63) -> 0
E19: TOTAL | J19: =SUM(J17:J18) -> 1052.5999 | K19: =SUM(K17:K18) -> 869.1505 | L19: =SUM(L17:L18) -> 0 | N19: =SUM(N17:N18) -> 0 | O19: =SUM(O17:O18) -> 441.15044 | P19: =SUM(P17:P18) -> 355.22217 | Q19: =SUM(Q17:Q18) -> 206.11378 | R19: =SUM(R17:R18) -> 9.0353 | S19: =SUM(S17:S18) -> 29.08964 | T19: =SUM(T17:T18) -> 11.98855 | U19: =SUM(U17:U18) -> 0 | ... Y19: =SUM(Y17:Y18) -> 0 | AA19: =SUM(AA17:AA18) -> 0 | AB19: =SUM(AB17:AB18) -> 0 | AC19: =SUM(AC17:AC18) -> 0 | AD19: =SUM(AD17:AD18) -> 0 | AE19: =SUM(AE17:AE18) -> 0 | AF19: =SUM(AF17:AF18) -> 0 | AG19: =SUM(AG17:AG18) -> 0 | AH19: =SUM(AH17:AH18) -> 0 | ... AL19: =SUM(AL17:AL18) -> 0
I21: check | J21: =IF(SUM(J24:J70)=J19, "OK", "Please correct: the sum of orders below is not equal to the total calculated above. Make sure to pick External or Group for each order and don't change the formulas in columns K and L") -> OK | N21: 2026 | AA21: 2027
E23: Customer Name | F23: External or Group | G23: Brand | H23: Outgroup | I23: Segment | J23: TOTAL ORDERBOOK | K23: Total amount 2026 | L23: Total amount 2026 | N23: 46023 | O23: 46054 | P23: 46082 | Q23: 46113 | R23: 46143 | S23: 46174 | T23: 46204 | U23: 46235 | V23: 46266 | W23: 46296 | X23: 46327 | Y23: 46357 | AA23: 46388 | AB23: 46419 | AC23: 46447 | AD23: 46478 | AE23: 46508 | AF23: 46539 | AG23: 46569 | AH23: 46600 | AI23: 46631 | AJ23: 46661 | AK23: 46692 | AL23: 46722
E24: BACCAROSE PERFUMES AND BEAUTY PRODUCTS PVT LTD | F24: External | G24: Gucci | H24: CL0920 Coty - other brands | I24: Shopfitting | J24: =+K24+L24 -> 0 | K24: =SUM(N24:Y24) -> 0 | L24: =SUM(AA24:AL24) -> 0 | N24: 0
E25: BACCAROSE PERFUMES AND BEAUTY PRODUCTS PVT LTD | F25: External | G25: Laura Mercier | H25: CL0540 Laura Mercier | I25: Prestige Cosmetic | J25: =+K25+L25 -> 7.26175 | K25: =SUM(N25:Y25) -> 7.26175 | L25: =SUM(AA25:AL25) -> 0 | Q25: 7.26175
E26: BACCAROSE PERFUMES AND BEAUTY PRODUCTS PVT LTD | F26: External | G26: Shiseido | H26: CL0285 Shiseido | I26: Prestige Cosmetic | J26: =+K26+L26 -> 19.0875 | K26: =SUM(N26:Y26) -> 19.0875 | L26: =SUM(AA26:AL26) -> 0 | P26: 19.0875
E27: Beauty Impex Pvt. Ltd | F27: External | G27: Guerlain | H27: CL0130 Guerlain | I27: Prestige Cosmetic | J27: =+K27+L27 -> 0.15439 | K27: =SUM(N27:Y27) -> 0.15439 | L27: =SUM(AA27:AL27) -> 0 | N27: 0 | O27: 0.15439
E28: Best In Brands | F28: External | G28: Shiseido | H28: CL0285 Shiseido | I28: Prestige Cosmetic | J28: =+K28+L28 -> 8.06821 | K28: =SUM(N28:Y28) -> 8.06821 | L28: =SUM(AA28:AL28) -> 0 | P28: 8.06821
E29: CHANEL INDIA | F29: External | G29: Chanel | H29: CL0065 Chanel | I29: Shopfitting | J29: =+K29+L29 -> 5.8857 | K29: =SUM(N29:Y29) -> 5.8857 | L29: =SUM(AA29:AL29) -> 0 | N29: 0 | O29: 5.8857
E30: Clarins Pte Ltd | F30: External | G30: Clarins | H30: CL0070 Clarins | I30: Shopfitting | J30: =+K30+L30 -> 0.42959 | K30: =SUM(N30:Y30) -> 0.42959 | L30: =SUM(AA30:AL30) -> 0 | O30: 0.42959
E31: Connectiv FZCO | F31: External | G31: L'Oreal TR | H31: CL0180 L'Oréal Divers | I31: Shopfitting | J31: =+K31+L31 -> 0.8584 | K31: =SUM(N31:Y31) -> 0.8584 | L31: =SUM(AA31:AL31) -> 0 | P31: 0.8584
E32: Coty | F32: External | G32: Coty | H32: CL0920 Coty - other brands | I32: Shopfitting | J32: =+K32+L32 -> 0 | K32: =SUM(N32:Y32) -> 0 | L32: =SUM(AA32:AL32) -> 0 | N32: 0
E33: Coty | F33: External | G33: Kylie | H33: CL0705 Coty KJ | I33: Shopfitting | J33: =+K33+L33 -> 0 | K33: =SUM(N33:Y33) -> 0 | L33: =SUM(AA33:AL33) -> 0 | N33: 0
E34: DDS | F34: Group | G34: Coty | H34: CL0920 Coty - other brands | I34: Shopfitting | J34: =+K34+L34 -> 6.79016 | K34: =SUM(N34:Y34) -> 6.79016 | L34: =SUM(AA34:AL34) -> 0 | N34: 0 | O34: 1e-05 | Q34: 6.79015
E35: DIAM Turkey | F35: Group | G35: Fenty Beauty | H35: CL0550 Kendo - Fenty | I35: Prestige Cosmetic | J35: =+K35+L35 -> 0 | K35: =SUM(N35:Y35) -> 0 | L35: =SUM(AA35:AL35) -> 0 | O35: 0
E36: Estee Lauder AG Lachen | F36: External | G36: Joe Malone | H36: CL0535 Joe Malone | I36: Prestige Cosmetic | J36: =+K36+L36 -> 0.34367 | K36: =SUM(N36:Y36) -> 0.34367 | L36: =SUM(AA36:AL36) -> 0 | O36: 0.34367
E37: Estee Lauder Middle East FZE | F37: External | G37: Too Faced | H37: CL0575 Too Faced | I37: Prestige Cosmetic | J37: =+K37+L37 -> 155.09715 | K37: =SUM(N37:Y37) -> 155.09715 | L37: =SUM(AA37:AL37) -> 0 | P37: 155.09715
E38: Estee Lauder Saudi Limited | F38: External | G38: Clinique | H38: CL0075 Clinique | I38: Prestige Cosmetic | J38: =+K38+L38 -> 3.57085 | K38: =SUM(N38:Y38) -> 3.57085 | L38: =SUM(AA38:AL38) -> 0 | O38: 3.57085
E39: Fenty Beauty LLC | F39: External | G39: Fenty Beauty | H39: CL0550 Kendo - Fenty | I39: Prestige Cosmetic | J39: =+K39+L39 -> 0.09252 | K39: =SUM(N39:Y39) -> 0.09252 | L39: =SUM(AA39:AL39) -> 0 | N39: 0 | O39: 0.09252
E40: Forma Brands, LLC f/k/a FB Acquisition LLC | F40: External | G40: Forma | H40: CL0735 Morphe | I40: Prestige Cosmetic | J40: =+K40+L40 -> 78.78296 | K40: =SUM(N40:Y40) -> 78.78296 | L40: =SUM(AA40:AL40) -> 0 | N40: 0 | O40: 53.12327 | Q40: 25.65969
E41: Global Shoppers Stop Beauty Brands Ltd | F41: External | G41: Clarins | H41: CL0070 Clarins | I41: Shopfitting | J41: =+K41+L41 -> 0 | K41: =SUM(N41:Y41) -> 0 | L41: =SUM(AA41:AL41) -> 0 | N41: 0
E42: Global Shoppers Stop Beauty Brands Ltd | F42: External | G42: Maison Margiela | H42: CL0180 L'Oréal Divers | I42: Shopfitting | J42: =+K42+L42 -> 0 | K42: =SUM(N42:Y42) -> 0 | L42: =SUM(AA42:AL42) -> 0 | N42: 0
E43: Global Shoppers Stop Beauty Brands Ltd | F43: External | G43: Nars | H43: CL0226 Nars | I43: Prestige Cosmetic | J43: =+K43+L43 -> 120.31943 | K43: =SUM(N43:Y43) -> 120.31943 | L43: =SUM(AA43:AL43) -> 0 | N43: 0 | O43: 41.06113 | P43: 79.2583
E44: Global Shoppers Stop Beauty Brands Ltd | F44: External | G44: Prada | H44: CL0180 L'Oréal Divers | I44: Shopfitting | J44: =+K44+L44 -> 16.99914 | K44: =SUM(N44:Y44) -> 16.99914 | L44: =SUM(AA44:AL44) -> 0 | N44: 0 | O44: 0.32537 | P44: 16.67377
E45: Indosing Distribution | F45: External | G45: Benefit | H45: CL0315 Benefit | I45: Prestige Cosmetic | J45: =+K45+L45 -> 23.51726 | K45: =SUM(N45:Y45) -> 23.51726 | L45: =SUM(AA45:AL45) -> 0 | N45: 0 | O45: 23.51726
E46: L Beauty Pte | F46: External | G46: Benefit | H46: CL0315 Benefit | I46: Prestige Cosmetic | J46: =+K46+L46 -> 38.26092 | K46: =SUM(N46:Y46) -> 38.26092 | L46: =SUM(AA46:AL46) -> 0 | N46: 0 | O46: 5.64633 | P46: 10.14104 | Q46: 22.47355
E47: L'Oreal India | F47: External | G47: Lancome | H47: CL0155 Lancôme | I47: Shopfitting | J47: =+K47+L47 -> 10.10262 | K47: =SUM(N47:Y47) -> 10.10262 | L47: =SUM(AA47:AL47) -> 0 | O47: 10.10262
E48: L'Oreal India | F48: External | G48: Lancome | H48: CL0155 Lancôme | I48: Prestige Cosmetic | J48: =+K48+L48 -> 16.752454 | K48: =SUM(N48:Y48) -> 16.752454 | L48: =SUM(AA48:AL48) -> 0 | O48: 16.752454
E49: L'Oreal India | F49: External | G49: YSL | H49: CL0310 YSL | I49: Shopfitting | J49: =+K49+L49 -> 1.19282 | K49: =SUM(N49:Y49) -> 1.19282 | L49: =SUM(AA49:AL49) -> 0 | N49: 0 | O49: 1.19282
E50: L'Oreal Travel Retail | F50: External | G50: Armani | H50: CL0345 Armani | I50: Shopfitting | J50: =+K50+L50 -> 31.13409 | K50: =SUM(N50:Y50) -> 31.13409 | L50: =SUM(AA50:AL50) -> 0 | O50: 1e-05 | Q50: 31.13408
E51: L'Oreal Travel Retail | F51: External | G51: Lancome | H51: CL0155 Lancôme | I51: Shopfitting | J51: =+K51+L51 -> 16.50256 | K51: =SUM(N51:Y51) -> 16.50256 | L51: =SUM(AA51:AL51) -> 0 | Q51: 16.50256
E52: L'Oreal Travel Retail | F52: External | G52: Loreal Paris | H52: CL0170 L'Oréal Paris (L'OAP) | I52: Shopfitting | J52: =+K52+L52 -> 8.90143 | K52: =SUM(N52:Y52) -> 8.90143 | L52: =SUM(AA52:AL52) -> 0 | O52: 8.90143
E53: L'Oreal Travel Retail | F53: External | G53: Multi | H53: CL0180 L'Oréal Divers | I53: Shopfitting | J53: =+K53+L53 -> 59.74111 | K53: =SUM(N53:Y53) -> 59.74111 | L53: =SUM(AA53:AL53) -> 0 | Q53: 59.74111
E54: L'Oreal Travel Retail | F54: External | G54: OAP | H54: CL0170 L'Oréal Paris (L'OAP) | I54: Shopfitting | J54: =+K54+L54 -> 8.80696 | K54: =SUM(N54:Y54) -> 8.80696 | L54: =SUM(AA54:AL54) -> 0 | Q54: 8.80696
E55: L'Oreal Travel Retail | F55: External | G55: RALPH LAUREN | H55: CL0405 Ralph Lauren | I55: Shopfitting | J55: =+K55+L55 -> 0 | K55: =SUM(N55:Y55) -> 0 | L55: =SUM(AA55:AL55) -> 0 | O55: 0
E56: L'Oreal Travel Retail | F56: External | G56: YSL | H56: CL0310 YSL | I56: Shopfitting | J56: =+K56+L56 -> 27.74393 | K56: =SUM(N56:Y56) -> 27.74393 | L56: =SUM(AA56:AL56) -> 0 | N56: 0 | Q56: 27.74393
E57: Puig India | F57: External | G57: CH, RB & JPG | H57: CL0840 Puig - other brands | I57: Shopfitting | J57: =+K57+L57 -> 14.850921 | K57: =SUM(N57:Y57) -> 14.850921 | L57: =SUM(AA57:AL57) -> 0 | N57: 0 | P57: 14.850921
E58: Rare Beauty LLC | F58: External | G58: Rare Beauty | H58: CL0765 Rare Beauty | I58: Prestige Cosmetic | J58: =+K58+L58 -> 57.10995 | K58: =SUM(N58:Y58) -> 57.10995 | L58: =SUM(AA58:AL58) -> 0 | N58: 0 | O58: 57.10995
E59: Reliance Luxe Beauty Limited | F59: External | G59: Rare Beauty | H59: CL0765 Rare Beauty | I59: Prestige Cosmetic | J59: =+K59+L59 -> 41.94971 | K59: =SUM(N59:Y59) -> 41.94971 | L59: =SUM(AA59:AL59) -> 0 | O59: 41.94971
E60: Shoppers Stop Ltd | F60: External | G60: Clinique | H60: CL0075 Clinique | I60: Prestige Cosmetic | J60: =+K60+L60 -> 3.321 | K60: =SUM(N60:Y60) -> 3.321 | L60: =SUM(AA60:AL60) -> 0 | O60: 3.321
E61: Shoppers Stop Ltd | F61: External | G61: ELCA Brand | H61: CL0680 Estée Lauder - other brands | I61: Prestige Cosmetic | J61: =+K61+L61 -> 0 | K61: =SUM(N61:Y61) -> 0 | L61: =SUM(AA61:AL61) -> 0 | N61: 0
E62: Shoppers Stop Ltd | F62: External | G62: Tom Ford | H62: CL0570 Tom Ford | I62: Shopfitting | J62: =+K62+L62 -> 22.85927 | K62: =SUM(N62:Y62) -> 22.85927 | L62: =SUM(AA62:AL62) -> 0 | N62: 0 | O62: 22.85927
E63: ELCA Cosmetics Pvt. Ltd. | F63: External | G63: Clinique | H63: CL0075 Clinique | I63: Prestige Cosmetic | J63: =+K63+L63 -> 62.66207 | K63: =SUM(N63:Y63) -> 62.66207 | L63: =SUM(AA63:AL63) -> 0 | N63: 0 | O63: 57.99121 | P63: 2.33543 | T63: 2.33543
E64: ELCA Cosmetics Pvt. Ltd. | F64: External | G64: Dr Jart+ | H64: CL0680 Estée Lauder - other brands | I64: Prestige Cosmetic | J64: =+K64+L64 -> 3.18812 | K64: =SUM(N64:Y64) -> 3.18812 | L64: =SUM(AA64:AL64) -> 0 | N64: 0 | P64: 3.18812
E65: ELCA Cosmetics Pvt. Ltd. | F65: External | G65: Estee Lauder | H65: CL0110 Estée Lauder | I65: Prestige Cosmetic | J65: =+K65+L65 -> 81.08612 | K65: =SUM(N65:Y65) -> 81.08612 | L65: =SUM(AA65:AL65) -> 0 | N65: 0 | O65: 76.41526 | P65: 2.33543 | T65: 2.33543
E66: ELCA Cosmetics Pvt. Ltd. | F66: External | G66: Mac | H66: CL0395 MAC | I66: Prestige Cosmetic | J66: =+K66+L66 -> 22.09122 | K66: =SUM(N66:Y66) -> 22.09122 | L66: =SUM(AA66:AL66) -> 0 | N66: 0 | O66: 8.38506 | P66: 2.33543 | R66: 9.0353 | T66: 2.33543
E67: ELCA Cosmetics Pvt. Ltd. | F67: External | G67: Smashbox | H67: CL0525 Smashbox | I67: Prestige Cosmetic | J67: =+K67+L67 -> 3.36 | K67: =SUM(N67:Y67) -> 3.36 | L67: =SUM(AA67:AL67) -> 0 | N67: 0 | O67: 0.08644 | P67: 1.63678 | T67: 1.63678
E68: ELCA Cosmetics Pvt. Ltd. | F68: External | G68: The Ordinary | H68: CL0680 Estée Lauder - other brands | I68: Prestige Cosmetic | J68: =+K68+L68 -> 15.44741 | K68: =SUM(N68:Y68) -> 15.44741 | L68: =SUM(AA68:AL68) -> 0 | N68: 0 | O68: 0.91922 | P68: 13.02117 | T68: 1.50702
E69: ELCA Cosmetics Pvt. Ltd. | F69: External | G69: Tom Ford | H69: CL0570 Tom Ford | I69: Prestige Cosmetic | J69: =+K69+L69 -> 27.06692 | K69: =SUM(N69:Y69) -> 27.06692 | L69: =SUM(AA69:AL69) -> 0 | N69: 0 | O69: 1.0139 | P69: 25.27454 | T69: 0.77848
E70: ELCA Cosmetics Pvt. Ltd. | F70: External | G70: Too Faced | H70: CL0575 Too Faced | I70: Prestige Cosmetic | J70: =+K70+L70 -> 31.2096 | K70: =SUM(N70:Y70) -> 31.2096 | L70: =SUM(AA70:AL70) -> 0 | P70: 1.05998 | S70: 29.08964 | T70: 1.05998
E73: Deferred revenue balance as on | F73: 46023 | G73: 218 | H73: K Euro
E74: Add: Deferred revenue addition during Jan-26 | G74: 151 | H74: K Euro
E75: Less: Deferred revenue reversed during Jan-26 | G75: 138 | H75: K Euro
E76: Deferred revenue balance as on | F76: 46053 | G76: =G73+G74-G75 -> 231 | H76: K Euro
E78: Brand | H78: Amt. in K Euro
E79: Benefit | H79: 27.153124
E80: Clinique | H80: 0.0859
E81: Estee Lauder | H81: 0.0859
E82: Fenty Beauty | H82: 7e-07
E83: Jo Malone | H83: 0.06526
E84: Mac | H84: 0.0859
E85: Nars | H85: 8.8550295
E86: Smashbox | H86: 0.0864415
E87: The Ordinary | H87: 0.0859
E88: Tom Ford | H88: 9.66332
E89: YSL | H89: 27.74393
E90: Grand Total | H90: =SUM(H79:H89) -> 73.910705

Sheet W7
E2: ENTITY NAME : | G2: =+parameters!D2 -> Diam India | I2: ORDER BOOK SYNTHESIS in K€
E4: WEEK : | G4: W7 | I4: Cells to be filled in
E6: MONTH : | G6: =+VLOOKUP(G4, parameters!G:H, 2, 0) -> February
E8: TURNOVER | F8: =parameters!D4 -> k€ | H8: YTD Turnover | J8: =+G6&" Turnover" -> February Turnover | L8: Last estim. for the month: | O8: Forecast 2026
H9: =+"from January 1 until end of "&G4 -> from January 1 until end of W7 | J9: =+"from "&G6&" 1 until end of "&G4 -> from February 1 until end of W7 | L9: =+G6 -> February | O9: =+G4 -> W7 | P9: =+VLOOKUP(G4, parameters!$G$9:$I$61,3,0) -> W6 | Q9: Var
E10: EXTERNAL SALES INVOICED (=outside group) | H10: =600+J10 -> 673 | J10: 73 | L10: =J10+O17 -> 460.98343 | O10: =+H10+K17 -> 1674.1901 | P10: {=INDIRECT(ADDRESS(10,15,,,VLOOKUP($G$4,parameters!$G:$I,3,0)))} -> 1529.6503 | Q10: =O10-P10 -> 144.5398
E11: GROUP SALES INVOICED | H11: =13+J11 -> 23 | J11: 10 | L11: =J11+O18 -> 11.663103 | O11: =+H11+K18 -> 31.453248 | P11: {=INDIRECT(ADDRESS(11,15,,,VLOOKUP($G$4,parameters!$G:$I,3,0)))} -> 22.18016 | Q11: =O11-P11 -> 9.2730881 | S11: Definition orders : you consider the orders which are sure even if the order customers paper order is not yet received
E12: TOTAL | H12: =SUM(H10:H11) -> 696 | J12: 83 | L12: =SUM(L10:L11) -> 472.64653 | O12: =SUM(O10:O11) -> 1705.6434 | P12: =SUM(P10:P11) -> 1551.8305 | Q12: =O12-P12 -> 153.81289 | S12: The quantity, value, and delivery date can be changed before final delivery
E16: ORDERBOOK | F16: =+F8 -> k€ | I16: =H12-J12 -> 613 | J16: TOTAL ORDERBOOK | K16: Total amount 2026 | L16: Total amount 2027 | N16: 46023 | O16: 46054 | P16: 46082 | Q16: 46113 | R16: 46143 | S16: 46174 | T16: 46204 | U16: 46235 | V16: 46266 | W16: 46296 | X16: 46327 | Y16: 46357 | AA16: 46388 | AB16: 46419 | AC16: 46447 | AD16: 46478 | AE16: 46508 | AF16: 46539 | AG16: 46569 | AH16: 46600 | AI16: 46631 | AJ16: 46661 | AK16: 46692 | AL16: 46722
E17: External | J17: =+SUMIF($F$24:$F$72,"External",$J$24:$J$72) -> 1001.1901 | K17: =+SUMIF($F$24:$F$72,"External",$K$24:$K$72) -> 1001.1901 | L17: =+SUMIF($F$24:$F$72,"External",$L$24:$L$72) -> 0 | N17: =+SUMIF($F$24:$F$72,"External",N$24:N$72) -> 0 | O17: =+SUMIF($F$24:$F$72,"External",O$24:O$72) -> 387.98343 | P17: =+SUMIF($F$24:$F$72,"External",P$24:P$72) -> 355.22215 | Q17: =+SUMIF($F$24:$F$72,"External",Q$24:Q$72) -> 208.44479 | R17: =+SUMIF($F$24:$F$72,"External",R$24:R$72) -> 9.035297 | S17: =+SUMIF($F$24:$F$72,"External",S$24:S$72) -> 28.515911 | T17: =+SUMIF($F$24:$F$72,"External",T$24:T$72) -> 11.988554 | U17: =+SUMIF($F$24:$F$72,"External",U$24:U$72) -> 0 | ... Y17: =+SUMIF($F$24:$F$72,"External",Y$24:Y$72) -> 0 | AA17: =+SUMIF($F$24:$F$72,"External",AA$24:AA$72) -> 0 | AB17: =+SUMIF($F$24:$F$72,"External",AB$24:AB$72) -> 0 | AC17: =+SUMIF($F$24:$F$72,"External",AC$24:AC$72) -> 0 | AD17: =+SUMIF($F$24:$F$72,"External",AD$24:AD$72) -> 0 | AE17: =+SUMIF($F$24:$F$72,"External",AE$24:AE$72) -> 0 | AF17: =+SUMIF($F$24:$F$72,"External",AF$24:AF$72) -> 0 | AG17: =+SUMIF($F$24:$F$72,"External",AG$24:AG$72) -> 0 | AH17: =+SUMIF($F$24:$F$72,"External",AH$24:AH$72) -> 0 | ... AL17: =+SUMIF($F$24:$F$72,"External",AL$24:AL$72) -> 0
E18: Group | J18: =+SUMIF($F$24:$F$72,"Group",$J$24:$J$72) -> 8.4532481 | K18: =+SUMIF($F$24:$F$72,"Group",$K$24:$K$72) -> 8.4532481 | L18: =SUMIF($F$24:$F$72,"Group",$L$24:$L$72) -> 0 | N18: =+SUMIF($F$24:$F$72,"Group",N$24:N$72) -> 0 | O18: =+SUMIF($F$24:$F$72,"Group",O$24:O$72) -> 1.6631026 | P18: =+SUMIF($F$24:$F$72,"Group",P$24:P$72) -> 0 | Q18: =+SUMIF($F$24:$F$72,"Group",Q$24:Q$72) -> 6.7901454 | R18: =+SUMIF($F$24:$F$72,"Group",R$24:R$72) -> 0 | S18: =+SUMIF($F$24:$F$72,"Group",S$24:S$72) -> 0 | T18: =+SUMIF($F$24:$F$72,"Group",T$24:T$72) -> 0 | U18: =+SUMIF($F$24:$F$72,"Group",U$24:U$72) -> 0 | ... Y18: =+SUMIF($F$24:$F$72,"Group",Y$24:Y$72) -> 0 | AA18: =+SUMIF($F$24:$F$72,"Group",AA$24:AA$72) -> 0 | AB18: =+SUMIF($F$24:$F$72,"Group",AB$24:AB$72) -> 0 | AC18: =+SUMIF($F$24:$F$72,"Group",AC$24:AC$72) -> 0 | AD18: =+SUMIF($F$24:$F$72,"Group",AD$24:AD$72) -> 0 | AE18: =+SUMIF($F$24:$F$72,"Group",AE$24:AE$72) -> 0 | AF18: =+SUMIF($F$24:$F$72,"Group",AF$24:AF$72) -> 0 | AG18: =+SUMIF($F$24:$F$72,"Group",AG$24:AG$72) -> 0 | AH18: =+SUMIF($F$24:$F$72,"Group",AH$24:AH$72) -> 0 | ... AL18: =+SUMIF($F$24:$F$72,"Group",AL$24:AL$72) -> 0
E19: TOTAL | J19: =SUM(J17:J18) -> 1009.6434 | K19: =SUM(K17:K18) -> 1009.6434 | L19: =SUM(L17:L18) -> 0 | N19: =SUM(N17:N18) -> 0 | O19: =SUM(O17:O18) -> 389.64653 | P19: =SUM(P17:P18) -> 355.22215 | Q19: =SUM(Q17:Q18) -> 215.23494 | R19: =SUM(R17:R18) -> 9.035297 | S19: =SUM(S17:S18) -> 28.515911 | T19: =SUM(T17:T18) -> 11.988554 | U19: =SUM(U17:U18) -> 0 | ... Y19: =SUM(Y17:Y18) -> 0 | AA19: =SUM(AA17:AA18) -> 0 | AB19: =SUM(AB17:AB18) -> 0 | AC19: =SUM(AC17:AC18) -> 0 | AD19: =SUM(AD17:AD18) -> 0 | AE19: =SUM(AE17:AE18) -> 0 | AF19: =SUM(AF17:AF18) -> 0 | AG19: =SUM(AG17:AG18) -> 0 | AH19: =SUM(AH17:AH18) -> 0 | ... AL19: =SUM(AL17:AL18) -> 0
I21: check | J21: =IF(SUM(J24:J72)=J19, "OK", "Please correct: the sum of orders below is not equal to the total calculated above. Make sure to pick External or Group for each order and don't change the formulas in columns K and L") -> OK | N21: 2026 | AA21: 2027
E23: Customer Name | F23: External or Group | G23: Brand | H23: Outgroup | I23: Segment | J23: TOTAL ORDERBOOK | K23: Total amount 2026 | L23: Total amount 2026 | N23: 46023 | O23: 46054 | P23: 46082 | Q23: 46113 | R23: 46143 | S23: 46174 | T23: 46204 | U23: 46235 | V23: 46266 | W23: 46296 | X23: 46327 | Y23: 46357 | AA23: 46388 | AB23: 46419 | AC23: 46447 | AD23: 46478 | AE23: 46508 | AF23: 46539 | AG23: 46569 | AH23: 46600 | AI23: 46631 | AJ23: 46661 | AK23: 46692 | AL23: 46722
D24: X | E24: BACCAROSE PERFUMES AND BEAUTY PRODUCTS PVT LTD | F24: External | G24: Laura Mercier | H24: CL0540 Laura Mercier | I24: Prestige Cosmetic | J24: =+K24+L24 -> 7.2617511 | K24: =SUM(N24:Y24) -> 7.2617511 | L24: =SUM(AA24:AL24) -> 0 | Q24: 7.2617511
E25: BACCAROSE PERFUMES AND BEAUTY PRODUCTS PVT LTD | F25: External | G25: Shiseido | H25: CL0285 Shiseido | I25: Prestige Cosmetic | J25: =+K25+L25 -> 19.0875 | K25: =SUM(N25:Y25) -> 19.0875 | L25: =SUM(AA25:AL25) -> 0 | P25: 19.0875
E26: Beauty Impex Pvt. Ltd | F26: External | G26: Guerlain | H26: CL0130 Guerlain | I26: Prestige Cosmetic | J26: =+K26+L26 -> 0 | K26: =SUM(N26:Y26) -> 0 | L26: =SUM(AA26:AL26) -> 0
E27: Best In Brands | F27: External | G27: Shiseido | H27: CL0285 Shiseido | I27: Prestige Cosmetic | J27: =+K27+L27 -> 8.0682141 | K27: =SUM(N27:Y27) -> 8.0682141 | L27: =SUM(AA27:AL27) -> 0 | P27: 8.0682141
E28: CHANEL INDIA | F28: External | G28: Chanel | H28: CL0065 Chanel | I28: Shopfitting | J28: =+K28+L28 -> 5.8856955 | K28: =SUM(N28:Y28) -> 5.8856955 | L28: =SUM(AA28:AL28) -> 0 | O28: 5.8856955
E29: Clarins Pte Ltd | F29: External | G29: Clarins | H29: CL0070 Clarins | I29: Shopfitting | J29: =+K29+L29 -> 0 | K29: =SUM(N29:Y29) -> 0 | L29: =SUM(AA29:AL29) -> 0
E30: Connectiv FZCO | F30: External | G30: L'Oreal TR | H30: CL0180 L'Oréal Divers | I30: Shopfitting | J30: =+K30+L30 -> 0.8584046 | K30: =SUM(N30:Y30) -> 0.8584046 | L30: =SUM(AA30:AL30) -> 0 | P30: 0.8584046
E31: Coty | F31: External | G31: Coty | H31: CL0920 Coty - other brands | I31: Shopfitting | J31: =+K31+L31 -> 0 | K31: =SUM(N31:Y31) -> 0 | L31: =SUM(AA31:AL31) -> 0
E32: Coty | F32: External | G32: Kylie | H32: CL0705 Coty KJ | I32: Shopfitting | J32: =+K32+L32 -> 0 | K32: =SUM(N32:Y32) -> 0 | L32: =SUM(AA32:AL32) -> 0
E33: DDS | F33: Group | G33: Coty | H33: CL0920 Coty - other brands | I33: Shopfitting | J33: =+K33+L33 -> 6.7901454 | K33: =SUM(N33:Y33) -> 6.7901454 | L33: =SUM(AA33:AL33) -> 0 | Q33: 6.7901454
E34: DIAM Turkey | F34: Group | G34: Fenty Beauty | H34: CL0550 Kendo - Fenty | I34: Prestige Cosmetic | J34: =+K34+L34 -> 1.6631026 | K34: =SUM(N34:Y34) -> 1.6631026 | L34: =SUM(AA34:AL34) -> 0 | O34: 1.6631026
E35: Elca Cosmetics Pvt Ltd | F35: External | G35: Too Faced | H35: CL0575 Too Faced | I35: Prestige Cosmetic | J35: =+K35+L35 -> 28.515911 | K35: =SUM(N35:Y35) -> 28.515911 | L35: =SUM(AA35:AL35) -> 0 | S35: 28.515911
E36: ELCA Cosmetics Pvt. Ltd. | F36: External | G36: Clinique | H36: CL0075 Clinique | I36: Prestige Cosmetic | J36: =+K36+L36 -> 62.521814 | K36: =SUM(N36:Y36) -> 62.521814 | L36: =SUM(AA36:AL36) -> 0 | O36: 57.850948 | P36: 2.3354327 | T36: 2.3354327
E37: ELCA Cosmetics Pvt. Ltd. | F37: External | G37: Dr Jart+ | H37: CL0680 Estée Lauder - other brands | I37: Prestige Cosmetic | J37: =+K37+L37 -> 3.1881163 | K37: =SUM(N37:Y37) -> 3.1881163 | L37: =SUM(AA37:AL37) -> 0 | P37: 3.1881163
E38: ELCA Cosmetics Pvt. Ltd. | F38: External | G38: Estee Lauder | H38: CL0110 Estée Lauder | I38: Prestige Cosmetic | J38: =+K38+L38 -> 80.495252 | K38: =SUM(N38:Y38) -> 80.495252 | L38: =SUM(AA38:AL38) -> 0 | O38: 75.824387 | P38: 2.3354327 | T38: 2.3354327
E39: ELCA Cosmetics Pvt. Ltd. | F39: External | G39: Mac | H39: CL0395 MAC | I39: Prestige Cosmetic | J39: =+K39+L39 -> 21.847042 | K39: =SUM(N39:Y39) -> 21.847042 | L39: =SUM(AA39:AL39) -> 0 | O39: 8.1408794 | P39: 2.3354327 | R39: 9.035297 | T39: 2.3354327
E40: ELCA Cosmetics Pvt. Ltd. | F40: External | G40: Smashbox | H40: CL0525 Smashbox | I40: Prestige Cosmetic | J40: =+K40+L40 -> 3.2735576 | K40: =SUM(N40:Y40) -> 3.2735576 | L40: =SUM(AA40:AL40) -> 0 | O40: 0 | P40: 1.6367788 | T40: 1.6367788
E41: ELCA Cosmetics Pvt. Ltd. | F41: External | G41: The Ordinary | H41: CL0680 Estée Lauder - other brands | I41: Prestige Cosmetic | J41: =+K41+L41 -> 15.342188 | K41: =SUM(N41:Y41) -> 15.342188 | L41: =SUM(AA41:AL41) -> 0 | O41: 0.8139934 | P41: 13.021174 | T41: 1.50702
E42: ELCA Cosmetics Pvt. Ltd. | F42: External | G42: Tom Ford | H42: CL0570 Tom Ford | I42: Prestige Cosmetic | J42: =+K42+L42 -> 27.066908 | K42: =SUM(N42:Y42) -> 27.066908 | L42: =SUM(AA42:AL42) -> 0 | O42: 1.0139011 | P42: 25.274529 | T42: 0.7784776
E43: ELCA Cosmetics Pvt. Ltd. | F43: External | G43: Too Faced | H43: CL0575 Too Faced | I43: Prestige Cosmetic | J43: =+K43+L43 -> 2.11996 | K43: =SUM(N43:Y43) -> 2.11996 | L43: =SUM(AA43:AL43) -> 0 | P43: 1.05998 | T43: 1.05998
E44: Estee Lauder AG Lachen | F44: External | G44: Jo Malone | H44: CL0535 Joe Malone | I44: Prestige Cosmetic | J44: =+K44+L44 -> 0.0099548 | K44: =SUM(N44:Y44) -> 0.0099548 | L44: =SUM(AA44:AL44) -> 0 | O44: 0.0099548
E45: Estee Lauder Middle East FZE | F45: External | G45: Too Faced | H45: CL0575 Too Faced | I45: Prestige Cosmetic | J45: =+K45+L45 -> 155.09714 | K45: =SUM(N45:Y45) -> 155.09714 | L45: =SUM(AA45:AL45) -> 0 | P45: 155.09714
E46: Estee Lauder Saudi Limited | F46: External | G46: Clinique | H46: CL0075 Clinique | I46: Prestige Cosmetic | J46: =+K46+L46 -> 3.5708258 | K46: =SUM(N46:Y46) -> 3.5708258 | L46: =SUM(AA46:AL46) -> 0 | O46: 3.5708258
E47: Fenty Beauty LLC | F47: External | G47: Fenty Beauty | H47: CL0550 Kendo - Fenty | I47: Prestige Cosmetic | J47: =+K47+L47 -> 0 | K47: =SUM(N47:Y47) -> 0 | L47: =SUM(AA47:AL47) -> 0
E48: Forma Brands, LLC f/k/a FB Acquisition LLC | F48: External | G48: Forma | H48: CL0735 Morphe | I48: Prestige Cosmetic | J48: =+K48+L48 -> 30.286168 | K48: =SUM(N48:Y48) -> 30.286168 | L48: =SUM(AA48:AL48) -> 0 | O48: 0 | Q48: 30.286168
E49: Global Shoppers Stop Beauty Brands Ltd | F49: External | G49: Clarins | H49: CL0070 Clarins | I49: Shopfitting | J49: =+K49+L49 -> 0 | K49: =SUM(N49:Y49) -> 0 | L49: =SUM(AA49:AL49) -> 0
E50: Global Shoppers Stop Beauty Brands Ltd | F50: External | G50: Maison Margiela | H50: CL0180 L'Oréal Divers | I50: Shopfitting | J50: =+K50+L50 -> 0 | K50: =SUM(N50:Y50) -> 0 | L50: =SUM(AA50:AL50) -> 0
E51: Global Shoppers Stop Beauty Brands Ltd | F51: External | G51: Nars | H51: CL0226 Nars | I51: Prestige Cosmetic | J51: =+K51+L51 -> 116.92212 | K51: =SUM(N51:Y51) -> 116.92212 | L51: =SUM(AA51:AL51) -> 0 | O51: 37.663825 | P51: 79.2583
E52: Global Shoppers Stop Beauty Brands Ltd | F52: External | G52: Prada | H52: CL0180 L'Oréal Divers | I52: Shopfitting | J52: =+K52+L52 -> 16.999136 | K52: =SUM(N52:Y52) -> 16.999136 | L52: =SUM(AA52:AL52) -> 0 | O52: 0.32537 | P52: 16.673766
E53: Indosing Distribution | F53: External | G53: Benefit | H53: CL0315 Benefit | I53: Prestige Cosmetic | J53: =+K53+L53 -> 23.517266 | K53: =SUM(N53:Y53) -> 23.517266 | L53: =SUM(AA53:AL53) -> 0 | O53: 23.517266
E54: L Beauty Pte | F54: External | G54: Benefit | H54: CL0315 Benefit | I54: Prestige Cosmetic | J54: =+K54+L54 -> 47.250297 | K54: =SUM(N54:Y54) -> 47.250297 | L54: =SUM(AA54:AL54) -> 0 | O54: 10.141033 | P54: 10.141033 | Q54: 26.968231
E55: L'Oreal India | F55: External | G55: Lancome | H55: CL0155 Lancôme | I55: Prestige Cosmetic | J55: =+K55+L55 -> 16.75243 | K55: =SUM(N55:Y55) -> 16.75243 | L55: =SUM(AA55:AL55) -> 0 | O55: 16.75243
E56: L'Oreal India | F56: External | G56: Lancome | H56: CL0155 Lancôme | I56: Shopfitting | J56: =+K56+L56 -> 10.102618 | K56: =SUM(N56:Y56) -> 10.102618 | L56: =SUM(AA56:AL56) -> 0 | O56: 10.102618
E57: L'Oreal India | F57: External | G57: YSL | H57: CL0310 YSL | I57: Shopfitting | J57: =+K57+L57 -> 1.1928188 | K57: =SUM(N57:Y57) -> 1.1928188 | L57: =SUM(AA57:AL57) -> 0 | O57: 1.1928188
E58: L'Oreal Travel Retail | F58: External | G58: Armani | H58: CL0345 Armani | I58: Shopfitting | J58: =+K58+L58 -> 31.134083 | K58: =SUM(N58:Y58) -> 31.134083 | L58: =SUM(AA58:AL58) -> 0 | Q58: 31.134083
E59: L'Oreal Travel Retail | F59: External | G59: ARMANI PRIVE | H59: CL0345 Armani | I59: Shopfitting | J59: =+K59+L59 -> 1.05772e-05 | K59: =SUM(N59:Y59) -> 1.05772e-05 | L59: =SUM(AA59:AL59) -> 0 | O59: 1.05772e-05
E60: L'Oreal Travel Retail | F60: External | G60: Lancome | H60: CL0155 Lancôme | I60: Shopfitting | J60: =+K60+L60 -> 16.502558 | K60: =SUM(N60:Y60) -> 16.502558 | L60: =SUM(AA60:AL60) -> 0 | Q60: 16.502558
E61: L'Oreal Travel Retail | F61: External | G61: Loreal Paris | H61: CL0170 L'Oréal Paris (L'OAP) | I61: Shopfitting | J61: =+K61+L61 -> 8.9014259 | K61: =SUM(N61:Y61) -> 8.9014259 | L61: =SUM(AA61:AL61) -> 0 | O61: 8.9014259
E62: L'Oreal Travel Retail | F62: External | G62: Multi | H62: CL0180 L'Oréal Divers | I62: Shopfitting | J62: =+K62+L62 -> 59.741114 | K62: =SUM(N62:Y62) -> 59.741114 | L62: =SUM(AA62:AL62) -> 0 | Q62: 59.741114
E63: L'Oreal Travel Retail | F63: External | G63: OAP | H63: CL0170 L'Oréal Paris (L'OAP) | I63: Shopfitting | J63: =+K63+L63 -> 8.8069593 | K63: =SUM(N63:Y63) -> 8.8069593 | L63: =SUM(AA63:AL63) -> 0 | Q63: 8.8069593
E64: L'Oreal Travel Retail | F64: External | G64: RALPH LAUREN | H64: CL0405 Ralph Lauren | I64: Shopfitting | J64: =SUM(Y64:AJ64) -> 0 | K64: =SUM(Z64:AK64) -> 0 | L64: =SUM(AA64:AL64) -> 0 | O64: -6.68e-08
E65: L'Oreal Travel Retail | F65: External | G65: YSL | H65: CL0310 YSL | I65: Shopfitting | J65: =+K65+L65 -> 27.743928 | K65: =SUM(N65:Y65) -> 27.743928 | L65: =SUM(AA65:AL65) -> 0 | Q65: 27.743928
E66: Puig India | F66: External | G66: CH, RB & JPG | H66: CL0840 Puig - other brands | I66: Shopfitting | J66: =+K66+L66 -> 14.85092 | K66: =SUM(N66:Y66) -> 14.85092 | L66: =SUM(AA66:AL66) -> 0 | P66: 14.85092
E67: Rare Beauty LLC | F67: External | G67: Rare Beauty | H67: CL0765 Rare Beauty | I67: Prestige Cosmetic | J67: =+K67+L67 -> 57.109955 | K67: =SUM(N67:Y67) -> 57.109955 | L67: =SUM(AA67:AL67) -> 0 | O67: 57.109955
E68: Reliance Luxe Beauty Limited | F68: External | G68: Rare Beauty | H68: CL0765 Rare Beauty | I68: Prestige Cosmetic | J68: =+K68+L68 -> 42.985819 | K68: =SUM(N68:Y68) -> 42.985819 | L68: =SUM(AA68:AL68) -> 0 | O68: 42.985819
E69: Shoppers Stop Ltd | F69: External | G69: Clinique | H69: CL0075 Clinique | I69: Prestige Cosmetic | J69: =+K69+L69 -> 3.321 | K69: =SUM(N69:Y69) -> 3.321 | L69: =SUM(AA69:AL69) -> 0 | O69: 3.321
E70: Shoppers Stop Ltd | F70: External | G70: ELCA Brand | H70: CL0680 Estée Lauder - other brands | I70: Prestige Cosmetic | J70: =+K70+L70 -> 0 | K70: =SUM(N70:Y70) -> 0 | L70: =SUM(AA70:AL70) -> 0
E71: Shoppers Stop Ltd | F71: External | G71: Tom Ford | H71: CL0570 Tom Ford | I71: Shopfitting | J71: =+K71+L71 -> 22.859271 | K71: =SUM(N71:Y71) -> 22.859271 | L71: =SUM(AA71:AL71) -> 0 | O71: 22.859271
J72: =+K72+L72 -> 0 | K72: =SUM(N72:Y72) -> 0 | L72: =SUM(AA72:AL72) -> 0
E74: Deferred revenue balance as on | F74: 46023 | G74: 218 | H74: K Euro
E75: Add: Deferred revenue addition during Jan-26 | G75: 151 | H75: K Euro
E76: Less: Deferred revenue reversed during Jan-26 | G76: 138 | H76: K Euro
E77: Deferred revenue balance as on | F77: 46053 | G77: =G74+G75-G76 -> 231 | H77: K Euro
E79: Brand | H79: Amt. in K Euro
E80: Benefit | H80: 9
E81: Fenty Beauty | H81: 2
E82: Grand Total | H82: =SUM(H80:H81) -> 11
E85: Actual Orderbook of last week | H85: ='W6'!J19 -> 1052.5999
E86: New Orders in Current Week | H86: =H82 -> 11
E87: Sales booked in current week | H87: =J12-'W6'!J12 -> 13.32
E88: Standard Orderbook should be in Current Week | H88: =H85+H86-H87 -> 1050.2799
E89: Actual Orderbook in Current Week | H89: =K19 -> 1009.6434
E90: Difference | H90: =H88-H89 -> 40.6365 | I90: Check whether new orders are reported correctly or invoiced order have been removed from the sales dashboard.
I91: deferred revenue

Sheet W8
E2: ENTITY NAME : | G2: =+parameters!D2 -> Diam India | I2: ORDER BOOK SYNTHESIS in K€
E4: WEEK : | G4: W8 | I4: Cells to be filled in
E6: MONTH : | G6: =+VLOOKUP(G4, parameters!G:H, 2, 0) -> February
E8: TURNOVER | F8: =parameters!D4 -> k€ | H8: YTD Turnover | J8: =+G6&" Turnover" -> February Turnover | L8: Last estim. for the month: | O8: Forecast 2026
H9: =+"from January 1 until end of "&G4 -> from January 1 until end of W8 | J9: =+"from "&G6&" 1 until end of "&G4 -> from February 1 until end of W8 | L9: =+G6 -> February | O9: =+G4 -> W8 | P9: =+VLOOKUP(G4, parameters!$G$9:$I$61,3,0) -> W7 | Q9: Var
E10: EXTERNAL SALES INVOICED (=outside group) | H10: =600+J10 -> 749.23735 | J10: 149.23735 | L10: =J10+O17 -> 649.53025 | O10: =+H10+K17 -> 2008.7272 | P10: {=INDIRECT(ADDRESS(10,15,,,VLOOKUP($G$4,parameters!$G:$I,3,0)))} -> 1674.1901 | Q10: =O10-P10 -> 334.53705
E11: GROUP SALES INVOICED | H11: =13+J11 -> 20.01 | J11: 7.01 | L11: =J11+O18 -> 7.01 | O11: =+H11+K18 -> 26.800145 | P11: {=INDIRECT(ADDRESS(11,15,,,VLOOKUP($G$4,parameters!$G:$I,3,0)))} -> 31.453248 | Q11: =O11-P11 -> -4.6531026 | S11: Definition orders : you consider the orders which are sure even if the order customers paper order is not yet received
E12: TOTAL | H12: =SUM(H10:H11) -> 769.24735 | J12: =SUM(J10:J11) -> 156.24735 | L12: =SUM(L10:L11) -> 656.54025 | O12: =SUM(O10:O11) -> 2035.5273 | P12: =SUM(P10:P11) -> 1705.6434 | Q12: =O12-P12 -> 329.88395 | S12: The quantity, value, and delivery date can be changed before final delivery
E16: ORDERBOOK | F16: =+F8 -> k€ | J16: TOTAL ORDERBOOK | K16: Total amount 2026 | L16: Total amount 2027 | N16: 46023 | O16: 46054 | P16: 46082 | Q16: 46113 | R16: 46143 | S16: 46174 | T16: 46204 | U16: 46235 | V16: 46266 | W16: 46296 | X16: 46327 | Y16: 46357 | AA16: 46388 | AB16: 46419 | AC16: 46447 | AD16: 46478 | AE16: 46508 | AF16: 46539 | AG16: 46569 | AH16: 46600 | AI16: 46631 | AJ16: 46661 | AK16: 46692 | AL16: 46722
E17: External | J17: =+SUMIF($F$24:$F$251,"External",$J$24:$J$251) -> 1259.4898 | K17: =+SUMIF($F$24:$F$251,"External",$K$24:$K$251) -> 1259.4898 | L17: =+SUMIF($F$24:$F$251,"External",$L$24:$L$251) -> 0 | N17: =+SUMIF($F$24:$F$251,"External",N$24:N$251) -> 0 | O17: =+SUMIF($F$24:$F$251,"External",O$24:O$251) -> 500.29291 | P17: =+SUMIF($F$24:$F$251,"External",P$24:P$251) -> 263.41888 | Q17: =+SUMIF($F$24:$F$251,"External",Q$24:Q$251) -> 430.76252 | R17: =+SUMIF($F$24:$F$251,"External",R$24:R$251) -> 25.709063 | S17: =+SUMIF($F$24:$F$251,"External",S$24:S$251) -> 27.317922 | T17: =+SUMIF($F$24:$F$251,"External",T$24:T$251) -> 11.988554 | U17: =+SUMIF($F$24:$F$251,"External",U$24:U$251) -> 0 | ... Y17: =+SUMIF($F$24:$F$251,"External",Y$24:Y$251) -> 0 | AA17: =+SUMIF($F$24:$F$251,"External",AA$24:AA$251) -> 0 | AB17: =+SUMIF($F$24:$F$251,"External",AB$24:AB$251) -> 0 | AC17: =+SUMIF($F$24:$F$251,"External",AC$24:AC$251) -> 0 | AD17: =+SUMIF($F$24:$F$251,"External",AD$24:AD$251) -> 0 | AE17: =+SUMIF($F$24:$F$251,"External",AE$24:AE$251) -> 0 | AF17: =+SUMIF($F$24:$F$251,"External",AF$24:AF$251) -> 0 | AG17: =+SUMIF($F$24:$F$251,"External",AG$24:AG$251) -> 0 | AH17: =+SUMIF($F$24:$F$251,"External",AH$24:AH$251) -> 0 | ... AL17: =+SUMIF($F$24:$F$251,"External",AL$24:AL$251) -> 0
E18: Group | J18: =+SUMIF($F$24:$F$251,"Group",$J$24:$J$251) -> 6.7901454 | K18: =+SUMIF($F$24:$F$251,"Group",$K$24:$K$251) -> 6.7901454 | L18: =SUMIF($F$24:$F$251,"Group",$L$24:$L$251) -> 0 | N18: =+SUMIF($F$24:$F$251,"Group",N$24:N$251) -> 0 | O18: =+SUMIF($F$24:$F$251,"Group",O$24:O$251) -> 0 | P18: =+SUMIF($F$24:$F$251,"Group",P$24:P$251) -> 0 | Q18: =+SUMIF($F$24:$F$251,"Group",Q$24:Q$251) -> 6.7901454 | R18: =+SUMIF($F$24:$F$251,"Group",R$24:R$251) -> 0 | S18: =+SUMIF($F$24:$F$251,"Group",S$24:S$251) -> 0 | T18: =+SUMIF($F$24:$F$251,"Group",T$24:T$251) -> 0 | U18: =+SUMIF($F$24:$F$251,"Group",U$24:U$251) -> 0 | ... Y18: =+SUMIF($F$24:$F$251,"Group",Y$24:Y$251) -> 0 | AA18: =+SUMIF($F$24:$F$251,"Group",AA$24:AA$251) -> 0 | AB18: =+SUMIF($F$24:$F$251,"Group",AB$24:AB$251) -> 0 | AC18: =+SUMIF($F$24:$F$251,"Group",AC$24:AC$251) -> 0 | AD18: =+SUMIF($F$24:$F$251,"Group",AD$24:AD$251) -> 0 | AE18: =+SUMIF($F$24:$F$251,"Group",AE$24:AE$251) -> 0 | AF18: =+SUMIF($F$24:$F$251,"Group",AF$24:AF$251) -> 0 | AG18: =+SUMIF($F$24:$F$251,"Group",AG$24:AG$251) -> 0 | AH18: =+SUMIF($F$24:$F$251,"Group",AH$24:AH$251) -> 0 | ... AL18: =+SUMIF($F$24:$F$251,"Group",AL$24:AL$251) -> 0
E19: TOTAL | J19: =SUM(J17:J18) -> 1266.28 | K19: =SUM(K17:K18) -> 1266.28 | L19: =SUM(L17:L18) -> 0 | N19: =SUM(N17:N18) -> 0 | O19: =SUM(O17:O18) -> 500.29291 | P19: =SUM(P17:P18) -> 263.41888 | Q19: =SUM(Q17:Q18) -> 437.55267 | R19: =SUM(R17:R18) -> 25.709063 | S19: =SUM(S17:S18) -> 27.317922 | T19: =SUM(T17:T18) -> 11.988554 | U19: =SUM(U17:U18) -> 0 | ... Y19: =SUM(Y17:Y18) -> 0 | AA19: =SUM(AA17:AA18) -> 0 | AB19: =SUM(AB17:AB18) -> 0 | AC19: =SUM(AC17:AC18) -> 0 | AD19: =SUM(AD17:AD18) -> 0 | AE19: =SUM(AE17:AE18) -> 0 | AF19: =SUM(AF17:AF18) -> 0 | AG19: =SUM(AG17:AG18) -> 0 | AH19: =SUM(AH17:AH18) -> 0 | ... AL19: =SUM(AL17:AL18) -> 0
I21: check | J21: =IF(SUM(J24:J251)=J19, "OK", "Please correct: the sum of orders below is not equal to the total calculated above. Make sure to pick External or Group for each order and don't change the formulas in columns K and L") -> OK | N21: 2026 | AA21: 2027
E23: Customer Name | F23: External or Group | G23: Brand | H23: Outgroup | I23: Segment | J23: TOTAL ORDERBOOK | K23: Total amount 2026 | L23: Total amount 2026 | N23: 46023 | O23: 46054 | P23: 46082 | Q23: 46113 | R23: 46143 | S23: 46174 | T23: 46204 | U23: 46235 | V23: 46266 | W23: 46296 | X23: 46327 | Y23: 46357 | AA23: 46388 | AB23: 46419 | AC23: 46447 | AD23: 46478 | AE23: 46508 | AF23: 46539 | AG23: 46569 | AH23: 46600 | AI23: 46631 | AJ23: 46661 | AK23: 46692 | AL23: 46722
D24: X | E24: BACCAROSE PERFUMES AND BEAUTY PRODUCTS PVT LTD | F24: External | G24: Gucci | H24: CL0920 Coty - other brands | I24: Shopfitting | J24: =+K24+L24 -> 1.52838 | K24: =SUM(N24:Y24) -> 1.52838 | L24: =SUM(AA24:AL24) -> 0 | O24: 1.52838
E25: BACCAROSE PERFUMES AND BEAUTY PRODUCTS PVT LTD | F25: External | G25: Laura Mercier | H25: CL0540 Laura Mercier | I25: Prestige Cosmetic | J25: =+K25+L25 -> 7.2617511 | K25: =SUM(N25:Y25) -> 7.2617511 | L25: =SUM(AA25:AL25) -> 0 | Q25: 7.2617511
E26: BACCAROSE PERFUMES AND BEAUTY PRODUCTS PVT LTD | F26: External | G26: Shiseido | H26: CL0285 Shiseido | I26: Prestige Cosmetic | J26: =+K26+L26 -> 19.0875 | K26: =SUM(N26:Y26) -> 19.0875 | L26: =SUM(AA26:AL26) -> 0 | P26: 19.0875
E27: Beauty Impex Pvt. Ltd | F27: External | G27: Guerlain | H27: CL0130 Guerlain | I27: Prestige Cosmetic | J27: =+K27+L27 -> 10.208249 | K27: =SUM(N27:Y27) -> 10.208249 | L27: =SUM(AA27:AL27) -> 0 | O27: 10.208249
E28: Best In Brands | F28: External | G28: Shiseido | H28: CL0285 Shiseido | I28: Prestige Cosmetic | J28: =+K28+L28 -> 8.0682141 | K28: =SUM(N28:Y28) -> 8.0682141 | L28: =SUM(AA28:AL28) -> 0 | P28: 8.0682141
E29: CHANEL INDIA | F29: External | G29: Chanel | H29: CL0065 Chanel | I29: Shopfitting | J29: =+K29+L29 -> 5.8856955 | K29: =SUM(N29:Y29) -> 5.8856955 | L29: =SUM(AA29:AL29) -> 0 | O29: 5.8856955
E30: Connectiv FZCO | F30: External | G30: L'Oreal TR | H30: CL0180 L'Oréal Divers | I30: Shopfitting | J30: =+K30+L30 -> 0.8584046 | K30: =SUM(N30:Y30) -> 0.8584046 | L30: =SUM(AA30:AL30) -> 0 | P30: 0.8584046
E31: DDS | F31: Group | G31: Coty | H31: CL0920 Coty - other brands | I31: Shopfitting | J31: =+K31+L31 -> 6.7901454 | K31: =SUM(N31:Y31) -> 6.7901454 | L31: =SUM(AA31:AL31) -> 0 | Q31: 6.7901454
E32: DIAM Turkey | F32: Group | G32: Fenty Beauty | H32: CL0550 Kendo - Fenty | I32: Prestige Cosmetic | J32: =+K32+L32 -> 0 | K32: =SUM(N32:Y32) -> 0 | L32: =SUM(AA32:AL32) -> 0 | O32: 0
E33: ELCA Cosmetics Pvt. Ltd. | F33: External | G33: Clinique | H33: CL0075 Clinique | I33: Prestige Cosmetic | J33: =+K33+L33 -> 71.267651 | K33: =SUM(N33:Y33) -> 71.267651 | L33: =SUM(AA33:AL33) -> 0 | O33: 45.304466 | P33: 23.627752 | T33: 2.3354327
E34: ELCA Cosmetics Pvt. Ltd. | F34: External | G34: Dr Jart+ | H34: CL0680 Estée Lauder - other brands | I34: Prestige Cosmetic | J34: =+K34+L34 -> 3.1881163 | K34: =SUM(N34:Y34) -> 3.1881163 | L34: =SUM(AA34:AL34) -> 0 | P34: 3.1881163
E35: ELCA Cosmetics Pvt. Ltd. | F35: External | G35: Estee Lauder | H35: CL0110 Estée Lauder | I35: Prestige Cosmetic | J35: =+K35+L35 -> 75.940163 | K35: =SUM(N35:Y35) -> 75.940163 | L35: =SUM(AA35:AL35) -> 0 | O35: 47.805547 | P35: 25.799184 | T35: 2.3354327
E36: ELCA Cosmetics Pvt. Ltd. | F36: External | G36: Mac | H36: CL0395 MAC | I36: Prestige Cosmetic | J36: =+K36+L36 -> 30.598912 | K36: =SUM(N36:Y36) -> 30.598912 | L36: =SUM(AA36:AL36) -> 0 | O36: 8.7518718 | P36: 10.47631 | R36: 9.035297 | T36: 2.3354327
E37: ELCA Cosmetics Pvt. Ltd. | F37: External | G37: Smashbox | H37: CL0525 Smashbox | I37: Prestige Cosmetic | J37: =+K37+L37 -> 3.2735576 | K37: =SUM(N37:Y37) -> 3.2735576 | L37: =SUM(AA37:AL37) -> 0 | O37: 0 | P37: 1.6367788 | T37: 1.6367788
E38: ELCA Cosmetics Pvt. Ltd. | F38: External | G38: The Ordinary | H38: CL0680 Estée Lauder - other brands | I38: Prestige Cosmetic | J38: =+K38+L38 -> 18.954026 | K38: =SUM(N38:Y38) -> 18.954026 | L38: =SUM(AA38:AL38) -> 0 | O38: 3.6118382 | P38: 13.835168 | T38: 1.50702
E39: ELCA Cosmetics Pvt. Ltd. | F39: External | G39: Tom Ford | H39: CL0570 Tom Ford | I39: Prestige Cosmetic | J39: =+K39+L39 -> 27.066908 | K39: =SUM(N39:Y39) -> 27.066908 | L39: =SUM(AA39:AL39) -> 0 | P39: 26.28843 | T39: 0.7784776
E40: ELCA Cosmetics Pvt. Ltd. | F40: External | G40: Too Faced | H40: CL0575 Too Faced | I40: Prestige Cosmetic | J40: =+K40+L40 -> 40.98012 | K40: =SUM(N40:Y40) -> 40.98012 | L40: =SUM(AA40:AL40) -> 0 | P40: 1.05998 | Q40: 11.542238 | S40: 27.317922 | T40: 1.05998
E41: Estee Lauder AG Lachen | F41: External | G41: Jo Malone | H41: CL0535 Joe Malone | I41: Prestige Cosmetic | J41: =+K41+L41 -> 0.0099548 | K41: =SUM(N41:Y41) -> 0.0099548 | L41: =SUM(AA41:AL41) -> 0 | O41: 0.0099548
E42: Estee Lauder Middle East FZE | F42: External | G42: Too Faced | H42: CL0575 Too Faced | I42: Prestige Cosmetic | J42: =+K42+L42 -> 155.09714 | K42: =SUM(N42:Y42) -> 155.09714 | L42: =SUM(AA42:AL42) -> 0 | Q42: 155.09714
E43: Estee Lauder Saudi Limited | F43: External | G43: Clinique | H43: CL0075 Clinique | I43: Prestige Cosmetic | J43: =+K43+L43 -> 3.5708258 | K43: =SUM(N43:Y43) -> 3.5708258 | L43: =SUM(AA43:AL43) -> 0 | P43: 3.5708258
E44: Forma Brands, LLC f/k/a FB Acquisition LLC | F44: External | G44: Forma | H44: CL0735 Morphe | I44: Prestige Cosmetic | J44: =+K44+L44 -> 30.286168 | K44: =SUM(N44:Y44) -> 30.286168 | L44: =SUM(AA44:AL44) -> 0 | O44: 0 | Q44: 30.286168
E45: Global Shoppers Stop Beauty Brands Ltd | F45: External | G45: Nars | H45: CL0226 Nars | I45: Prestige Cosmetic | J45: =+K45+L45 -> 117.23664 | K45: =SUM(N45:Y45) -> 117.23664 | L45: =SUM(AA45:AL45) -> 0 | O45: 5.2617689 | P45: 63.35588 | Q45: 48.61899
E46: Global Shoppers Stop Beauty Brands Ltd | F46: External | G46: Prada | H46: CL0180 L'Oréal Divers | I46: Shopfitting | J46: =+K46+L46 -> 16.673766 | K46: =SUM(N46:Y46) -> 16.673766 | L46: =SUM(AA46:AL46) -> 0 | O46: 0 | R46: 16.673766
E47: Indosing Distribution | F47: External | G47: Benefit | H47: CL0315 Benefit | I47: Prestige Cosmetic | J47: =+K47+L47 -> 23.332406 | K47: =SUM(N47:Y47) -> 23.332406 | L47: =SUM(AA47:AL47) -> 0 | O47: 3.6e-06 | P47: 23.332403
E48: L Beauty Pte | F48: External | G48: Benefit | H48: CL0315 Benefit | I48: Prestige Cosmetic | J48: =+K48+L48 -> 47.250297 | K48: =SUM(N48:Y48) -> 47.250297 | L48: =SUM(AA48:AL48) -> 0 | P48: 20.282065 | Q48: 26.968231
E49: L'Oreal India | F49: External | G49: Lancome | H49: CL0155 Lancôme | I49: Prestige Cosmetic | J49: =+K49+L49 -> 16.75243 | K49: =SUM(N49:Y49) -> 16.75243 | L49: =SUM(AA49:AL49) -> 0 | O49: 9.6930685 | Q49: 7.059362
E50: L'Oreal India | F50: External | G50: Lancome | H50: CL0155 Lancôme | I50: Shopfitting | J50: =+K50+L50 -> 10.820262 | K50: =SUM(N50:Y50) -> 10.820262 | L50: =SUM(AA50:AL50) -> 0 | O50: 10.102618 | P50: 0.717644
E51: L'Oreal India | F51: External | G51: YSL | H51: CL0310 YSL | I51: Shopfitting | J51: =+K51+L51 -> 1.1928188 | K51: =SUM(N51:Y51) -> 1.1928188 | L51: =SUM(AA51:AL51) -> 0 | P51: 1.1928188
E52: L'Oreal Travel Retail | F52: External | G52: Armani | H52: CL0345 Armani | I52: Shopfitting | J52: =+K52+L52 -> 31.134083 | K52: =SUM(N52:Y52) -> 31.134083 | L52: =SUM(AA52:AL52) -> 0 | Q52: 31.134083
E53: L'Oreal Travel Retail | F53: External | G53: ARMANI PRIVE | H53: CL0345 Armani | I53: Shopfitting | J53: =+K53+L53 -> 1.05772e-05 | K53: =SUM(N53:Y53) -> 1.05772e-05 | L53: =SUM(AA53:AL53) -> 0 | O53: 1.05772e-05
E54: L'Oreal Travel Retail | F54: External | G54: Lancome | H54: CL0155 Lancôme | I54: Shopfitting | J54: =+K54+L54 -> 16.502558 | K54: =SUM(N54:Y54) -> 16.502558 | L54: =SUM(AA54:AL54) -> 0 | Q54: 16.502558
E55: L'Oreal Travel Retail | F55: External | G55: Loreal Paris | H55: CL0170 L'Oréal Paris (L'OAP) | I55: Shopfitting | J55: =+K55+L55 -> 8.9014259 | K55: =SUM(N55:Y55) -> 8.9014259 | L55: =SUM(AA55:AL55) -> 0 | O55: 8.9014259
E56: L'Oreal Travel Retail | F56: External | G56: Multi | H56: CL0180 L'Oréal Divers | I56: Shopfitting | J56: =+K56+L56 -> 59.741114 | K56: =SUM(N56:Y56) -> 59.741114 | L56: =SUM(AA56:AL56) -> 0 | Q56: 59.741114
E57: L'Oreal Travel Retail | F57: External | G57: OAP | H57: CL0170 L'Oréal Paris (L'OAP) | I57: Shopfitting | J57: =+K57+L57 -> 8.8069593 | K57: =SUM(N57:Y57) -> 8.8069593 | L57: =SUM(AA57:AL57) -> 0 | Q57: 8.8069593
E58: L'Oreal Travel Retail | F58: External | G58: RALPH LAUREN | H58: CL0405 Ralph Lauren | I58: Shopfitting | J58: =+K58+L58 -> 0 | K58: =SUM(N58:Y58) -> 0 | L58: =SUM(AA58:AL58) -> 0 | O58: 0
E59: L'Oreal Travel Retail | F59: External | G59: YSL | H59: CL0310 YSL | I59: Shopfitting | J59: =+K59+L59 -> 30.785181 | K59: =SUM(N59:Y59) -> 30.785181 | L59: =SUM(AA59:AL59) -> 0 | O59: 3.0412531 | Q59: 27.743928
E60: Puig India | F60: External | G60: CH, RB & JPG | H60: CL0840 Puig - other brands | I60: Shopfitting | J60: =+K60+L60 -> 0 | K60: =SUM(N60:Y60) -> 0 | L60: =SUM(AA60:AL60) -> 0 | P60: 0
E61: Rare Beauty LLC | F61: External | G61: Rare Beauty | H61: CL0765 Rare Beauty | I61: Prestige Cosmetic | J61: =+K61+L61 -> 295.00667 | K61: =SUM(N61:Y61) -> 295.00667 | L61: =SUM(AA61:AL61) -> 0 | O61: 294.48222 | P61: 0.52445086
E62: Reliance Luxe Beauty Limited | F62: External | G62: Rare Beauty | H62: CL0765 Rare Beauty | I62: Prestige Cosmetic | J62: =+K62+L62 -> 36.041219 | K62: =SUM(N62:Y62) -> 36.041219 | L62: =SUM(AA62:AL62) -> 0 | O62: 36.041219
E63: Shoppers Stop Ltd | F63: External | G63: Clinique | H63: CL0075 Clinique | I63: Prestige Cosmetic | J63: =+K63+L63 -> 3.321 | K63: =SUM(N63:Y63) -> 3.321 | L63: =SUM(AA63:AL63) -> 0 | P63: 3.321
E64: Shoppers Stop Ltd | F64: External | G64: Tom Ford | H64: CL0570 Tom Ford | I64: Shopfitting | J64: =+K64+L64 -> 22.859271 | K64: =SUM(N64:Y64) -> 22.859271 | L64: =SUM(AA64:AL64) -> 0 | O64: 9.6633208 | P64: 13.19595
J65: =+K65+L65 -> 0 | K65: =SUM(N65:Y65) -> 0 | L65: =SUM(AA65:AL65) -> 0
J66: =+K66+L66 -> 0 | K66: =SUM(N66:Y66) -> 0 | L66: =SUM(AA66:AL66) -> 0
J67: =+K67+L67 -> 0 | K67: =SUM(N67:Y67) -> 0 | L67: =SUM(AA67:AL67) -> 0
J68: =+K68+L68 -> 0 | K68: =SUM(N68:Y68) -> 0 | L68: =SUM(AA68:AL68) -> 0
J69: =+K69+L69 -> 0 | K69: =SUM(N69:Y69) -> 0 | L69: =SUM(AA69:AL69) -> 0
J70: =+K70+L70 -> 0 | K70: =SUM(N70:Y70) -> 0 | L70: =SUM(AA70:AL70) -> 0
J71: =+K71+L71 -> 0 | K71: =SUM(N71:Y71) -> 0 | L71: =SUM(AA71:AL71) -> 0
J72: =+K72+L72 -> 0 | K72: =SUM(N72:Y72) -> 0 | L72: =SUM(AA72:AL72) -> 0
J73: =+K73+L73 -> 0 | K73: =SUM(N73:Y73) -> 0 | L73: =SUM(AA73:AL73) -> 0
J74: =+K74+L74 -> 0 | K74: =SUM(N74:Y74) -> 0 | L74: =SUM(AA74:AL74) -> 0
J75: =+K75+L75 -> 0 | K75: =SUM(N75:Y75) -> 0 | L75: =SUM(AA75:AL75) -> 0
J76: =+K76+L76 -> 0 | K76: =SUM(N76:Y76) -> 0 | L76: =SUM(AA76:AL76) -> 0
... J252: =+K252+L252 -> 0 | K252: =SUM(N252:Y252) -> 0 | L252: =SUM(AA252:AL252) -> 0
E255: Deferred revenue balance as on | F255: 46023 | G255: 218 | H255: K Euro
E256: Add: Deferred revenue addition during Jan-26 | G256: 151 | H256: K Euro
E257: Less: Deferred revenue reversed during Jan-26 | G257: 138 | H257: K Euro
E258: Deferred revenue balance as on | F258: 46053 | G258: =G255+G256-G257 -> 231 | H258: K Euro
E260: Brand | H260: Amt. in K Euro
E261: Clinique | H261: 3.3486144
E262: Dr Jart+ | H262: 3.5988095
E263: Estee Lauder | H263: 5.2863704
E264: Fenty Beauty | H264: 9.012076
E265: Lancome | H265: 0.717644
E266: Mac | H266: 24.753346
E267: Nars | H267: 0.51047
E268: Rare Beauty | H268: 237.89671
E269: The Ordinary | H269: 10.896449
E270: Too Faced | H270: 11.542238
E271: YSL | H271: 3.0412531
E273: Grand Total | H273: =SUM(H261:H272) -> 310.60398
E276: Actual Orderbook of last week | H276: ='W7'!J19 -> 1009.6434
E277: New Orders in Current Week | H277: =H273 -> 310.60398
E278: Sales booked in current week | H278: =J12-'W7'!J12 -> 73.247346
E279: Standard Orderbook should be in Current Week | H279: =H276+H277-H278 -> 1247
E280: Actual Orderbook in Current Week | H280: =J19 -> 1266.28
E281: Difference | H281: =H279-H280 -> -19.279968 | I281: Check whether new orders are reported correctly or invoiced order have been removed from the sales dashboard.
I282: deferred revenue

Sheet W9
E2: ENTITY NAME : | G2: =+parameters!D2 -> Diam India | I2: ORDER BOOK SYNTHESIS in K€
E4: WEEK : | G4: W9 | I4: Cells to be filled in
E6: MONTH : | G6: =+VLOOKUP(G4, parameters!G:H, 2, 0) -> February
E8: TURNOVER | F8: =parameters!D4 -> k€ | H8: YTD Turnover | J8: =+G6&" Turnover" -> February Turnover | L8: Last estim. for the month: | O8: Forecast 2026
H9: =+"from January 1 until end of "&G4 -> from January 1 until end of W9 | J9: =+"from "&G6&" 1 until end of "&G4 -> from February 1 until end of W9 | L9: =+G6 -> February | O9: =+G4 -> W9 | P9: =+VLOOKUP(G4, parameters!$G$9:$I$61,3,0) -> W8 | Q9: Var
E10: EXTERNAL SALES INVOICED (=outside group) | H10: =600+J10 -> 1165 | J10: 565 | L10: =J10+O17 -> 565 | O10: =+H10+K17 -> 3461.1422 | P10: {=INDIRECT(ADDRESS(10,15,,,VLOOKUP($G$4,parameters!$G:$I,3,0)))} -> 2008.7272 | Q10: =O10-P10 -> 1452.415
E11: GROUP SALES INVOICED | H11: =13+J11 -> 21 | J11: 8 | L11: =J11+O18 -> 8 | O11: =+H11+K18 -> 27.79015 | P11: {=INDIRECT(ADDRESS(11,15,,,VLOOKUP($G$4,parameters!$G:$I,3,0)))} -> 26.800145 | Q11: =O11-P11 -> 0.99000457 | S11: Definition orders : you consider the orders which are sure even if the order customers paper order is not yet received
E12: TOTAL | H12: =SUM(H10:H11) -> 1186 | J12: =SUM(J10:J11) -> 573 | L12: =SUM(L10:L11) -> 573 | O12: =SUM(O10:O11) -> 3488.9324 | P12: =SUM(P10:P11) -> 2035.5273 | Q12: =O12-P12 -> 1453.4051 | S12: The quantity, value, and delivery date can be changed before final delivery
E16: ORDERBOOK | F16: =+F8 -> k€ | J16: TOTAL ORDERBOOK | K16: Total amount 2026 | L16: Total amount 2027 | N16: 46023 | O16: 46054 | P16: 46082 | Q16: 46113 | R16: 46143 | S16: 46174 | T16: 46204 | U16: 46235 | V16: 46266 | W16: 46296 | X16: 46327 | Y16: 46357 | AA16: 46388 | AB16: 46419 | AC16: 46447 | AD16: 46478 | AE16: 46508 | AF16: 46539 | AG16: 46569 | AH16: 46600 | AI16: 46631 | AJ16: 46661 | AK16: 46692 | AL16: 46722
E17: External | J17: =+SUMIF($F$24:$F$64,"External",$J$24:$J$64) -> 2296.1422 | K17: =+SUMIF($F$24:$F$64,"External",$K$24:$K$64) -> 2296.1422 | L17: =+SUMIF($F$24:$F$64,"External",$L$24:$L$64) -> 0 | N17: =+SUMIF($F$24:$F$64,"External",N$24:N$64) -> 0 | O17: =+SUMIF($F$24:$F$64,"External",O$24:O$64) -> 0 | P17: =+SUMIF($F$24:$F$64,"External",P$24:P$64) -> 509.61635 | Q17: =+SUMIF($F$24:$F$64,"External",Q$24:Q$64) -> 597.18207 | R17: =+SUMIF($F$24:$F$64,"External",R$24:R$64) -> 564.95642 | S17: =+SUMIF($F$24:$F$64,"External",S$24:S$64) -> 469.5734 | T17: =+SUMIF($F$24:$F$64,"External",T$24:T$64) -> 154.814 | U17: =+SUMIF($F$24:$F$64,"External",U$24:U$64) -> 0 | ... Y17: =+SUMIF($F$24:$F$64,"External",Y$24:Y$64) -> 0 | AA17: =+SUMIF($F$24:$F$64,"External",AA$24:AA$64) -> 0 | AB17: =+SUMIF($F$24:$F$64,"External",AB$24:AB$64) -> 0 | AC17: =+SUMIF($F$24:$F$64,"External",AC$24:AC$64) -> 0 | AD17: =+SUMIF($F$24:$F$64,"External",AD$24:AD$64) -> 0 | AE17: =+SUMIF($F$24:$F$64,"External",AE$24:AE$64) -> 0 | AF17: =+SUMIF($F$24:$F$64,"External",AF$24:AF$64) -> 0 | AG17: =+SUMIF($F$24:$F$64,"External",AG$24:AG$64) -> 0 | AH17: =+SUMIF($F$24:$F$64,"External",AH$24:AH$64) -> 0 | ... AL17: =+SUMIF($F$24:$F$64,"External",AL$24:AL$64) -> 0
E18: Group | J18: =+SUMIF($F$24:$F$64,"Group",$J$24:$J$64) -> 6.79015 | K18: =+SUMIF($F$24:$F$64,"Group",$K$24:$K$64) -> 6.79015 | L18: =SUMIF($F$24:$F$64,"Group",$L$24:$L$64) -> 0 | N18: =+SUMIF($F$24:$F$64,"Group",N$24:N$64) -> 0 | O18: =+SUMIF($F$24:$F$64,"Group",O$24:O$64) -> 0 | P18: =+SUMIF($F$24:$F$64,"Group",P$24:P$64) -> 0 | Q18: =+SUMIF($F$24:$F$64,"Group",Q$24:Q$64) -> 6.79015 | R18: =+SUMIF($F$24:$F$64,"Group",R$24:R$64) -> 0 | S18: =+SUMIF($F$24:$F$64,"Group",S$24:S$64) -> 0 | T18: =+SUMIF($F$24:$F$64,"Group",T$24:T$64) -> 0 | U18: =+SUMIF($F$24:$F$64,"Group",U$24:U$64) -> 0 | ... Y18: =+SUMIF($F$24:$F$64,"Group",Y$24:Y$64) -> 0 | AA18: =+SUMIF($F$24:$F$64,"Group",AA$24:AA$64) -> 0 | AB18: =+SUMIF($F$24:$F$64,"Group",AB$24:AB$64) -> 0 | AC18: =+SUMIF($F$24:$F$64,"Group",AC$24:AC$64) -> 0 | AD18: =+SUMIF($F$24:$F$64,"Group",AD$24:AD$64) -> 0 | AE18: =+SUMIF($F$24:$F$64,"Group",AE$24:AE$64) -> 0 | AF18: =+SUMIF($F$24:$F$64,"Group",AF$24:AF$64) -> 0 | AG18: =+SUMIF($F$24:$F$64,"Group",AG$24:AG$64) -> 0 | AH18: =+SUMIF($F$24:$F$64,"Group",AH$24:AH$64) -> 0 | ... AL18: =+SUMIF($F$24:$F$64,"Group",AL$24:AL$64) -> 0
E19: TOTAL | J19: =SUM(J17:J18) -> 2302.9324 | K19: =SUM(K17:K18) -> 2302.9324 | L19: =SUM(L17:L18) -> 0 | N19: =SUM(N17:N18) -> 0 | O19: =SUM(O17:O18) -> 0 | P19: =SUM(P17:P18) -> 509.61635 | Q19: =SUM(Q17:Q18) -> 603.97222 | R19: =SUM(R17:R18) -> 564.95642 | S19: =SUM(S17:S18) -> 469.5734 | T19: =SUM(T17:T18) -> 154.814 | U19: =SUM(U17:U18) -> 0 | ... Y19: =SUM(Y17:Y18) -> 0 | AA19: =SUM(AA17:AA18) -> 0 | AB19: =SUM(AB17:AB18) -> 0 | AC19: =SUM(AC17:AC18) -> 0 | AD19: =SUM(AD17:AD18) -> 0 | AE19: =SUM(AE17:AE18) -> 0 | AF19: =SUM(AF17:AF18) -> 0 | AG19: =SUM(AG17:AG18) -> 0 | AH19: =SUM(AH17:AH18) -> 0 | ... AL19: =SUM(AL17:AL18) -> 0
I21: check | J21: =IF(SUM(J24:J64)=J19, "OK", "Please correct: the sum of orders below is not equal to the total calculated above. Make sure to pick External or Group for each order and don't change the formulas in columns K and L") -> OK | N21: 2026 | AA21: 2027
E23: Customer Name | F23: External or Group | G23: Brand | H23: Outgroup | I23: Segment | J23: TOTAL ORDERBOOK | K23: Total amount 2026 | L23: Total amount 2026 | N23: 46023 | O23: 46054 | P23: 46082 | Q23: 46113 | R23: 46143 | S23: 46174 | T23: 46204 | U23: 46235 | V23: 46266 | W23: 46296 | X23: 46327 | Y23: 46357 | AA23: 46388 | AB23: 46419 | AC23: 46447 | AD23: 46478 | AE23: 46508 | AF23: 46539 | AG23: 46569 | AH23: 46600 | AI23: 46631 | AJ23: 46661 | AK23: 46692 | AL23: 46722
D24: X | E24: BACCAROSE PERFUMES AND BEAUTY PRODUCTS PVT LTD | F24: External | G24: Laura Mercier | H24: CL0540 Laura Mercier | I24: Prestige Cosmetic | J24: =+K24+L24 -> 7.26175 | K24: =SUM(N24:Y24) -> 7.26175 | L24: =SUM(AA24:AL24) -> 0 | Q24: 7.26175
E25: BACCAROSE PERFUMES AND BEAUTY PRODUCTS PVT LTD | F25: External | G25: Shiseido | H25: CL0285 Shiseido | I25: Prestige Cosmetic | J25: =+K25+L25 -> 19.0875 | K25: =SUM(N25:Y25) -> 19.0875 | L25: =SUM(AA25:AL25) -> 0 | P25: 19.0875
E26: Beauty Impex Pvt. Ltd | F26: External | G26: Guerlain | H26: CL0130 Guerlain | I26: Prestige Cosmetic | J26: =+K26+L26 -> 10.20824 | K26: =SUM(N26:Y26) -> 10.20824 | L26: =SUM(AA26:AL26) -> 0 | P26: 10.20824
E27: Best In Brands | F27: External | G27: Shiseido | H27: CL0285 Shiseido | I27: Prestige Cosmetic | J27: =+K27+L27 -> 8.06821 | K27: =SUM(N27:Y27) -> 8.06821 | L27: =SUM(AA27:AL27) -> 0 | P27: 8.06821
E28: CHANEL INDIA | F28: External | G28: Chanel | H28: CL0065 Chanel | I28: Shopfitting | J28: =+K28+L28 -> 314.44096 | K28: =SUM(N28:Y28) -> 314.44096 | L28: =SUM(AA28:AL28) -> 0 | Q28: 38.80527 | S28: 275.63569
E29: Clarins Pte Ltd | F29: External | G29: Clarins | H29: CL0070 Clarins | I29: Shopfitting | J29: =+K29+L29 -> 22.77611 | K29: =SUM(N29:Y29) -> 22.77611 | L29: =SUM(AA29:AL29) -> 0 | S29: 22.77611
E30: Coty | F30: External | G30: Coty | H30: CL0920 Coty - other brands | I30: Shopfitting | J30: =+K30+L30 -> 1.11239 | K30: =SUM(N30:Y30) -> 1.11239 | L30: =SUM(AA30:AL30) -> 0 | P30: 1.11239
E31: DDS | F31: Group | G31: Coty | H31: CL0920 Coty - other brands | I31: Shopfitting | J31: =+K31+L31 -> 6.79015 | K31: =SUM(N31:Y31) -> 6.79015 | L31: =SUM(AA31:AL31) -> 0 | Q31: 6.79015
E32: ELCA Cosmetics Pvt. Ltd. | F32: External | G32: Clinique | H32: CL0075 Clinique | I32: Prestige Cosmetic | J32: =+K32+L32 -> 115.94644 | K32: =SUM(N32:Y32) -> 115.94644 | L32: =SUM(AA32:AL32) -> 0 | P32: 41.77507 | R32: 34.13494 | S32: 28.47144 | T32: 11.56499
E33: ELCA Cosmetics Pvt. Ltd. | F33: External | G33: Dr Jart+ | H33: CL0680 Estée Lauder - other brands | I33: Prestige Cosmetic | J33: =+K33+L33 -> 15.030068 | K33: =SUM(N33:Y33) -> 15.030068 | L33: =SUM(AA33:AL33) -> 0 | P33: 9.8836981 | Q33: 2.95184 | R33: 2.19453
E34: ELCA Cosmetics Pvt. Ltd. | F34: External | G34: Estee Lauder | H34: CL0110 Estée Lauder | I34: Prestige Cosmetic | J34: =+K34+L34 -> 102.89747 | K34: =SUM(N34:Y34) -> 102.89747 | L34: =SUM(AA34:AL34) -> 0 | P34: 52.0637 | R34: 11.78504 | S34: 8.24186 | T34: 30.80687
E35: ELCA Cosmetics Pvt. Ltd. | F35: External | G35: Mac | H35: CL0395 MAC | I35: Prestige Cosmetic | J35: =+K35+L35 -> 150.13818 | K35: =SUM(N35:Y35) -> 150.13818 | L35: =SUM(AA35:AL35) -> 0 | P35: 24.96715 | R35: 9.0353 | S35: 86.94504 | T35: 29.19069
E36: ELCA Cosmetics Pvt. Ltd. | F36: External | G36: Smashbox | H36: CL0525 Smashbox | I36: Prestige Cosmetic | J36: =+K36+L36 -> 87.48969 | K36: =SUM(N36:Y36) -> 87.48969 | L36: =SUM(AA36:AL36) -> 0 | P36: 1.63678 | S36: 5.94694 | T36: 79.90597
E37: ELCA Cosmetics Pvt. Ltd. | F37: External | G37: The Ordinary | H37: CL0680 Estée Lauder - other brands | I37: Prestige Cosmetic | J37: =+K37+L37 -> 43.85666 | K37: =SUM(N37:Y37) -> 43.85666 | L37: =SUM(AA37:AL37) -> 0 | P37: 24.52809 | S37: 17.82155 | T37: 1.50702
E38: ELCA Cosmetics Pvt. Ltd. | F38: External | G38: Tom Ford | H38: CL0570 Tom Ford | I38: Prestige Cosmetic | J38: =+K38+L38 -> 36.82692 | K38: =SUM(N38:Y38) -> 36.82692 | L38: =SUM(AA38:AL38) -> 0 | P38: 26.28844 | Q38: 9.76 | T38: 0.77848
E39: ELCA Cosmetics Pvt. Ltd. | F39: External | G39: Too Faced | H39: CL0575 Too Faced | I39: Prestige Cosmetic | J39: =+K39+L39 -> 39.48451 | K39: =SUM(N39:Y39) -> 39.48451 | L39: =SUM(AA39:AL39) -> 0 | P39: 1.05998 | Q39: 0 | R39: 13.62978 | S39: 23.73477 | T39: 1.05998
E40: Estee Lauder Middle East FZE | F40: External | G40: Too Faced | H40: CL0575 Too Faced | I40: Prestige Cosmetic | J40: =+K40+L40 -> 155.09715 | K40: =SUM(N40:Y40) -> 155.09715 | L40: =SUM(AA40:AL40) -> 0 | Q40: 155.09715
E41: Estee Lauder Saudi Limited | F41: External | G41: Clinique | H41: CL0075 Clinique | I41: Prestige Cosmetic | J41: =+K41+L41 -> 3.57085 | K41: =SUM(N41:Y41) -> 3.57085 | L41: =SUM(AA41:AL41) -> 0 | P41: 3.57085
E42: Exclusive Lines | F42: External | G42: Lancome | H42: CL0155 Lancôme | I42: Shopfitting | J42: =+K42+L42 -> 18.97625 | K42: =SUM(N42:Y42) -> 18.97625 | L42: =SUM(AA42:AL42) -> 0 | P42: 18.97625
E43: Forma Brands, LLC f/k/a FB Acquisition LLC | F43: External | G43: Forma | H43: CL0735 Morphe | I43: Prestige Cosmetic | J43: =+K43+L43 -> 99.98034 | K43: =SUM(N43:Y43) -> 99.98034 | L43: =SUM(AA43:AL43) -> 0 | Q43: 99.98034
E44: Global Shoppers Stop Beauty Brands Ltd | F44: External | G44: Nars | H44: CL0226 Nars | I44: Prestige Cosmetic | J44: =+K44+L44 -> 136.18332 | K44: =SUM(N44:Y44) -> 136.18332 | L44: =SUM(AA44:AL44) -> 0 | P44: 87.56433 | Q44: 48.61899
E45: Global Shoppers Stop Beauty Brands Ltd | F45: External | G45: Prada | H45: CL0180 L'Oréal Divers | I45: Shopfitting | J45: =+K45+L45 -> 16.67377 | K45: =SUM(N45:Y45) -> 16.67377 | L45: =SUM(AA45:AL45) -> 0 | Q45: 16.67377
E46: Indosing Distribution | F46: External | G46: Benefit | H46: CL0315 Benefit | I46: Prestige Cosmetic | J46: =+K46+L46 -> 23.3324 | K46: =SUM(N46:Y46) -> 23.3324 | L46: =SUM(AA46:AL46) -> 0 | P46: 23.3324
E47: L Beauty Pte | F47: External | G47: Benefit | H47: CL0315 Benefit | I47: Prestige Cosmetic | J47: =+K47+L47 -> 47.25034 | K47: =SUM(N47:Y47) -> 47.25034 | L47: =SUM(AA47:AL47) -> 0 | P47: 20.28208 | Q47: 26.96826
E48: L'Oreal India | F48: External | G48: Lancome | H48: CL0155 Lancôme | I48: Prestige Cosmetic | J48: =+K48+L48 -> 18.588254 | K48: =SUM(N48:Y48) -> 18.588254 | L48: =SUM(AA48:AL48) -> 0 | P48: 11.602924 | Q48: 6.98533
E49: L'Oreal India | F49: External | G49: Lancome | H49: CL0155 Lancôme | I49: Shopfitting | J49: =+K49+L49 -> 10.82026 | K49: =SUM(N49:Y49) -> 10.82026 | L49: =SUM(AA49:AL49) -> 0 | P49: 10.82026
E50: L'Oreal India | F50: External | G50: YSL | H50: CL0310 YSL | I50: Shopfitting | J50: =+K50+L50 -> 20.55917 | K50: =SUM(N50:Y50) -> 20.55917 | L50: =SUM(AA50:AL50) -> 0 | P50: 20.55917
E51: L'Oreal Travel Retail | F51: External | G51: Armani | H51: CL0345 Armani | I51: Shopfitting | J51: =+K51+L51 -> 37.94317 | K51: =SUM(N51:Y51) -> 37.94317 | L51: =SUM(AA51:AL51) -> 0 | P51: 6.80909 | Q51: 31.13408
E52: L'Oreal Travel Retail | F52: External | G52: Lancome | H52: CL0155 Lancôme | I52: Shopfitting | J52: =+K52+L52 -> 16.50256 | K52: =SUM(N52:Y52) -> 16.50256 | L52: =SUM(AA52:AL52) -> 0 | Q52: 16.50256
E53: L'Oreal Travel Retail | F53: External | G53: Loreal Paris | H53: CL0170 L'Oréal Paris (L'OAP) | I53: Shopfitting | J53: =+K53+L53 -> 10.17661 | K53: =SUM(N53:Y53) -> 10.17661 | L53: =SUM(AA53:AL53) -> 0 | Q53: 10.17661
E54: L'Oreal Travel Retail | F54: External | G54: Multi | H54: CL0180 L'Oréal Divers | I54: Shopfitting | J54: =+K54+L54 -> 59.74111 | K54: =SUM(N54:Y54) -> 59.74111 | L54: =SUM(AA54:AL54) -> 0 | Q54: 59.74111
E55: L'Oreal Travel Retail | F55: External | G55: OAP | H55: CL0170 L'Oréal Paris (L'OAP) | I55: Shopfitting | J55: =+K55+L55 -> 8.80696 | K55: =SUM(N55:Y55) -> 8.80696 | L55: =SUM(AA55:AL55) -> 0 | Q55: 8.80696
E56: L'Oreal Travel Retail | F56: External | G56: YSL | H56: CL0310 YSL | I56: Shopfitting | J56: =+K56+L56 -> 30.78518 | K56: =SUM(N56:Y56) -> 30.78518 | L56: =SUM(AA56:AL56) -> 0 | P56: 3.04125 | Q56: 27.74393
E57: Parfums Christian Dior | F57: External | G57: DIOR | H57: CL0090 Dior | I57: Shopfitting | J57: =+K57+L57 -> 494.17683 | K57: =SUM(N57:Y57) -> 494.17683 | L57: =SUM(AA57:AL57) -> 0 | R57: 494.17683
E58: Puig India | F58: External | G58: CH, RB & JPG | H58: CL0840 Puig - other brands | I58: Shopfitting | J58: =+K58+L58 -> 14.850921 | K58: =SUM(N58:Y58) -> 14.850921 | L58: =SUM(AA58:AL58) -> 0 | P58: 14.850921
E59: Rare Beauty LLC | F59: External | G59: Rare Beauty | H59: CL0765 Rare Beauty | I59: Prestige Cosmetic | J59: =+K59+L59 -> 0.52445 | K59: =SUM(N59:Y59) -> 0.52445 | L59: =SUM(AA59:AL59) -> 0 | P59: 0.52445
E60: Reliance Luxe Beauty Limited | F60: External | G60: Rare Beauty | H60: CL0765 Rare Beauty | I60: Prestige Cosmetic | J60: =+K60+L60 -> 48.133015 | K60: =SUM(N60:Y60) -> 48.133015 | L60: =SUM(AA60:AL60) -> 0 | P60: 48.133015
E61: Shoppers Stop Ltd | F61: External | G61: Clinique | H61: CL0075 Clinique | I61: Prestige Cosmetic | J61: =+K61+L61 -> 3.321 | K61: =SUM(N61:Y61) -> 3.321 | L61: =SUM(AA61:AL61) -> 0 | P61: 3.321
E62: Shoppers Stop Ltd | F62: External | G62: ELCA Brand | H62: CL0680 Estée Lauder - other brands | I62: Prestige Cosmetic | J62: =+K62+L62 -> 29.97412 | K62: =SUM(N62:Y62) -> 29.97412 | L62: =SUM(AA62:AL62) -> 0 | Q62: 29.97412
E63: Shoppers Stop Ltd | F63: External | G63: Tom Ford | H63: CL0570 Tom Ford | I63: Shopfitting | J63: =+K63+L63 -> 15.54911 | K63: =SUM(N63:Y63) -> 15.54911 | L63: =SUM(AA63:AL63) -> 0 | P63: 15.54911
J64: =+K64+L64 -> 0 | K64: =SUM(N64:Y64) -> 0 | L64: =SUM(AA64:AL64) -> 0
E68: Deferred revenue balance as on | F68: 46054 | G68: 218 | H68: K Euro
E69: Add: Deferred revenue addition during Feb-26 | G69: 151 | H69: K Euro
E70: Less: Deferred revenue reversed during Feb-26 | G70: 138 | H70: K Euro
E71: Deferred revenue balance as on | F71: 46053 | G71: =G68+G69-G70 -> 231 | H71: K Euro
E74: Brand | H74: Amt. in K Euro
E75: ARMANI | H75: 6.8351132
E76: Chanel | H76: 314.51441
E77: Clarins | H77: 23.319846
E78: Clinique | H78: 97.10112
E79: Coty | H79: 5.840244
E80: DIOR | H80: 494.17683
E81: Dr Jart+ | H81: 11.841945
E82: ELCA Brand | H82: 29.974113
E83: Estee Lauder | H83: 74.32386
E84: Forma | H84: 69.79545
E85: Lancome | H85: 21.212365
E86: Loreal Paris | H86: 1.280056
... E94: YSL | H94: 19.366345
E95: Grand Total | H95: =SUM(H75:H94) -> 1454.8058
H97: All PO( Confirmed & awaiting)
E98: Actual Orderbook of last week | H98: ='W8'!J19 -> 1266.28
E99: New Orders in Current Week | H99: =H95 -> 1454.8058
E100: Sales booked in current week | H100: =J12-'W8'!J12 -> 416.75265
E101: Standard Orderbook should be in Current Week | H101: =H98+H99-H100 -> 2304.3331
E102: Actual Orderbook in Current Week | H102: =J19 -> 2302.9324
E103: Difference | H103: =H101-H102 -> 1.4007076 | I103: Check whether new orders are reported correctly or invoiced order have been removed from the sales dashboard.

Sheet W10
E2: ENTITY NAME : | G2: =+parameters!D2 -> Diam India | I2: ORDER BOOK SYNTHESIS in K€
E4: WEEK : | G4: W10 | I4: Cells to be filled in
E6: MONTH : | G6: =+VLOOKUP(G4, parameters!G:H, 2, 0) -> March
E8: TURNOVER | F8: =parameters!D4 -> k€ | H8: YTD Turnover | J8: =+G6&" Turnover" -> March Turnover | L8: Last estim. for the month: | O8: Forecast 2026
H9: =+"from January 1 until end of "&G4 -> from January 1 until end of W10 | J9: =+"from "&G6&" 1 until end of "&G4 -> from March 1 until end of W10 | L9: =+G6 -> March | O9: =+G4 -> W10 | P9: =+VLOOKUP(G4, parameters!$G$9:$I$61,3,0) -> W9 | Q9: Var
E10: EXTERNAL SALES INVOICED (=outside group) | H10: =600+320+J10 -> 948 | J10: 28 | L10: =J10+P17 -> 598.64263 | O10: =+H10+K17 -> 3282.347 | P10: {=INDIRECT(ADDRESS(10,15,,,VLOOKUP($G$4,parameters!$G:$I,3,0)))} -> 3461.1422 | Q10: =O10-P10 -> -178.79528
E11: GROUP SALES INVOICED | H11: =21+J11 -> 24 | J11: 3 | L11: =J11+P18 -> 4.6097975 | O11: =+H11+K18 -> 32.399943 | P11: {=INDIRECT(ADDRESS(11,15,,,VLOOKUP($G$4,parameters!$G:$I,3,0)))} -> 27.79015 | Q11: =O11-P11 -> 4.609793 | S11: Definition orders : you consider the orders which are sure even if the order customers paper order is not yet received
E12: TOTAL | H12: =SUM(H10:H11) -> 972 | J12: =SUM(J10:J11) -> 31 | L12: =SUM(L10:L11) -> 603.25242 | O12: =SUM(O10:O11) -> 3314.7469 | P12: =SUM(P10:P11) -> 3488.9324 | Q12: =O12-P12 -> -174.18548 | S12: The quantity, value, and delivery date can be changed before final delivery
E16: ORDERBOOK | F16: =+F8 -> k€ | J16: TOTAL ORDERBOOK | K16: Total amount 2026 | L16: Total amount 2027 | N16: 46023 | O16: 46054 | P16: 46082 | Q16: 46113 | R16: 46143 | S16: 46174 | T16: 46204 | U16: 46235 | V16: 46266 | W16: 46296 | X16: 46327 | Y16: 46357 | AA16: 46388 | AB16: 46419 | AC16: 46447 | AD16: 46478 | AE16: 46508 | AF16: 46539 | AG16: 46569 | AH16: 46600 | AI16: 46631 | AJ16: 46661 | AK16: 46692 | AL16: 46722
E17: External | J17: =+SUMIF($F$24:$F$77,"External",$J$24:$J$77) -> 2334.347 | K17: =+SUMIF($F$24:$F$77,"External",$K$24:$K$77) -> 2334.347 | L17: =+SUMIF($F$24:$F$77,"External",$L$24:$L$77) -> 0 | N17: =+SUMIF($F$24:$F$77,"External",N$24:N$77) -> 0 | O17: =+SUMIF($F$24:$F$77,"External",O$24:O$77) -> 0 | P17: =+SUMIF($F$24:$F$77,"External",P$24:P$77) -> 570.64263 | Q17: =+SUMIF($F$24:$F$77,"External",Q$24:Q$77) -> 581.66591 | R17: =+SUMIF($F$24:$F$77,"External",R$24:R$77) -> 564.95642 | S17: =+SUMIF($F$24:$F$77,"External",S$24:S$77) -> 462.32798 | T17: =+SUMIF($F$24:$F$77,"External",T$24:T$77) -> 154.75403 | U17: =+SUMIF($F$24:$F$77,"External",U$24:U$77) -> 0 | ... Y17: =+SUMIF($F$24:$F$77,"External",Y$24:Y$77) -> 0 | AA17: =+SUMIF($F$24:$F$77,"External",AA$24:AA$77) -> 0 | AB17: =+SUMIF($F$24:$F$77,"External",AB$24:AB$77) -> 0 | AC17: =+SUMIF($F$24:$F$77,"External",AC$24:AC$77) -> 0 | AD17: =+SUMIF($F$24:$F$77,"External",AD$24:AD$77) -> 0 | AE17: =+SUMIF($F$24:$F$77,"External",AE$24:AE$77) -> 0 | AF17: =+SUMIF($F$24:$F$77,"External",AF$24:AF$77) -> 0 | AG17: =+SUMIF($F$24:$F$77,"External",AG$24:AG$77) -> 0 | AH17: =+SUMIF($F$24:$F$77,"External",AH$24:AH$77) -> 0 | ... AL17: =+SUMIF($F$24:$F$77,"External",AL$24:AL$77) -> 0
E18: Group | J18: =+SUMIF($F$24:$F$77,"Group",$J$24:$J$77) -> 8.399943 | K18: =+SUMIF($F$24:$F$77,"Group",$K$24:$K$77) -> 8.399943 | L18: =SUMIF($F$24:$F$77,"Group",$L$24:$L$77) -> 0 | N18: =+SUMIF($F$24:$F$77,"Group",N$24:N$77) -> 0 | O18: =+SUMIF($F$24:$F$77,"Group",O$24:O$77) -> 0 | P18: =+SUMIF($F$24:$F$77,"Group",P$24:P$77) -> 1.6097975 | Q18: =+SUMIF($F$24:$F$77,"Group",Q$24:Q$77) -> 6.7901454 | R18: =+SUMIF($F$24:$F$77,"Group",R$24:R$77) -> 0 | S18: =+SUMIF($F$24:$F$77,"Group",S$24:S$77) -> 0 | T18: =+SUMIF($F$24:$F$77,"Group",T$24:T$77) -> 0 | U18: =+SUMIF($F$24:$F$77,"Group",U$24:U$77) -> 0 | ... Y18: =+SUMIF($F$24:$F$77,"Group",Y$24:Y$77) -> 0 | AA18: =+SUMIF($F$24:$F$77,"Group",AA$24:AA$77) -> 0 | AB18: =+SUMIF($F$24:$F$77,"Group",AB$24:AB$77) -> 0 | AC18: =+SUMIF($F$24:$F$77,"Group",AC$24:AC$77) -> 0 | AD18: =+SUMIF($F$24:$F$77,"Group",AD$24:AD$77) -> 0 | AE18: =+SUMIF($F$24:$F$77,"Group",AE$24:AE$77) -> 0 | AF18: =+SUMIF($F$24:$F$77,"Group",AF$24:AF$77) -> 0 | AG18: =+SUMIF($F$24:$F$77,"Group",AG$24:AG$77) -> 0 | AH18: =+SUMIF($F$24:$F$77,"Group",AH$24:AH$77) -> 0 | ... AL18: =+SUMIF($F$24:$F$77,"Group",AL$24:AL$77) -> 0
E19: TOTAL | J19: =SUM(J17:J18) -> 2342.7469 | K19: =SUM(K17:K18) -> 2342.7469 | L19: =SUM(L17:L18) -> 0 | N19: =SUM(N17:N18) -> 0 | O19: =SUM(O17:O18) -> 0 | P19: =SUM(P17:P18) -> 572.25242 | Q19: =SUM(Q17:Q18) -> 588.45606 | R19: =SUM(R17:R18) -> 564.95642 | S19: =SUM(S17:S18) -> 462.32798 | T19: =SUM(T17:T18) -> 154.75403 | U19: =SUM(U17:U18) -> 0 | ... Y19: =SUM(Y17:Y18) -> 0 | AA19: =SUM(AA17:AA18) -> 0 | AB19: =SUM(AB17:AB18) -> 0 | AC19: =SUM(AC17:AC18) -> 0 | AD19: =SUM(AD17:AD18) -> 0 | AE19: =SUM(AE17:AE18) -> 0 | AF19: =SUM(AF17:AF18) -> 0 | AG19: =SUM(AG17:AG18) -> 0 | AH19: =SUM(AH17:AH18) -> 0 | ... AL19: =SUM(AL17:AL18) -> 0
I21: check | J21: =IF(SUM(J24:J77)=J19, "OK", "Please correct: the sum of orders below is not equal to the total calculated above. Make sure to pick External or Group for each order and don't change the formulas in columns K and L") -> OK | N21: 2026 | AA21: 2027
E23: Customer Name | F23: External or Group | G23: Brand | H23: Outgroup | I23: Segment | J23: TOTAL ORDERBOOK | K23: Total amount 2026 | L23: Total amount 2027 | N23: 46023 | O23: 46054 | P23: 46082 | Q23: 46113 | R23: 46143 | S23: 46174 | T23: 46204 | U23: 46235 | V23: 46266 | W23: 46296 | X23: 46327 | Y23: 46357 | AA23: 46388 | AB23: 46419 | AC23: 46447 | AD23: 46478 | AE23: 46508 | AF23: 46539 | AG23: 46569 | AH23: 46600 | AI23: 46631 | AJ23: 46661 | AK23: 46692 | AL23: 46722
D24: X | E24: BACCAROSE PERFUMES AND BEAUTY PRODUCTS PVT LTD | F24: External | G24: Gucci | H24: CL0920 Coty - other brands | I24: Shopfitting | J24: =+K24+L24 -> 1.52838 | K24: =SUM(N24:Y24) -> 1.52838 | L24: =SUM(AA24:AL24) -> 0 | P24: 1.52838
E25: BACCAROSE PERFUMES AND BEAUTY PRODUCTS PVT LTD | F25: External | G25: Laura Mercier | H25: CL0540 Laura Mercier | I25: Prestige Cosmetic | J25: =+K25+L25 -> 7.2617511 | K25: =SUM(N25:Y25) -> 7.2617511 | L25: =SUM(AA25:AL25) -> 0 | Q25: 7.2617511
E26: BACCAROSE PERFUMES AND BEAUTY PRODUCTS PVT LTD | F26: External | G26: Shiseido | H26: CL0285 Shiseido | I26: Prestige Cosmetic | J26: =+K26+L26 -> 19.0875 | K26: =SUM(N26:Y26) -> 19.0875 | L26: =SUM(AA26:AL26) -> 0 | P26: 19.0875
E27: Beauty Impex Pvt. Ltd | F27: External | G27: Guerlain | H27: CL0130 Guerlain | I27: Prestige Cosmetic | J27: =+K27+L27 -> 7.1369106 | K27: =SUM(N27:Y27) -> 7.1369106 | L27: =SUM(AA27:AL27) -> 0 | P27: 7.1369106
E28: Best In Brands | F28: External | G28: Shiseido | H28: CL0285 Shiseido | I28: Prestige Cosmetic | J28: =+K28+L28 -> 8.0682141 | K28: =SUM(N28:Y28) -> 8.0682141 | L28: =SUM(AA28:AL28) -> 0 | P28: 8.0682141
E29: CHANEL INDIA | F29: External | G29: Chanel | H29: CL0065 Chanel | I29: Shopfitting | J29: =+K29+L29 -> 314.44096 | K29: =SUM(N29:Y29) -> 314.44096 | L29: =SUM(AA29:AL29) -> 0 | Q29: 38.805264 | S29: 275.63569
E30: Clarins Pte Ltd | F30: External | G30: Clarins | H30: CL0070 Clarins | I30: Shopfitting | J30: =+K30+L30 -> 22.776105 | K30: =SUM(N30:Y30) -> 22.776105 | L30: =SUM(AA30:AL30) -> 0 | S30: 22.776105
E31: Connectiv FZCO | F31: External | G31: L'Oreal TR | H31: CL0180 L'Oréal Divers | I31: Shopfitting | J31: =+K31+L31 -> 0.0137693 | K31: =SUM(N31:Y31) -> 0.0137693 | L31: =SUM(AA31:AL31) -> 0 | P31: 0.0137693
E32: Coty | F32: External | G32: Coty | H32: CL0920 Coty - other brands | I32: Shopfitting | J32: =+K32+L32 -> 4.0679743 | K32: =SUM(N32:Y32) -> 4.0679743 | L32: =SUM(AA32:AL32) -> 0 | P32: 4.0679743
E33: Coty | F33: External | G33: Kylie | H33: CL0705 Coty KJ | I33: Shopfitting | J33: =+K33+L33 -> 0 | K33: =SUM(N33:Y33) -> 0 | L33: =SUM(AA33:AL33) -> 0
E34: DDS | F34: Group | G34: Coty | H34: CL0920 Coty - other brands | I34: Shopfitting | J34: =+K34+L34 -> 6.7901454 | K34: =SUM(N34:Y34) -> 6.7901454 | L34: =SUM(AA34:AL34) -> 0 | Q34: 6.7901454
E35: DDS | F35: Group | G35: Kylie | H35: CL0705 Coty KJ | I35: Shopfitting | J35: =+K35+L35 -> -0.053305104 | K35: =SUM(N35:Y35) -> -0.053305104 | L35: =SUM(AA35:AL35) -> 0 | P35: -0.053305104
E36: DDS | F36: Group | G36: The Macallan | H36: CL0870 The Macallan | I36: Shopfitting | J36: =+K36+L36 -> 0 | K36: =SUM(N36:Y36) -> 0 | L36: =SUM(AA36:AL36) -> 0
E37: DIAM Turkey | F37: Group | G37: Fenty Beauty | H37: CL0550 Kendo - Fenty | I37: Prestige Cosmetic | J37: =+K37+L37 -> 1.6631026 | K37: =SUM(N37:Y37) -> 1.6631026 | L37: =SUM(AA37:AL37) -> 0 | P37: 1.6631026
E38: ELCA Cosmetics Pvt. Ltd. | F38: External | G38: Too Faced | H38: CL0575 Too Faced | I38: Prestige Cosmetic | J38: =+K38+L38 -> 39.364556 | K38: =SUM(N38:Y38) -> 39.364556 | L38: =SUM(AA38:AL38) -> 0 | P38: 1 | R38: 13.62978 | S38: 23.734776 | T38: 1
E39: ELCA Cosmetics Pvt. Ltd. | F39: External | G39: Clinique | H39: CL0075 Clinique | I39: Prestige Cosmetic | J39: =+K39+L39 -> 126.31474 | K39: =SUM(N39:Y39) -> 126.31474 | L39: =SUM(AA39:AL39) -> 0 | P39: 52.143363 | R39: 34.13494 | S39: 28.47144 | T39: 11.564993
E40: ELCA Cosmetics Pvt. Ltd. | F40: External | G40: Dr Jart+ | H40: CL0680 Estée Lauder - other brands | I40: Prestige Cosmetic | J40: =+K40+L40 -> 14.079619 | K40: =SUM(N40:Y40) -> 14.079619 | L40: =SUM(AA40:AL40) -> 0 | P40: 8.9332506 | Q40: 2.9518385 | R40: 2.1945298
E41: ELCA Cosmetics Pvt. Ltd. | F41: External | G41: Estee Lauder | H41: CL0110 Estée Lauder | I41: Prestige Cosmetic | J41: =+K41+L41 -> 106.88296 | K41: =SUM(N41:Y41) -> 106.88296 | L41: =SUM(AA41:AL41) -> 0 | P41: 56.049188 | R41: 11.78504 | S41: 8.24186 | T41: 30.806873
E42: ELCA Cosmetics Pvt. Ltd. | F42: External | G42: Mac | H42: CL0395 MAC | I42: Prestige Cosmetic | J42: =+K42+L42 -> 151.32968 | K42: =SUM(N42:Y42) -> 151.32968 | L42: =SUM(AA42:AL42) -> 0 | P42: 33.404071 | R42: 9.035297 | S42: 79.69962 | T42: 29.190693
E43: ELCA Cosmetics Pvt. Ltd. | F43: External | G43: Smashbox | H43: CL0525 Smashbox | I43: Prestige Cosmetic | J43: =+K43+L43 -> 90.961298 | K43: =SUM(N43:Y43) -> 90.961298 | L43: =SUM(AA43:AL43) -> 0 | P43: 5.1083898 | S43: 5.946939 | T43: 79.905969
E44: ELCA Cosmetics Pvt. Ltd. | F44: External | G44: The Ordinary | H44: CL0680 Estée Lauder - other brands | I44: Prestige Cosmetic | J44: =+K44+L44 -> 43.856668 | K44: =SUM(N44:Y44) -> 43.856668 | L44: =SUM(AA44:AL44) -> 0 | P44: 24.528098 | S44: 17.82155 | T44: 1.50702
E45: ELCA Cosmetics Pvt. Ltd. | F45: External | G45: Tom Ford | H45: CL0570 Tom Ford | I45: Prestige Cosmetic | J45: =+K45+L45 -> 36.94664 | K45: =SUM(N45:Y45) -> 36.94664 | L45: =SUM(AA45:AL45) -> 0 | P45: 26.408163 | Q45: 9.76 | T45: 0.7784776
E46: Estee Lauder AG Lachen | F46: External | G46: Jo Malone | H46: CL0535 Joe Malone | I46: Prestige Cosmetic | J46: =+K46+L46 -> 0 | K46: =SUM(N46:Y46) -> 0 | L46: =SUM(AA46:AL46) -> 0
E47: Estee Lauder Middle East FZE | F47: External | G47: Too Faced | H47: CL0575 Too Faced | I47: Prestige Cosmetic | J47: =+K47+L47 -> 155.09714 | K47: =SUM(N47:Y47) -> 155.09714 | L47: =SUM(AA47:AL47) -> 0 | Q47: 155.09714
E48: Estee Lauder Saudi Limited | F48: External | G48: Clinique | H48: CL0075 Clinique | I48: Prestige Cosmetic | J48: =+K48+L48 -> 3.5708258 | K48: =SUM(N48:Y48) -> 3.5708258 | L48: =SUM(AA48:AL48) -> 0 | P48: 3.5708258
E49: Exclusive Lines | F49: External | G49: Lancome | H49: CL0155 Lancôme | I49: Shopfitting | J49: =+K49+L49 -> 18.976251 | K49: =SUM(N49:Y49) -> 18.976251 | L49: =SUM(AA49:AL49) -> 0 | P49: 18.976251
E50: Fenty Beauty LLC | F50: External | G50: Fenty Beauty | H50: CL0550 Kendo - Fenty | I50: Prestige Cosmetic | J50: =+K50+L50 -> 9.0120765 | K50: =SUM(N50:Y50) -> 9.0120765 | L50: =SUM(AA50:AL50) -> 0 | P50: 9.0120765
E51: Forma Brands, LLC f/k/a FB Acquisition LLC | F51: External | G51: Forma | H51: CL0735 Morphe | I51: Prestige Cosmetic | J51: =+K51+L51 -> 99.980337 | K51: =SUM(N51:Y51) -> 99.980337 | L51: =SUM(AA51:AL51) -> 0 | Q51: 99.980337
E52: Global Shoppers Stop Beauty Brands Ltd | F52: External | G52: Clarins | H52: CL0070 Clarins | I52: Prestige Cosmetic | J52: =+K52+L52 -> 0.15506 | K52: =SUM(N52:Y52) -> 0.15506 | L52: =SUM(AA52:AL52) -> 0 | P52: 0.15506
E53: Global Shoppers Stop Beauty Brands Ltd | F53: External | G53: Clarins | H53: CL0070 Clarins | I53: Shopfitting | J53: =+K53+L53 -> 0 | K53: =SUM(N53:Y53) -> 0 | L53: =SUM(AA53:AL53) -> 0
E54: Global Shoppers Stop Beauty Brands Ltd | F54: External | G54: Maison Margiela | H54: CL0180 L'Oréal Divers | I54: Shopfitting | J54: =+K54+L54 -> 0 | K54: =SUM(N54:Y54) -> 0 | L54: =SUM(AA54:AL54) -> 0
E55: Global Shoppers Stop Beauty Brands Ltd | F55: External | G55: Nars | H55: CL0226 Nars | I55: Prestige Cosmetic | J55: =+K55+L55 -> 119.27898 | K55: =SUM(N55:Y55) -> 119.27898 | L55: =SUM(AA55:AL55) -> 0 | P55: 86.176078 | Q55: 33.102907
E56: Global Shoppers Stop Beauty Brands Ltd | F56: External | G56: Prada | H56: CL0180 L'Oréal Divers | I56: Shopfitting | J56: =+K56+L56 -> 16.673766 | K56: =SUM(N56:Y56) -> 16.673766 | L56: =SUM(AA56:AL56) -> 0 | Q56: 16.673766
E57: Indosing Distribution | F57: External | G57: Benefit | H57: CL0315 Benefit | I57: Prestige Cosmetic | J57: =+K57+L57 -> 23.332403 | K57: =SUM(N57:Y57) -> 23.332403 | L57: =SUM(AA57:AL57) -> 0 | P57: 23.332403
E58: L Beauty Pte | F58: External | G58: Benefit | H58: CL0315 Benefit | I58: Prestige Cosmetic | J58: =+K58+L58 -> 47.250297 | K58: =SUM(N58:Y58) -> 47.250297 | L58: =SUM(AA58:AL58) -> 0 | P58: 20.282065 | Q58: 26.968231
E59: L'Oreal India | F59: External | G59: Lancome | H59: CL0155 Lancôme | I59: Prestige Cosmetic | J59: =+K59+L59 -> 18.588231 | K59: =SUM(N59:Y59) -> 18.588231 | L59: =SUM(AA59:AL59) -> 0 | P59: 11.602918 | Q59: 6.9853122
E60: L'Oreal India | F60: External | G60: Lancome | H60: CL0155 Lancôme | I60: Shopfitting | J60: =+K60+L60 -> 10.820262 | K60: =SUM(N60:Y60) -> 10.820262 | L60: =SUM(AA60:AL60) -> 0 | P60: 10.820262
E61: L'Oreal India | F61: External | G61: YSL | H61: CL0310 YSL | I61: Shopfitting | J61: =+K61+L61 -> 14.355403 | K61: =SUM(N61:Y61) -> 14.355403 | L61: =SUM(AA61:AL61) -> 0 | P61: 14.355403
E62: L'Oreal Travel Retail | F62: External | G62: Armani | H62: CL0345 Armani | I62: Shopfitting | J62: =+K62+L62 -> 37.943177 | K62: =SUM(N62:Y62) -> 37.943177 | L62: =SUM(AA62:AL62) -> 0 | P62: 6.8090946 | Q62: 31.134083
E63: L'Oreal Travel Retail | F63: External | G63: ARMANI PRIVE | H63: CL0345 Armani | I63: Shopfitting | J63: =+K63+L63 -> 0 | K63: =SUM(N63:Y63) -> 0 | L63: =SUM(AA63:AL63) -> 0
E64: L'Oreal Travel Retail | F64: External | G64: Lancome | H64: CL0155 Lancôme | I64: Shopfitting | J64: =+K64+L64 -> 16.502558 | K64: =SUM(N64:Y64) -> 16.502558 | L64: =SUM(AA64:AL64) -> 0 | Q64: 16.502558
E65: L'Oreal Travel Retail | F65: External | G65: Loreal Paris | H65: CL0170 L'Oréal Paris (L'OAP) | I65: Shopfitting | J65: =+K65+L65 -> 10.176609 | K65: =SUM(N65:Y65) -> 10.176609 | L65: =SUM(AA65:AL65) -> 0 | Q65: 10.176609
E66: L'Oreal Travel Retail | F66: External | G66: Multi | H66: CL0180 L'Oréal Divers | I66: Shopfitting | J66: =+K66+L66 -> 59.741114 | K66: =SUM(N66:Y66) -> 59.741114 | L66: =SUM(AA66:AL66) -> 0 | Q66: 59.741114
E67: L'Oreal Travel Retail | F67: External | G67: OAP | H67: CL0170 L'Oréal Paris (L'OAP) | I67: Shopfitting | J67: =+K67+L67 -> 8.8069593 | K67: =SUM(N67:Y67) -> 8.8069593 | L67: =SUM(AA67:AL67) -> 0 | Q67: 8.8069593
E68: L'Oreal Travel Retail | F68: External | G68: RALPH LAUREN | H68: CL0405 Ralph Lauren | I68: Shopfitting | J68: =+K68+L68 -> 0 | K68: =SUM(N68:Y68) -> 0 | L68: =SUM(AA68:AL68) -> 0
E69: L'Oreal Travel Retail | F69: External | G69: YSL | H69: CL0310 YSL | I69: Shopfitting | J69: =+K69+L69 -> 30.785181 | K69: =SUM(N69:Y69) -> 30.785181 | L69: =SUM(AA69:AL69) -> 0 | P69: 3.0412531 | Q69: 27.743928
E70: Parfums Christian Dior | F70: External | G70: DIOR | H70: CL0090 Dior | I70: Shopfitting | J70: =+K70+L70 -> 494.17683 | K70: =SUM(N70:Y70) -> 494.17683 | L70: =SUM(AA70:AL70) -> 0 | R70: 494.17683
E71: Puig India | F71: External | G71: CH, RB & JPG | H71: CL0840 Puig - other brands | I71: Shopfitting | J71: =+K71+L71 -> 41.48435 | K71: =SUM(N71:Y71) -> 41.48435 | L71: =SUM(AA71:AL71) -> 0 | P71: 41.48435
E72: Rare Beauty LLC | F72: External | G72: Rare Beauty | H72: CL0765 Rare Beauty | I72: Prestige Cosmetic | J72: =+K72+L72 -> 8.4427269 | K72: =SUM(N72:Y72) -> 8.4427269 | L72: =SUM(AA72:AL72) -> 0 | P72: 8.4427269
E73: Reliance Luxe Beauty Limited | F73: External | G73: Rare Beauty | H73: CL0765 Rare Beauty | I73: Prestige Cosmetic | J73: =+K73+L73 -> 46.234476 | K73: =SUM(N73:Y73) -> 46.234476 | L73: =SUM(AA73:AL73) -> 0 | P73: 46.234476
E74: Shoppers Stop Ltd | F74: External | G74: Clinique | H74: CL0075 Clinique | I74: Prestige Cosmetic | J74: =+K74+L74 -> 3.321 | K74: =SUM(N74:Y74) -> 3.321 | L74: =SUM(AA74:AL74) -> 0 | P74: 3.321
E75: Shoppers Stop Ltd | F75: External | G75: ELCA Brand | H75: CL0680 Estée Lauder - other brands | I75: Prestige Cosmetic | J75: =+K75+L75 -> 29.974113 | K75: =SUM(N75:Y75) -> 29.974113 | L75: =SUM(AA75:AL75) -> 0 | Q75: 29.974113
E76: Shoppers Stop Ltd | F76: External | G76: Tom Ford | H76: CL0570 Tom Ford | I76: Shopfitting | J76: =+K76+L76 -> 15.549113 | K76: =SUM(N76:Y76) -> 15.549113 | L76: =SUM(AA76:AL76) -> 0 | P76: 15.549113
J77: =+K77+L77 -> 0 | K77: =SUM(N77:Y77) -> 0 | L77: =SUM(AA77:AL77) -> 0
E79: Deferred revenue balance as on | F79: 46054 | G79: 231 | H79: K Euro
E80: Add: Deferred revenue addition during Feb-26 | G80: 348 | H80: K Euro
E81: Less: Deferred revenue reversed during Feb-26 | G81: 151 | H81: K Euro
E82: Deferred revenue balance as on | F82: 46081 | G82: 428 | H82: K Euro
E84: Brand | H84: Amt. in K Euro
E85: CH, RB & JPG | H85: 26.633429
E86: Clarins | H86: 0.58465304
E87: Clinique | H87: 10.368241
E88: Coty | H88: 3.4125442
E89: Estee Lauder | H89: 3.985475
E90: Fenty Beauty | H90: 10.662267
E91: Gucci | H91: 1.52838
E92: Mac | H92: 1.1915029
E93: Rare Beauty | H93: 6.0195795
E94: Smashbox | H94: 3.471608
E96: Grand Total | H96: =SUM(H85:H95) -> 67.85768
H98: All PO( Confirmed & awaiting)
E99: Actual Orderbook of last week | H99: ='W9'!J19 -> 2302.9324
E100: New Orders in Current Week | H100: =H96 -> 67.85768
E101: Sales booked in current week | H101: =J12 -> 31
E102: Standard Orderbook should be in Current Week | H102: =H99+H100-H101 -> 2339.7901
E103: Actual Orderbook in Current Week | H103: =J19 -> 2342.7469
E104: Difference | H104: =H102-H103 -> -2.9568363 | I104: Check whether new orders are reported correctly or invoiced order have been removed from the sales dashboard.

Sheet W11
E2: ENTITY NAME : | G2: =+parameters!D2 -> Diam India | I2: ORDER BOOK SYNTHESIS in K€
E4: WEEK : | G4: W11 | I4: Cells to be filled in
E6: MONTH : | G6: =+VLOOKUP(G4, parameters!G:H, 2, 0) -> March
E8: TURNOVER | F8: =parameters!D4 -> k€ | H8: YTD Turnover | J8: =+G6&" Turnover" -> March Turnover | L8: Last estim. for the month: | O8: Forecast 2026
H9: =+"from January 1 until end of "&G4 -> from January 1 until end of W11 | J9: =+"from "&G6&" 1 until end of "&G4 -> from March 1 until end of W11 | L9: =+G6 -> March | O9: =+G4 -> W11 | P9: =+VLOOKUP(G4, parameters!$G$9:$I$61,3,0) -> W10 | Q9: Var
E10: EXTERNAL SALES INVOICED (=outside group) | H10: =600+320+J10 -> 995 | J10: 75 | L10: =J10+P17 -> 878.48511 | O10: =+H10+K17 -> 3984.6456 | P10: {=INDIRECT(ADDRESS(10,15,,,VLOOKUP($G$4,parameters!$G:$I,3,0)))} -> 3282.347 | Q10: =O10-P10 -> 702.2986
E11: GROUP SALES INVOICED | H11: =21+J11 -> 24 | J11: 3 | L11: =J11+P18 -> 4.6098 | O11: =+H11+K18 -> 32.39995 | P11: {=INDIRECT(ADDRESS(11,15,,,VLOOKUP($G$4,parameters!$G:$I,3,0)))} -> 32.399943 | Q11: =O11-P11 -> 7.0422e-06 | S11: Definition orders : you consider the orders which are sure even if the order customers paper order is not yet received
E12: TOTAL | H12: =SUM(H10:H11) -> 1019 | J12: =SUM(J10:J11) -> 78 | L12: =SUM(L10:L11) -> 883.09491 | O12: =SUM(O10:O11) -> 4017.0455 | P12: =SUM(P10:P11) -> 3314.7469 | Q12: =O12-P12 -> 702.29861 | S12: The quantity, value, and delivery date can be changed before final delivery
